Workbook

Sheet Master Tab
A1: Dairy_Annual_Report | F1: 22 AR Status | G1: Note | H1: APN Correct?
A2: A & M De Souza Dairy | F2: Y | G2: No Staff was assigned to this facility | H2: No
A3: Silva Dairy Farms #3A | F3: Y | G3: merged with Silva Dairy Farms #3B | H3: Yes
A4: Joe Borba Dairy Inc. | F4: Y | H4: No
A5: Ken Van Foeken Dairy #2 | F5: Y | H5: Yes
A6: Da Rosa Dairy | F6: Y | G6: under Dan's name | H6: Yes
A7: J_D Brasil Dairy | F7: Y | H7: Yes
A8: River Rock Ranch LLC | F8: Y | H8: Yes
A9: Double Cross #3 | F9: Y | H9: Yes
A10: Edward Nunes Dairy | F10: Y | G10: under Charles's name (It was uploaded to GT, np) | H10: Yes
A11: Gomes Dairy | F11: Y | H11: Yes
A12: Roest Family Dairy | F12: Y | H12: Yes
A13: Gil Tex Dairy | F13: Y | G13: Missing Signature | H13: No
A14: GJ Silva | F14: Y | G14: G J Silva #3 is merged with this dairy | H14: No | J14: N# of Non-Filer | K14: =COUNTIF(F2:F144, "N") -> 3
A15: Hilmar Holsteins Inc. | F15: Y | H15: Yes | J15: N# of Filer | K15: =COUNTIF(F2:F144, "Y") -> 131
A16: Jordao Dairy | F16: Y | G16: under Sean's name | H16: Yes
A17: Cross Creek Dairy | F17: Y | H17: Yes
A18: Double Cross #2 | F18: Y | H18: Yes
A19: LarryPetersonDairyFarms#2 | F19: Y | G19: under Dan's name | H19: Yes
A20: Fire_Lake Jerseys #2 | F20: Y | H20: No
A21: Lumar Dairy Farms | F21: Y | H21: Yes
A22: CMA Livestock | F22: Y | H22: Yes
A23: Fire Lakes Jerseys | F23: Y | G23: under Sean's name | H23: Yes
A24: Rick Jones Farms | F24: Y | H24: Yes
A25: Silveira Holsteins | F25: Y | H25: Yes
A26: Diamond B Dairy | F26: Y | H26: Yes
A27: Azevedo Dairy | F27: Y | H27: Yes
A28: Valsigna Dairy | F28: Y | H28: Yes
A29: WickstromJerseyFarmsInc. | F29: Y | H29: Yes
A30: Diniz Dairy | F30: Y | H30: Yes
A31: Crane Dairy Inc. | F31: Y | H31: Yes
A32: GM Silva Dairies #2 | F32: Y | H32: Yes
A33: Joe Oliveira Dairy | F33: Y | H33: Yes
A34: Vierra Dairy Farms #3 | F34: Y | H34: Yes
A35: Nelson Dairy | F35: Y | H35: Yes
... A41: T & M Borba Dairy | F41: Y | H41: Yes
A42: Oslo Dairy | F42: Y | H42: No | I42: Not signed
A43: Kronberg Facility | F43: Y | H43: Yes
A44: Ken Van Foeken Dairy | F44: Y | H44: Yes
A45: Amaral Dairy Farms | F45: Y | G45: John Avila confirmed that he will be sending AR in a week or 2 | H45: Yes
A46: B_6 Dairy | F46: Y | H46: Yes
A47: 6D Dores Dairy | F47: Y | H47: Yes
A48: Fanelli Dairy | F48: Y | H48: Yes
A49: Joao Sousa Dairy | F49: Y | H49: Yes
A50: Vierra Dairy Farms #2 | F50: Y | H50: Yes
A51: Michael Brasil Dairy | F51: Y | H51: Yes
A52: Anchor J Dairy | F52: Y | H52: Yes
A53: Oliveira Dairy | F53: Y | H53: Yes
A54: Souza Bros Dairy | F54: Y | H54: Yes
A55: Miguel Family Dairy | F55: Y | H55: Yes
A56: Dias Family Dairy | F56: Y | H56: Yes
A57: Empty was A_D Dairy | F57: HISTORICAL
A58: Michael Brasil Dairy #2 | F58: Y | H58: Yes
A59: F & A Lemos Dairy | F59: Y | G59: Called Owner at 209-632-7291, transferred to his assistant that confirmed that she will let Mr. Lemos know that he needs to submit 2022 AR | H59: No
A60: Alves & Son Dairy #2 | F60: Y | H60: Yes
A61: Golf Link RanchesLLC | F61: Y | H61: Yes
A62: Triple M Jerseys | F62: Y | H62: Yes
A63: Jose & Teresa Soares Dairy | F63: Y | H63: Yes
A64: MachadoGabriel&SonsDairy | F64: Y | H64: Yes
A65: Hawkins Ranch | F65: Y | G65: No Staff was assigned to this facility. | H65: Yes
A66: Silva Dairy Farms #3B | F66: Y | G66: under Dan's name | I66: Merged with 1499 edminster rd
A67: AhlemFarmsPartnership | F67: Y | H67: Yes
A68: Vierra Dairy Farms #4 | F68: Y | H68: Yes
A69: CaliforniaDairyFarms LLC | F69: Y | H69: Yes
A70: Larry Peterson Dairy | F70: Y | H70: Yes
A71: Joe Egli&Sons Dairy | F71: Y | H71: Yes
A72: CMA Livestock #2 | F72: Y | H72: Yes
A73: Valentine Dairy | F73: Y | H73: Yes
A74: CMC Jerseys LLC | F74: Y | H74: Yes
A75: Fanelli_Fanelli Brothers | F75: Y | H75: Yes
A76: Martins Bros Dairy | F76: Y | H76: No
A77: Gomes Heifer Ranch | F77: Y | G77: No staff was assigned to this facility | H77: No
A78: Ed Hirdes Dairy | F78: HISTORICAL
A79: Dematos Dairy | F79: Y | G79: under Gilberto's name | H79: Yes
A80: Carlos Estacio&Sons Dairy | F80: N | G80: Called Tony Esctacio at 209-678-2088 and left a message regarding 2021 & 2022 Ars/ based on Tony the Phone number to contact is 209-678-3801
A81: Live Oak Dairy G | F81: Y | G81: under Sean's name | H81: No
A82: Verissimo Facility | F82: Y | H82: Yes
A83: Double Cross Dairy | F83: Y | G83: no staff was assigned to this facility/ AR is combined with Charles Ahlem Ranch at 23546 W American Ave | H83: Yes
A84: Double Cross #4 | F84: Y | H84: Yes
A85: King Dairy | F85: Y | H85: Yes
A86: Vieira Livestock | F86: Y | H86: Yes
A87: AldenPeterson&SonsDairy Inc. | F87: Y | H87: Yes
A88: John Nunes Dairy #3 | F88: N | G88: Called Mr. Silva Paulo at 209 417 2822 and left a message
A89: Roestar Dairy | F89: Y | G89: under Charles's name | H89: Yes
A90: Luis M. Azevedo Dairy | F90: Y | G90: Mr. Azevedo at 209 216 7785 | H90: No
A91: Arlinda Holsteins | F91: Y | H91: Yes
A92: Robert Gioletti & Sons Dairy | F92: Y | G92: Under Bryan's Name | H92: Yes
A93: Carl Vieira Dairy | F93: Y | H93: Yes
A94: John Brasil & Sons Dairy | F94: Y | H94: Yes
A95: John Brasil Dairy #3 | F95: Y | H95: Yes
A96: KMA Dairy | F96: P | G96: Mr. Azevado Phone 209 216 7785
A97: Sallaberry Ranch | F97: Y | G97: no staff assigned | H97: Yes
A98: Alfred C Nunes Dairy | F98: Y | H98: No
A99: Jim Vieira & Son Dairy | F99: Y | H99: Yes
A100: Ehrlich Dairy | F100: Y | H100: Yes
A101: D&A Brasil Facility | F101: HISTORICAL
A102: Silva's Holsteins | F102: Y | H102: Yes
A103: G J Silva #3 | G103: Merged with G. J. Silva Dairy, Inc, the facility ID based on CIWQS is 227211/Address 3107 S Prairie Flower Rd
A104: Jim Vieira and Son Dairy #2 | F104: Y | H104: Yes
A105: Johal Dairy | F105: Y | H105: Yes
...

Sheet Dairy_Annual_Report
A1: REGION | B1: FACILITY ID | C1: FACILITY NAME | D1: PLACE TYPE | E1: PLACE SUBTYPE | F1: FACILITY TYPE | G1: AGENCY NAME | H1: AGENCY TYPE | I1: PLACE ADDRESS | J1: PLACE CITY | K1: PLACE ZIP | L1: PLACE COUNTY | M1: LATITUDE DECIMAL DEGREES | N1: LONGITUDE DECIMAL DEGREES | O1: SIC DESC 1 | P1: NAICS DESC 1 | Q1: PROGRAM | R1: PROGRAM CATEGORY | S1: WDID | T1: REG MEASURE ID | U1: REG MEASURE TYPE | V1: REG MEASURE TITLE | W1: REG MEASURE DESCRIPTION | X1: ORDER # | Y1: STATUS | Z1: STATUS DATE | AA1: EFFECTIVE DATE | AB1: EXPIRATION/REVIEW DATE | AC1: FEE CODE | AD1: STAFF ASSIGNED | AE1: # OF STAFF ASSIGNED | AF1: APPLICATION FEE AMT RECEIVED | AG1: CAFO SUBTYPE | AH1: CAFO TYPE | AI1: CAFO POPULATION | AJ1: QUALITY ASSURANCE | AK1: Animal Equivalent Units (AEU) | AL1: AR Recieve Date | AM1: Consultant | AN1: Signature | AO1: OwnOp = CIWQS | AP1: Milk Cows | AQ1: Dry Cows | AR1: Bred Heifers 15-24 mo | AS1: Heifers 7-14 mo | AT1: Calves 4-6 mo | AU1: Calves 0-3 mo | AV1: Mature Herd Size | AW1: Max Allowed Herd Size | AX1: Billing Change | AY1: Expansion | AZ1: WW Exports | BA1: Manure Exports | BB1: Manure Manifests | BC1: Imports | BD1: Total Acreage | BE1: Missing Harvest Data | BF1: Low Water Application | BG1: High Harvest N Data | BH1: Low Harvest Rates | BI1: High N Ratio | BJ1: Domestic Wells w/ N-NO3 > 10 | BK1: GW lab samples | BL1: Missing Manure Samples | BM1: Missing Wastewater Samples | BN1: Revised Site Plans | BO1: Additional Notes/Concerns
A2: 5S | B2: 203907 | C2: A & M De Souza Dairy | D2: Growing | E2: Animal Feeding | F2: Agricultural | G2: De Sousa, Armelin & Maria | H2: Privately-Owned Business | I2: 3030 South Central Avenue | J2: Turlock | K2: 95380 | L2: Stanislaus | M2: 37.46564 | N2: -120.95585 | O2: Dairy Farms | P2: Dairy Cattle and Milk Production | Q2: ANIWSTCOWS | R2: ANIMALWASTE | S2: 5B50NC00226 | T2: 335259 | U2: Enrollee - WDR | V2: Enrollee Under Dairy GO for De Sousa, Armelin & Maria - A & M De Souza Dairy | X2: R5-2013-0122 | Y2: Active | Z2: 42181 | AA2: 39262 | AB2: 10/02/2018 | AC2: 10 - Confined animal feeding facility | AD2: Lamyae Zinebi | AE2: 1 | AF2: 2725 | AG2: Mature dairy cattle | AH2: Dairies | AI2: 1539 | AJ2: N
A3: 5S | B3: 209495 | C3: Silva Dairy Farms #3A | D3: Growing | E3: Animal Feeding | F3: Agricultural | G3: Silva, Manuel | H3: Privately-Owned Business | I3: 1499 North Edminster Road | J3: Stevinson | K3: 95374 | L3: Merced | M3: 37.311085 | N3: -120.89674 | O3: Dairy Farms | P3: Dairy Cattle and Milk Production | Q3: ANIWSTCOWS | R3: ANIMALWASTE | S3: 5B24NC00263 | T3: 334890 | U3: Enrollee - WDR | V3: Enrollee Under Dairy GO for Silva, Manuel - Silva Dairy Farms #3A | X3: R5-2013-0122 | Y3: Active | Z3: 43412 | AA3: 39262 | AB3: 10/02/2018 | AC3: 10 - Confined animal feeding facility | AD3: Lamyae Zinebi | AE3: 1 | AF3: 654 | AG3: Mature dairy cattle | AH3: Dairies | AI3: 1605 | AJ3: Y
A4: 5S | B4: 210049 | C4: Joe Borba Dairy Inc. | D4: Growing | E4: Animal Feeding | F4: Agricultural | G4: Joe Borba Dairy Inc | H4: Privately-Owned Business | I4: 3431 South Moffett Road | J4: Turlock | K4: 95380 | L4: Stanislaus | M4: 37.45977 | N4: -120.95136 | O4: Dairy Farms | P4: Dairy Cattle and Milk Production | Q4: ANIWSTCOWS | R4: ANIMALWASTE | S4: 5B50NC00262 | T4: 335295 | U4: Enrollee - WDR | V4: Enrollee Under Dairy Gen Order for Joe Borba Dairy Inc | X4: R5-2013-0122 | Y4: Active | Z4: 42181 | AA4: 39262 | AB4: 10/02/2018 | AC4: 15 - WDRs pending rescission | AD4: Lamyae Zinebi | AE4: 1 | AF4: 654 | AG4: Heifers (non dairy affiliated) | AH4: Dairies | AI4: 85 | AJ4: N
A5: 5S | B5: 218891 | C5: Ken Van Foeken Dairy #2 | D5: Growing | E5: Animal Feeding | F5: Agricultural | G5: Van Foeken, Kenneth L | H5: Privately-Owned Business | I5: 9375 North Washington Road | J5: Hilmar | K5: 95324 | L5: Merced | M5: 37.42486 | N5: -120.90462 | O5: Dairy Farms | P5: Dairy Cattle and Milk Production | Q5: ANIWSTCOWS | R5: ANIMALWASTE | S5: 5B24NC00160 | T5: 334789 | U5: Enrollee - WDR | V5: Enrollee Under Dairy GO for Van Foeken, Kenneth L. - Ken Van Foeken Dairy #2 | X5: R5-2013-0122 | Y5: Active | Z5: 43411 | AA5: 39262 | AB5: 10/02/2018 | AC5: 10 - Confined animal feeding facility | AD5: Lamyae Zinebi | AE5: 1 | AF5: 654 | AG5: Mature dairy cattle | AH5: Dairies | AI5: 651 | AJ5: Y
A6: 5S | B6: 218992 | C6: Da Rosa Dairy | D6: Growing | E6: Animal Feeding | F6: Agricultural | G6: Da Rosa, Luis & Olivia | H6: Privately-Owned Business | I6: 1131 Story Road | J6: Turlock | K6: 95380 | L6: Stanislaus | M6: 37.48168 | N6: -120.78966 | O6: Dairy Farms | Q6: ANIWSTCOWS | R6: ANIMALWASTE | S6: 5B50NC00277 | T6: 335310 | U6: Enrollee - WDR | V6: Enrollee Under Dairy GO for Da Rosa, Luis & Olivia | X6: R5-2013-0122 | Y6: Active | Z6: 42181 | AA6: 39262 | AB6: 10/02/2018 | AC6: 10 - Confined animal feeding facility | AD6: Lamyae Zinebi | AE6: 1 | AF6: 654 | AG6: Mature dairy cattle | AH6: Dairies | AI6: 115 | AJ6: N
A7: 5S | B7: 219290 | C7: J_D Brasil Dairy | D7: Growing | E7: Animal Feeding | F7: Agricultural | G7: Brasil, Danny | H7: Privately-Owned Business | I7: 5600 Clayton Road | J7: Turlock | K7: 95380 | L7: Stanislaus | M7: 37.47989 | N7: -120.91512 | O7: Dairy Farms | Q7: ANIWSTCOWS | R7: ANIMALWASTE | S7: 5B50NC00103 | T7: 335136 | U7: Enrollee - WDR | V7: Enrollee Under Dairy Gen Order for Brasil, Danny, J-D Brasil Dairy | W7: 22 June 2012- The RB has approved operator transfer for Danny Brasil for the J-D Brasil Dairy.-Dy | X7: R5-2013-0122 | Y7: Active | Z7: 42173 | AA7: 39262 | AB7: 10/02/2018 | AC7: 10 - Confined animal feeding facility | AD7: Lamyae Zinebi | AE7: 1 | AF7: 654 | AG7: Mature dairy cattle | AH7: Dairies | AI7: 410 | AJ7: N
A8: 5S | B8: 220560 | C8: River Rock Ranch LLC | D8: Growing | E8: Animal Feeding | F8: Agricultural | G8: River Rock Ranch, LLC | H8: Privately-Owned Business | I8: 22846 West Second Avenue | J8: Stevinson | K8: 95374 | L8: Merced | M8: 37.33335 | N8: -120.91002 | O8: Dairy Farms | P8: Dairy Cattle and Milk Production | Q8: ANIWSTCOWS | R8: ANIMALWASTE | S8: 5B24NC00272 | T8: 334899 | U8: Enrollee - WDR | V8: Enrollee Under Dairy GO for River Rock Ranch, LLC | X8: R5-2013-0122 | Y8: Active | Z8: 44453 | AA8: 39262 | AB8: 10/02/2018 | AC8: 10 - Confined animal feeding facility | AD8: Lamyae Zinebi | AE8: 1 | AF8: 1308 | AG8: Mature dairy cattle | AH8: Dairies | AI8: 1380 | AJ8: N
A9: 5S | B9: 221709 | C9: Double Cross #3 | D9: Growing | E9: Animal Feeding | F9: Agricultural | G9: Coelho, Joe & Louise | H9: Privately-Owned Business | I9: 11071 Youngstown Road | J9: Turlock | K9: 95380 | L9: Merced | M9: 37.44974 | N9: -120.824 | O9: Dairy Farms | P9: Dairy Cattle and Milk Production | Q9: ANIWSTCOWS | R9: ANIMALWASTE | S9: 5C245033001 | T9: 354671 | U9: Enrollee - WDR | V9: Enrollee Under Dairy GO for Ahlem, Mark - Double Cross #3 | W9: 11/23/2016 - Op. has changed (was Dominic Coehlo) - ak 08/03/2011 - the Board approves the request for owner/operator transfer effective the date of the letter. Coelho, Joe & Louise, are now authorized to oversee the operation of the dairy - jv | X9: R5-2013-0122 | Y9: Active | Z9: 43417 | AA9: 39262 | AB9: 10/02/2018 | AC9: 10 - Confined animal feeding facility | AD9: Lamyae Zinebi | AE9: 1 | AG9: Mature dairy cattle | AH9: Dairies | AI9: 402 | AJ9: Y
A10: 5S | B10: 222320 | C10: Edward Nunes Dairy | D10: Growing | E10: Animal Feeding | F10: Agricultural | G10: Nunes, Edward | H10: Privately-Owned Business | I10: 17399 East Avena Road | J10: Escalon | K10: 95320 | L10: San Joaquin | M10: 37.84172 | N10: -121.09854 | O10: Dairy Farms | P10: Dairy Cattle and Milk Production | Q10: ANIWSTCOWS | R10: ANIMALWASTE | S10: 5B39NC00062 | T10: 334959 | U10: Enrollee - WDR | V10: Enrollee Under Dairy GO for Nunes, Edward - Edward Nunes Dairy | X10: R5-2013-0122 | Y10: Active | Z10: 43417 | AA10: 39262 | AB10: 10/02/2018 | AC10: 10 - Confined animal feeding facility | AD10: Lamyae Zinebi | AE10: 1 | AF10: 1308 | AG10: Mature dairy cattle | AH10: Dairies | AI10: 2129 | AJ10: Y
A11: 5S | B11: 224219 | C11: Gomes Dairy | D11: Growing | E11: Animal Feeding | F11: Agricultural | G11: Gomes Dairy | H11: Privately-Owned Business | I11: 9735 Washington Road | J11: Hilmar | K11: 95324 | L11: Merced | M11: 37.42819 | N11: -120.90548 | O11: Dairy Farms | P11: Dairy Cattle and Milk Production | Q11: ANIWSTCOWS | R11: ANIMALWASTE | S11: 5B24NC00161 | T11: 334790 | U11: Enrollee - WDR | V11: Enrollee Under Dairy GO for Gomes Dairy | W11: 3/19/2019 - Chang of Owner/Operator. -JY | X11: R5-2013-0122 | Y11: Active | Z11: 43549 | AA11: 39262 | AB11: 10/02/2018 | AC11: 10 - Confined animal feeding facility | AD11: Lamyae Zinebi | AE11: 1 | AF11: 654 | AG11: Mature dairy cattle | AH11: Dairies | AI11: 715 | AJ11: N
A12: 5S | B12: 226601 | C12: Roest Family Dairy | D12: Growing | E12: Animal Feeding | F12: Agricultural | G12: Roest, Aire | H12: Privately-Owned Business | I12: 2472 Gates Road | J12: Modesto | K12: 95358 | L12: Stanislaus | M12: 37.67324 | N12: -121.15929 | O12: Dairy Farms | P12: Dairy Cattle and Milk Production | Q12: ANIWSTCOWS | R12: ANIMALWASTE | S12: 5B50NC00111 | T12: 335144 | U12: Enrollee - WDR | V12: Enrollee Under Dairy GO for Roest, Arie | X12: R5-2013-0122 | Y12: Active | Z12: 42173 | AA12: 39262 | AB12: 10/02/2018 | AC12: 10 - Confined animal feeding facility | AD12: Lamyae Zinebi | AE12: 2 | AF12: 1308 | AG12: Mature dairy cattle | AH12: Dairies | AI12: 1102 | AJ12: N
A13: 5S | B13: 227158 | C13: Gil Tex Dairy | D13: Growing | E13: Animal Feeding | F13: Agricultural | G13: Teixeira, Gilbert & Linda | H13: Privately-Owned Business | I13: 5601 Mountain View Road | J13: Turlock | K13: 95382 | L13: Stanislaus | M13: 37.54581 | N13: -120.88142 | O13: Dairy Farms | P13: Dairy Cattle and Milk Production | Q13: ANIWSTCOWS | R13: ANIMALWASTE | S13: 5C505022001 | T13: 354688 | U13: Enrollee - WDR | V13: Enrollee Under Dairy GO for Teixeira, Gilbert & Linda - Gil Tex Dairy | X13: R5-2013-0122 | Y13: Active | Z13: 43353 | AA13: 39262 | AB13: 10/02/2018 | AC13: 10 - Confined animal feeding facility | AD13: Lamyae Zinebi | AE13: 1 | AG13: Mature dairy cattle | AH13: Dairies | AI13: 490 | AJ13: N
A14: 5S | B14: 227211 | C14: GJ Silva | D14: Growing | E14: Animal Feeding | F14: Agricultural | G14: Latters, Susan | H14: Privately-Individual | I14: 3107 South Prairie Flower Road | J14: Turlock | K14: 95380 | L14: Stanislaus | M14: 37.46541 | N14: -120.93535 | O14: Dairy Farms | P14: Dairy Cattle and Milk Production | Q14: ANIWSTCOWS | R14: ANIMALWASTE | S14: 5B50NC00275 | T14: 335308 | U14: Enrollee - WDR | V14: Enrollee Under Dairy GO for G J Silva & Sons, Inc. | W14: 03/19/2019 - Owner/ Operator transfer. - JY 12/18/2018 GJ Silva Heifer Facility (3630 S Prairie Flower Road) merged with this dairy. -JY | X14: R5-2013-0122 | Y14: Active | Z14: 43570 | AA14: 39262 | AB14: 10/02/2018 | AC14: 10 - Confined animal feeding facility | AD14: Lamyae Zinebi | AE14: 1 | AF14: 4260 | AG14: Mature dairy cattle | AH14: Dairies | AI14: 2583 | AJ14: N
A15: 5S | B15: 230428 | C15: Hilmar Holsteins Inc. | D15: Growing | E15: Animal Feeding | F15: Agricultural | G15: Matheron, Aaron dba Hilmar Holsteins Inc | H15: Privately-Owned Business | I15: 21859 Crane Avenue | J15: Hilmar | K15: 95324 | L15: Merced | M15: 37.38274 | N15: -120.88425 | O15: Dairy Farms | P15: Dairy Cattle and Milk Production | Q15: ANIWSTCOWS | R15: ANIMALWASTE | S15: 5B24NC00131 | T15: 334760 | U15: Enrollee - WDR | V15: Enrollee Under Dairy GO for Matheron, Aaron dba Hilmar Holsteins Inc. | W15: 10/08/2018 Hilmar Holsteins Heifer Corral #2 is now merged with this dairy. -JY 10/08/2018 Hilmar Holsteins Heifer Corral #1 is now merged with this dairy. -JY 7/3/2015 - Dairy located at 6271 Columbus Avenue is now merged with this dairy. Total animal count of 2829. -JY 10/14/14: OP/owner changed to Matheron, Aaron dba Hilmar Holsteins Inc. - HT | X15: R5-2013-0122 | Y15: Active | Z15: 43510 | AA15: 39262 | AB15: 10/02/2018 | AC15: 10 - Confined animal feeding facility | AD15: Lamyae Zinebi | AE15: 1 | AF15: 2725 | AG15: Mature dairy cattle | AH15: Dairies | AI15: 2400 | AJ15: Y
A16: 5S | B16: 233735 | C16: Jordao Dairy | D16: Growing | E16: Animal Feeding | F16: Agricultural | G16: Jordao, Joe & Jose | H16: Privately-Owned Business | I16: 6025 South Central Avenue | J16: Turlock | K16: 95380 | L16: Stanislaus | M16: 37.436412 | N16: -120.9586 | O16: Dairy Farms | P16: Dairy Cattle and Milk Production | Q16: ANIWSTCOWS | R16: ANIMALWASTE | S16: 5B50NC00221 | T16: 335254 | U16: Enrollee - WDR | V16: Enrollee Under Dairy GO for Jordao, Joe and Jose | X16: R5-2013-0122 | Y16: Active | Z16: 42181 | AA16: 39262 | AB16: 10/02/2018 | AC16: 10 - Confined animal feeding facility | AD16: Lamyae Zinebi | AE16: 1 | AF16: 1308 | AG16: Mature dairy cattle | AH16: Dairies | AI16: 920 | AJ16: Y
A17: 5S | B17: 233749 | C17: Cross Creek Dairy | D17: Growing | E17: Animal Feeding | F17: Agricultural | G17: Branco, Joe & Cathy | H17: Privately-Owned Business | I17: 7965 Washington Road | J17: Hilmar | K17: 95324 | L17: Merced | M17: 37.40419 | N17: -120.90492 | O17: Dairy Farms | P17: Dairy Cattle and Milk Production | Q17: ANIWSTCOWS | R17: ANIMALWASTE | S17: 5B24NC00159 | T17: 334788 | U17: Enrollee - WDR | V17: Enrollee Under Dairy Gen Order for Branco, Joe & Cathy - Cross Creek Dairy | X17: R5-2013-0122 | Y17: Active | Z17: 43411 | AA17: 39262 | AB17: 10/02/2018 | AC17: 10 - Confined animal feeding facility | AD17: Lamyae Zinebi | AE17: 1 | AF17: 654 | AG17: Mature dairy cattle | AH17: Dairies | AI17: 780 | AJ17: Y
A18: 5S | B18: 233757 | C18: Double Cross #2 | D18: Growing | E18: Animal Feeding | F18: Agricultural | G18: Joe Coelho Dairy | H18: Privately-Owned Business | I18: 18637 East Bradbury Road | J18: Turlock | K18: 95380 | L18: Merced | M18: 37.44886 | N18: -120.82427 | O18: Dairy Farms | P18: Dairy Cattle and Milk Production | Q18: ANIWSTCOWS | R18: ANIMALWASTE | S18: 5B24NC00277 | T18: 334904 | U18: Enrollee - WDR | V18: Enrollee Under Dairy GO for Coehlo, Joe - Double Cross #2 | W18: 11/23/2016 - Op. has changed (was Coehlo, Joe) - ak | X18: R5-2013-0122 | Y18: Active | Z18: 43417 | AA18: 39262 | AB18: 10/02/2018 | AC18: 10 - Confined animal feeding facility | AD18: Lamyae Zinebi | AE18: 1 | AF18: 654 | AG18: Mature dairy cattle | AH18: Dairies | AI18: 637 | AJ18: Y
A19: 5S | B19: 233895 | C19: LarryPetersonDairyFarms#2 | D19: Growing | E19: Animal Feeding | F19: Agricultural | G19: Leonardo, John Dairy | H19: Privately-Owned Business | I19: 20775 West American Avenue | J19: Hilmar | K19: 95324 | L19: Merced | M19: 37.40978 | N19: -120.86592 | O19: Dairy Farms | P19: Dairy Cattle and Milk Production | Q19: ANIWSTCOWS | R19: ANIMALWASTE | S19: 5B24NC00107 | T19: 334740 | U19: Enrollee - WDR | V19: Enrollee Under Dairy GO for John Leonardo - Larry B. Peterson Dairy Farms #2 | W19: 11/23/2016 - Op. has changed (were Dominic & Mary Coelho) - ak | X19: R5-2013-0122 | Y19: Active | Z19: 43411 | AA19: 39262 | AB19: 10/02/2018 | AC19: 10 - Confined animal feeding facility | AD19: Lamyae Zinebi | AE19: 1 | AF19: 654 | AG19: Mature dairy cattle | AH19: Dairies | AI19: 381 | AJ19: Y
A20: 5S | B20: 233934 | C20: Fire_Lake Jerseys #2 | D20: Growing | E20: Animal Feeding | F20: Agricultural | G20: Thomas, Rhonda | H20: Privately-Owned Business | I20: 10408 West Bradbury Road | J20: Turlock | K20: 95380 | L20: Stanislaus | M20: 37.449239 | N20: -120.96768 | O20: Dairy Farms | P20: Dairy Cattle and Milk Production | Q20: ANIWSTCOWS | R20: ANIMALWASTE | S20: 5B50NC00289 | T20: 335322 | U20: Enrollee - WDR | V20: Enrollee Under Dairy GO for Thomas, Rhonda, Fire-Lake Jerseys #2 | X20: R5-2013-0122 | Y20: Active | Z20: 43068 | AA20: 39262 | AB20: 10/02/2018 | AC20: 10 - Confined animal feeding facility | AD20: Lamyae Zinebi | AE20: 1 | AF20: 654 | AG20: Heifers (non dairy affiliated) | AH20: Dairies | AI20: 740 | AJ20: N
A21: 5S | B21: 237694 | C21: Lumar Dairy Farms | D21: Growing | E21: Animal Feeding | F21: Agricultural | G21: Borba, Luis & Maria | H21: Privately-Owned Business | I21: 7215 South Prairie Flower Road | J21: Turlock | K21: 95380 | L21: Stanislaus | M21: 37.423154 | N21: -120.93134 | O21: Dairy Farms | P21: Dairy Cattle and Milk Production | Q21: ANIWSTCOWS | R21: ANIMALWASTE | S21: 5B50NC00269 | T21: 335302 | U21: Enrollee - WDR | V21: Enrollee Under Dairy Gen Order for Borba, Luis & Maria, Lumar Dairy Farms | X21: R5-2013-0122 | Y21: Active | Z21: 42181 | AA21: 39262 | AB21: 10/02/2018 | AC21: 10 - Confined animal feeding facility | AD21: Lamyae Zinebi | AE21: 1 | AF21: 2725 | AG21: Mature dairy cattle | AH21: Dairies | AI21: 2100 | AJ21: Y
A22: 5S | B22: 239367 | C22: CMA Livestock | D22: Growing | E22: Animal Feeding | F22: Agricultural | G22: Luis, Manuel S. & Bernardet | H22: Privately-Owned Business | I22: 19051 West Williams Avenue | J22: Hilmar | K22: 95324 | L22: Merced | M22: 37.389598 | N22: -120.83234 | O22: Dairy Farms | P22: Dairy Cattle and Milk Production | Q22: ANIWSTCOWS | R22: ANIMALWASTE | S22: 5B24NC00163 | T22: 334792 | U22: Enrollee - WDR | V22: Enrollee Under Dairy GO for Manuel Luis - CMA Livestock | W22: 11/23/2016 - Op. has changed (was Luis, Manuel S.) - ak | X22: R5-2013-0122 | Y22: Active | Z22: 43411 | AA22: 39262 | AB22: 10/02/2018 | AC22: 10 - Confined animal feeding facility | AD22: Lamyae Zinebi | AE22: 1 | AF22: 1308 | AG22: Mature dairy cattle | AH22: Dairies | AI22: 684 | AJ22: Y
A23: 5S | B23: 251780 | C23: Fire Lakes Jerseys | D23: Growing | E23: Animal Feeding | F23: Agricultural | G23: Sanders, Scott | H23: Privately-Owned Business | I23: 11301 West Bradbury Road | J23: Turlock | K23: 95380 | L23: Stanislaus | M23: 37.44931 | N23: -120.97775 | O23: Dairy Farms | P23: Dairy Cattle and Milk Production | Q23: ANIWSTCOWS | R23: ANIMALWASTE | S23: 5B50NC00308 | T23: 364501 | U23: Enrollee - WDR | V23: Enrollee Under Dairy GO for Sanders, Scott & Sharalee | W23: On 12/05/08, we received a request for owner / operator transfer approval for SAS Dairy #4. The owner/operator transfer approval was issued to take effect on 03/16/09 - jv | X23: R5-2013-0122 | Y23: Active | Z23: 42181 | AA23: 39262 | AB23: 10/02/2018 | AC23: 10 - Confined animal feeding facility | AD23: Lamyae Zinebi | AE23: 1 | AG23: Mature dairy cattle | AH23: Dairies | AI23: 278 | AJ23: Y
A24: 5S | B24: 252667 | C24: Rick Jones Farms | D24: Growing | E24: Animal Feeding | F24: Agricultural | G24: Jones Farms | H24: Privately-Owned Business | I24: 1511 Van Clief Road | J24: Stevinson | K24: 95374 | L24: Merced | M24: 37.30955 | N24: -120.83303 | O24: Dairy Farms | P24: Dairy Cattle and Milk Production | Q24: ANIWSTCOWS | R24: ANIMALWASTE | S24: 5C245037001 | T24: 354675 | U24: Enrollee - WDR | V24: Enrollee Under Dairy GO for Rick Jones Farms | W24: 10/08/2018 Jones Farms Heifer Facility is now merged with this dairy. -JY | X24: R5-2013-0122 | Y24: Active | Z24: 43510 | AA24: 39262 | AB24: 10/02/2018 | AC24: 10 - Confined animal feeding facility | AD24: Lamyae Zinebi | AE24: 1 | AG24: Mature dairy cattle | AH24: Dairies | AI24: 690
A25: 5S | B25: 257092 | C25: Silveira Holsteins | D25: Growing | E25: Animal Feeding | F25: Agricultural | G25: Silveira, Manuel | H25: Privately-Owned Business | I25: 23356 Short Avenue | J25: Hilmar | K25: 95324 | L25: Merced | M25: 37.42641 | N25: -120.91051 | O25: Dairy Farms | P25: Dairy Cattle and Milk Production | Q25: ANIWSTCOWS | R25: ANIMALWASTE | S25: 5B24NC00149 | T25: 334778 | U25: Enrollee - WDR | V25: Enrollee Under Dairy GO for Silveira, Manuel - Silveira Holsteins | W25: 1/17/2019 - Dairy located at 5531 Ehrlich Road (Former Blue Island Jerseys), Turlock is now merged with this dairy. Total Animal population of 735. - JY | X25: R5-2013-0122 | Y25: Active | Z25: 43510 | AA25: 39262 | AB25: 10/02/2018 | AC25: 10 - Confined animal feeding facility | AD25: Lamyae Zinebi | AE25: 1 | AF25: 654 | AG25: Mature dairy cattle | AH25: Dairies | AI25: 679 | AJ25: Y
A26: 5S | B26: 263088 | C26: Diamond B Dairy | D26: Growing | E26: Animal Feeding | F26: Agricultural | G26: Brasil, John | H26: Privately-Individual | I26: 3137 East Tuolumne Road | J26: Ceres | K26: 95307 | L26: Stanislaus | M26: 37.51451 | N26: -120.9356 | O26: Dairy Farms | Q26: ANIWSTCOWS | R26: ANIMALWASTE | S26: 5B50NC00300 | T26: 353697 | U26: Enrollee - WDR | V26: Enrollee Under Dairy GO for Meneses, Adeline - Diamond B Dairy | W26: 22 June 2012- The Board has approved operator transfer for John Brasil as the operator at the Diamond B Dairy.-Dy | X26: R5-2013-0122 | Y26: Active | Z26: 43579 | AA26: 39262 | AB26: 10/02/2018 | AC26: 10 - Confined animal feeding facility | AD26: Lamyae Zinebi | AE26: 1 | AF26: 0 | AG26: Mature dairy cattle | AH26: Dairies | AI26: 679 | AJ26: N
A27: 5S | B27: 264484 | C27: Azevedo Dairy | D27: Growing | E27: Animal Feeding | F27: Agricultural | G27: Azevedo, Tiberio & Rosa | H27: Privately-Owned Business | I27: 21480 August Avenue | J27: Hilmar | K27: 95324 | L27: Merced | M27: 37.418948 | N27: -120.87684 | O27: Dairy Farms | P27: Dairy Cattle and Milk Production | Q27: ANIWSTCOWS | R27: ANIMALWASTE | S27: 5B24NC00111 | T27: 334744 | U27: Enrollee - WDR | V27: Enrollee Under Dairy Gen Order for Azevedo, Tiberio & Rosa - Azevedo Dairy | X27: R5-2013-0122 | Y27: Active | Z27: 43411 | AA27: 39262 | AB27: 10/02/2018 | AC27: 10 - Confined animal feeding facility | AD27: Lamyae Zinebi | AE27: 1 | AF27: 1308 | AG27: Mature dairy cattle | AH27: Dairies | AI27: 930 | AJ27: Y
A28: 5S | B28: 272502 | C28: Valsigna Dairy | D28: Growing | E28: Animal Feeding | F28: Agricultural | G28: Wickstrom, Tim & Vern | H28: Privately-Owned Business | I28: 6071 North Larson Avenue | J28: Hilmar | K28: 95324 | L28: Merced | M28: 37.38248 | N28: -120.85019 | O28: Dairy Farms | P28: Dairy Cattle and Milk Production | Q28: ANIWSTCOWS | R28: ANIMALWASTE | S28: 5B24NC00144 | T28: 334773 | U28: Enrollee - WDR | V28: Enrollee Under Dairy GO for Wickstrom, Tim & Vern - Valsigna Dairy | X28: R5-2013-0122 | Y28: Active | Z28: 43411 | AA28: 39262 | AB28: 10/02/2018 | AC28: 10 - Confined animal feeding facility | AD28: Lamyae Zinebi | AF28: 2725 | AG28: Mature dairy cattle | AH28: Dairies | AI28: 2940 | AJ28: Y
A29: 5S | B29: 705196 | C29: WickstromJerseyFarmsInc. | D29: Growing | E29: Animal Feeding | F29: Agricultural | G29: Wickstrom, Mike | H29: Privately-Owned Business | I29: 5638 Columbus Avenue | J29: Hilmar | K29: 95324 | L29: Merced | M29: 37.36976 | N29: -120.86883 | O29: Dairy Farms | P29: Dairy Cattle and Milk Production | Q29: ANIWSTCOWS | R29: ANIMALWASTE | S29: 5B24NC00123 | T29: 333921 | U29: Enrollee - WDR | V29: Enrollee Under Dairy GO for Wickstrom, Mike - Wickstrom Jersey Farms, Inc. | X29: R5-2013-0122 | Y29: Active | Z29: 43411 | AA29: 39262 | AB29: 10/02/2018 | AC29: 10 - Confined animal feeding facility | AD29: Lamyae Zinebi | AE29: 1 | AF29: 2725 | AG29: Mature dairy cattle | AH29: Dairies | AI29: 2750 | AJ29: Y
A30: 5S | B30: 705203 | C30: Diniz Dairy | D30: Growing | E30: Animal Feeding | F30: Agricultural | G30: Diniz, Antonio V & Maria | H30: Privately-Owned Business | I30: 9558 Columbus Avenue | J30: Hilmar | K30: 95324 | L30: Merced | M30: 37.42795 | N30: -120.86571 | O30: Dairy Farms | P30: Dairy Cattle and Milk Production | Q30: ANIWSTCOWS | R30: ANIMALWASTE | S30: 5B24NC00126 | T30: 333932 | U30: Enrollee - WDR | V30: Enrollee Under Dairy GO for Diniz, Antonio V & Maria - Diniz Dairy | X30: R5-2013-0122 | Y30: Active | Z30: 43411 | AA30: 39262 | AB30: 10/02/2018 | AC30: 10 - Confined animal feeding facility | AD30: Lamyae Zinebi | AE30: 1 | AF30: 654 | AG30: Mature dairy cattle | AH30: Dairies | AI30: 550 | AJ30: Y
A31: 5S | B31: 705219 | C31: Crane Dairy Inc. | D31: Growing | E31: Animal Feeding | F31: Agricultural | G31: Crane Dairy, Inc | H31: Privately-Owned Business | I31: 20633 West Crane Avenue | J31: Hilmar | K31: 95324 | L31: Merced | M31: 37.38259 | N31: -120.86194 | O31: Dairy Farms | P31: Dairy Cattle and Milk Production | Q31: ANIWSTCOWS | R31: ANIMALWASTE | S31: 5B24NC00128 | T31: 334757 | U31: Enrollee - WDR | V31: Enrollee Under Dairy GO for Leroy Souza - Crane Dairy, Inc | W31: 10/08/2018 Crane Heifer Feedlot #2 (6404 Columbus Avenue) is now merged with this dairy. -JY 10/08/2018 Crane Heifer Feedlot #1 (6736 Columbus Avenue) with this Dairy. -JY 11/23/2016 - Ow/Op have changed (were Souza, Leroy & Phillip) - ak | X31: R5-2013-0122 | Y31: Active | Z31: 43508 | AA31: 39262 | AB31: 10/02/2018 | AC31: 10 - Confined animal feeding facility | AD31: Lamyae Zinebi | AE31: 1 | AF31: 654 | AG31: Heifers (non dairy affiliated) | AH31: Dairies | AI31: 968 | AJ31: Y
A32: 5S | B32: 705229 | C32: GM Silva Dairies #2 | D32: Growing | E32: Animal Feeding | F32: Agricultural | G32: Silva, George & Margaret | H32: Privately-Owned Business | I32: 20316 West Crane Avenue | J32: Hilmar | K32: 95324 | L32: Merced | M32: 37.38259 | N32: -120.85601 | O32: Dairy Farms | P32: Dairy Cattle and Milk Production | Q32: ANIWSTCOWS | R32: ANIMALWASTE | S32: 5B24NC00129 | T32: 334758 | U32: Enrollee - WDR | V32: Enrollee Under Dairy GO for Silva, George & Margaret - GM Silva Dairies #2 | W32: 11/23/2016 - Owner and operator have changed (was Silva, Manuel) - ak 02/14/2020 - Dairy at 20633 Turner Ave, Hilmar is now merged with this dairy. Total Animal Population of 1467 - SP | X32: R5-2013-0122 | Y32: Active | Z32: 43880 | AA32: 39262 | AB32: 10/02/2018 | AC32: 10 - Confined animal feeding facility | AD32: Lamyae Zinebi | AE32: 1 | AF32: 654 | AG32: Mature dairy cattle | AH32: Dairies | AI32: 1461 | AJ32: Y
A33: 5S | B33: 705233 | C33: Joe Oliveira Dairy | D33: Growing | E33: Animal Feeding | F33: Agricultural | G33: Oliveira, Joe | H33: Privately-Owned Business | I33: 19104 Crane Avenue | J33: Hilmar | K33: 95324 | L33: Merced | M33: 37.38237 | N33: -120.83311 | O33: Dairy Farms | P33: Dairy Cattle and Milk Production | Q33: ANIWSTCOWS | R33: ANIMALWASTE | S33: 5B24NC00130 | T33: 334759 | U33: Enrollee - WDR | V33: Enrollee Under Dairy GO for Oliveira, Joe - Joe Oliveira Dairy | X33: R5-2013-0122 | Y33: Active | Z33: 42172 | AA33: 39262 | AB33: 10/02/2018 | AC33: 10 - Confined animal feeding facility | AD33: Lamyae Zinebi | AE33: 1 | AF33: 1308 | AG33: Mature dairy cattle | AH33: Dairies | AI33: 1270 | AJ33: Y
A34: 5S | B34: 705238 | C34: Vierra Dairy Farms #3 | D34: Growing | E34: Animal Feeding | F34: Agricultural | G34: Ferreira, Eleanor | H34: Privately-Individual | I34: 7884 Faith Home Road | J34: Hilmar | K34: 95324 | L34: Merced | M34: 37.40304 | N34: -120.92265 | O34: Dairy Farms | P34: Dairy Cattle and Milk Production | Q34: ANIWSTCOWS | R34: ANIMALWASTE | S34: 5B24NC00133 | T34: 334762 | U34: Enrollee - WDR | V34: Enrollee Under Dairy Gen Order for Ferreira, Eleanor - Vierra Dairy Farms #3 | W34: 10/19/18 - Operator transfer - JY | X34: R5-2013-0122 | Y34: Active | Z34: 43392 | AA34: 39262 | AB34: 10/02/2018 | AC34: 10 - Confined animal feeding facility | AD34: Lamyae Zinebi | AE34: 1 | AF34: 654 | AG34: Mature dairy cattle | AH34: Dairies | AI34: 321 | AJ34: N
A35: 5S | B35: 705241 | C35: Nelson Dairy | D35: Growing | E35: Animal Feeding | F35: Agricultural | G35: Joyce W. Nelson and Trust | H35: Privately-Owned Business | I35: 19481 Geer Avenue | J35: Hilmar | K35: 95324 | L35: Merced | M35: 37.39689 | N35: -120.84006 | O35: Dairy Farms | P35: Dairy Cattle and Milk Production | Q35: ANIWSTCOWS | R35: ANIMALWASTE | S35: 5B24NC00134 | T35: 334763 | U35: Enrollee - WDR | V35: Enrollee Under Dairy GO for Joyce W. Nelson and Trust - Nelson Dairy | X35: R5-2013-0122 | Y35: Active | Z35: 43411 | AA35: 39262 | AB35: 10/02/2018 | AC35: 10 - Confined animal feeding facility | AD35: Lamyae Zinebi | AE35: 1 | AF35: 327 | AG35: Heifers (non dairy affiliated) | AH35: Dairies | AI35: 177 | AJ35: N
A36: 5S | B36: 705247 | C36: Mario&ChristinaNunesDairy | D36: Growing | E36: Animal Feeding | F36: Agricultural | G36: Jorge, Luis & Maria | H36: Privately-Owned Business | I36: 21625 Geer Avenue | J36: Hilmar | K36: 95324 | L36: Merced | M36: 37.39599 | N36: -120.87862 | O36: Dairy Farms | P36: Dairy Cattle and Milk Production | Q36: ANIWSTCOWS | R36: ANIMALWASTE | S36: 5B24NC00136 | T36: 334765 | U36: Enrollee - WDR | V36: Enrollee Under Dairy GO for Jorge, Luis & Maria - Mario and Christina Nunes Dairy | W36: 03/06/2017 - Op. has changed - ak On 12/30/08, we received a request for operator transfer approval for the dairy located at 21625 Geer Ave. The operator transfer approval is effective 03/16/09 - jv | X36: R5-2013-0122 | Y36: Active | Z36: 43411 | AA36: 39262 | AB36: 10/02/2018 | AC36: 10 - Confined animal feeding facility | AD36: Lamyae Zinebi | AE36: 1 | AF36: 327 | AG36: Mature dairy cattle | AH36: Dairies | AI36: 0 | AJ36: N
A37: 5S | B37: 705274 | C37: B & D Dairy | D37: Growing | E37: Animal Feeding | F37: Agricultural | G37: Huff, Eric | H37: Privately-Owned Business | I37: 9579 Hultberg Road | J37: Hilmar | K37: 95324 | L37: Merced | M37: 37.42649 | N37: -120.89554 | O37: Dairy Farms | P37: Dairy Cattle and Milk Production | Q37: ANIWSTCOWS | R37: ANIMALWASTE | S37: 5B24NC00139 | T37: 334768 | U37: Enrollee - WDR | V37: Enrollee Under Dairy GO for Huff, Eric - B & D Dairy | X37: R5-2013-0122 | Y37: Active | Z37: 43411 | AA37: 39262 | AB37: 10/02/2018 | AC37: 10 - Confined animal feeding facility | AD37: Lamyae Zinebi | AE37: 1 | AF37: 654 | AG37: Heifers (non dairy affiliated) | AH37: Dairies | AI37: 1200 | AJ37: N
A38: 5S | B38: 705276 | C38: Silveira Dairy Inc. | D38: Growing | E38: Animal Feeding | F38: Agricultural | G38: Silveira, Frank | H38: Privately-Owned Business | I38: 20271 Johnson Avenue | J38: Hilmar | K38: 95324 | L38: Merced | M38: 37.43333 | N38: -120.85196 | O38: Dairy Farms | P38: Dairy Cattle and Milk Production | Q38: ANIWSTCOWS | R38: ANIMALWASTE | S38: 5B24NC00140 | T38: 334769 | U38: Enrollee - WDR | V38: Enrollee Under Dairy GO for Silveira, Frank - Silveira Dairy, Inc. | X38: R5-2013-0122 | Y38: Active | Z38: 43411 | AA38: 39262 | AB38: 10/02/2018 | AC38: 10 - Confined animal feeding facility | AD38: Lamyae Zinebi | AE38: 1 | AF38: 654 | AG38: Mature dairy cattle | AH38: Dairies | AI38: 400 | AJ38: Y
A39: 5S | B39: 705277 | C39: Jade Jersey Dairy | D39: Growing | E39: Animal Feeding | F39: Agricultural | G39: Ahlem, James & Carol | H39: Privately-Owned Business | I39: 20326 Johnson Avenue | J39: Hilmar | K39: 95324 | L39: Merced | M39: 37.4333 | N39: -120.85581 | O39: Dairy Farms | P39: Dairy Cattle and Milk Production | Q39: ANIWSTCOWS | R39: ANIMALWASTE | S39: 5B24NC00141 | T39: 334770 | U39: Enrollee - WDR | V39: Enrollee Under Dairy Gen Order for Ahlem, James & Carol - Jade Jersey Dairy | X39: R5-2013-0122 | Y39: Active | Z39: 43411 | AA39: 39262 | AB39: 10/02/2018 | AC39: 10 - Confined animal feeding facility | AD39: Lamyae Zinebi | AE39: 1 | AF39: 654 | AG39: Mature dairy cattle | AH39: Dairies | AI39: 450 | AJ39: Y
A40: 5S | B40: 705279 | C40: Live Oak Dairy A | D40: Growing | E40: Animal Feeding | F40: Agricultural | G40: Nyman, Brad | H40: Privately-Owned Business | I40: 21052 Johnson Avenue | J40: Hilmar | K40: 95324 | L40: Merced | M40: 37.43355 | N40: -120.87067 | O40: Dairy Farms | P40: Dairy Cattle and Milk Production | Q40: ANIWSTCOWS | R40: ANIMALWASTE | S40: 5B24NC00142 | T40: 334771 | U40: Enrollee - WDR | V40: Enrollee Under Dairy GO for Nyman, Brad - Live Oak Dairy A | X40: R5-2013-0122 | Y40: Active | Z40: 42647 | AA40: 39262 | AB40: 10/02/2018 | AC40: 10 - Confined animal feeding facility | AD40: Lamyae Zinebi | AE40: 1 | AF40: 654 | AG40: Mature dairy cattle | AH40: Dairies | AI40: 475 | AJ40: Y
A41: 5S | B41: 705281 | C41: T & M Borba Dairy | D41: Growing | E41: Animal Feeding | F41: Agricultural | G41: DeBorba, Maria & Antonio | H41: Privately-Owned Business | I41: 6275 Mitchell Road | J41: Hilmar | K41: 95324 | L41: Merced | M41: 37.37565 | N41: -120.94139 | O41: Dairy Farms | P41: Dairy Cattle and Milk Production | Q41: ANIWSTCOWS | R41: ANIMALWASTE | S41: 5B24NC00145 | T41: 334774 | U41: Enrollee - WDR | V41: Enrollee Under Dairy GO for DeBorba, Maria & Antonio - T & M Borba Dairy | X41: R5-2013-0122 | Y41: Active | Z41: 43411 | AA41: 39262 | AB41: 10/02/2018 | AC41: 10 - Confined animal feeding facility | AD41: Lamyae Zinebi | AE41: 1 | AF41: 1308 | AG41: Mature dairy cattle | AH41: Dairies | AI41: 1650 | AJ41: N
A42: 5S | B42: 705283 | C42: Oslo Dairy | D42: Growing | E42: Animal Feeding | F42: Agricultural | G42: Nyman, Brad | H42: Privately-Owned Business | I42: 20334 West Oslo Road | J42: Hilmar | K42: 95324 | L42: Merced | M42: 37.42637 | N42: -120.8559 | O42: Dairy Farms | Q42: ANIWSTCOWS | R42: ANIMALWASTE | S42: 5B24NC00146 | T42: 334775 | U42: Enrollee - WDR | V42: Enrollee Under Dairy GO for Nymand, Brad - Oslo Dairy | W42: 22 June 2012- The Board has approved operator transfer for Brad Nymand to the Oslo Dairy.-Dy | X42: R5-2013-0122 | Y42: Active | Z42: 43411 | AA42: 39262 | AB42: 10/02/2018 | AC42: 10 - Confined animal feeding facility | AD42: Lamyae Zinebi | AE42: 1 | AF42: 654 | AG42: Mature dairy cattle | AH42: Dairies | AI42: 0 | AJ42: N
A43: 5S | B43: 705286 | C43: Kronberg Facility | D43: Growing | E43: Animal Feeding | F43: Agricultural | G43: Kronberg, Virgil | H43: Privately-Owned Business | I43: 20777 Riverside Avenue | J43: Hilmar | K43: 95324 | L43: Merced | M43: 37.3642 | N43: -120.86552 | O43: Dairy Farms | P43: Dairy Cattle and Milk Production | Q43: ANIWSTCOWS | R43: ANIMALWASTE | S43: 5B24NC00148 | T43: 334777 | U43: Enrollee - WDR | V43: Enrollee Under Dairy GO for Kronberg, Virgil - Kronberg Facility | W43: 08/04/2020 - Change of operator - ak Operator has changed effective 10/17/08 (was Dores, Frank) - jv (9/26/08) | X43: R5-2013-0122 | Y43: Active | Z43: 44204 | AA43: 39262 | AB43: 10/02/2018 | AC43: 10 - Confined animal feeding facility | AD43: Lamyae Zinebi | AE43: 1 | AF43: 327 | AG43: Mature dairy cattle | AH43: Dairies | AI43: 0 | AJ43: Y
A44: 5S | B44: 705288 | C44: Ken Van Foeken Dairy | D44: Growing | E44: Animal Feeding | F44: Agricultural | G44: Van Foeken, Kenneth L | H44: Privately-Owned Business | I44: 22338 Short Avenue | J44: Hilmar | K44: 95324 | L44: Merced | M44: 37.42642 | N44: -120.89098 | O44: Dairy Farms | P44: Dairy Cattle and Milk Production | Q44: ANIWSTCOWS | R44: ANIMALWASTE | S44: 5B24NC00150 | T44: 334779 | U44: Enrollee - WDR | V44: Enrollee Under Dairy GO for Van Foeken, Kenneth L - Ken Van Foeken Dairy | W44: CDQAP list shows facility passed QA certification as of 9/22/2007 | X44: R5-2013-0122 | Y44: Active | Z44: 43411 | AA44: 39262 | AB44: 10/02/2018 | AC44: 10 - Confined animal feeding facility | AD44: Lamyae Zinebi | AE44: 1 | AF44: 654 | AG44: Mature dairy cattle | AH44: Dairies | AI44: 464 | AJ44: Y
A45: 5S | B45: 705290 | C45: Amaral Dairy Farms | D45: Growing | E45: Animal Feeding | F45: Agricultural | G45: Kindberg, Mike | H45: Privately-Individual | I45: 7706 Tegner Road | J45: Hilmar | K45: 95324 | L45: Merced | M45: 37.40027 | N45: -120.8853 | O45: Dairy Farms | P45: Dairy Cattle and Milk Production | Q45: ANIWSTCOWS | R45: ANIMALWASTE | S45: 5B24NC00152 | T45: 334781 | U45: Enrollee - WDR | V45: Enrollee Under Dairy GO for Kindberg, Mik - Amaral Dairy Farms | W45: 11/21/2016 - Op. has changed (was Scott Wickstrom) - ak | X45: R5-2013-0122 | Y45: Active | Z45: 43411 | AA45: 39262 | AB45: 10/02/2018 | AC45: 10 - Confined animal feeding facility | AD45: Lamyae Zinebi | AE45: 1 | AF45: 654 | AG45: Mature dairy cattle | AH45: Dairies | AI45: 290 | AJ45: N
A46: 5S | B46: 705294 | C46: B_6 Dairy | D46: Growing | E46: Animal Feeding | F46: Agricultural | G46: Borba, Mike | H46: Privately-Owned Business | I46: 22014 Turner Avenue | J46: Hilmar | K46: 95324 | L46: Merced | M46: 37.37203 | N46: -120.88788 | O46: Dairy Farms | P46: Dairy Cattle and Milk Production | Q46: ANIWSTCOWS | R46: ANIMALWASTE | S46: 5B24NC00156 | T46: 334785 | U46: Enrollee - WDR | V46: Enrollee Under Dairy Gen Order for Borba, Mike - B-6 Dairy | W46: Operator has changed effective 7/01/08 (was Frank Gonsalves)- jv | X46: R5-2013-0122 | Y46: Active | Z46: 43411 | AA46: 39262 | AB46: 10/02/2018 | AC46: 10 - Confined animal feeding facility | AD46: Lamyae Zinebi | AE46: 1 | AF46: 1308 | AG46: Mature dairy cattle | AH46: Dairies | AI46: 1905 | AJ46: Y
A47: 5S | B47: 705296 | C47: 6D Dores Dairy | D47: Growing | E47: Animal Feeding | F47: Agricultural | G47: Dores, John | H47: Privately-Owned Business | I47: 25762 Turner Avenue | J47: Hilmar | K47: 95324 | L47: Merced | M47: 37.37417 | N47: -120.95495 | O47: Dairy Farms | P47: Dairy Cattle and Milk Production | Q47: ANIWSTCOWS | R47: ANIMALWASTE | S47: 5B24NC00157 | T47: 334786 | U47: Enrollee - WDR | V47: Enrollee Under Dairy GO for Dores, John - 6D Dores Dairy | X47: R5-2013-0122 | Y47: Active | Z47: 43411 | AA47: 39262 | AB47: 10/02/2018 | AC47: 10 - Confined animal feeding facility | AD47: Lamyae Zinebi | AE47: 1 | AF47: 1308 | AG47: Mature dairy cattle | AH47: Dairies | AI47: 895 | AJ47: N
A48: 5S | B48: 705297 | C48: Fanelli Dairy | D48: Growing | E48: Animal Feeding | F48: Agricultural | G48: Fanelli, Philip | H48: Privately-Owned Business | I48: 7689 Washington Road | J48: Hilmar | K48: 95324 | L48: Merced | M48: 37.40006 | N48: -120.90697 | O48: Dairy Farms | P48: Dairy Cattle and Milk Production | Q48: ANIWSTCOWS | R48: ANIMALWASTE | S48: 5B24NC00158 | T48: 334787 | U48: Enrollee - WDR | V48: Enrollee Under Dairy GO for Fanelli, Phil V - Fanelli Dairy | X48: R5-2013-0122 | Y48: Active | Z48: 43411 | AA48: 39262 | AB48: 10/02/2018 | AC48: 10 - Confined animal feeding facility | AD48: Lamyae Zinebi | AE48: 1 | AF48: 654 | AG48: Mature dairy cattle | AH48: Dairies | AI48: 745 | AJ48: Y
A49: 5S | B49: 705298 | C49: Joao Sousa Dairy | D49: Growing | E49: Animal Feeding | F49: Agricultural | G49: Sousa, Joao | H49: Privately-Owned Business | I49: 18005 Williams Avenue | J49: Hilmar | K49: 95324 | L49: Merced | M49: 37.38528 | N49: -120.81469 | O49: Dairy Farms | P49: Dairy Cattle and Milk Production | Q49: ANIWSTCOWS | R49: ANIMALWASTE | S49: 5B24NC00162 | T49: 334791 | U49: Enrollee - WDR | V49: Enrollee Under Dairy GO for Sousa, Joao - Joao Sousa Dairy | W49: 09/20/2013 - The RB office issued approval for Owner transfer for the Joao Sousa Dairy. Operator has changed effective 10/17/2008 (was Jose Gomes and Family Dairy) - jv (2/10/2009) | X49: R5-2013-0122 | Y49: Active | Z49: 43411 | AA49: 39262 | AB49: 10/02/2018 | AC49: 10 - Confined animal feeding facility | AD49: Lamyae Zinebi | AE49: 1 | AF49: 327 | AG49: Mature dairy cattle | AH49: Dairies | AI49: 290 | AJ49: N
A50: 5S | B50: 705300 | C50: Vierra Dairy Farms #2 | D50: Growing | E50: Animal Feeding | F50: Agricultural | G50: R & R Ranches LLC | H50: Privately-Owned Business | I50: 22682 West Williams Avenue | J50: Hilmar | K50: 95324 | L50: Merced | M50: 37.39026 | N50: -120.89859 | O50: Dairy Farms | P50: Dairy Cattle and Milk Production | Q50: ANIWSTCOWS | R50: ANIMALWASTE | S50: 5B24NC00165 | T50: 334794 | U50: Enrollee - WDR | V50: Enrollee Under Dairy GO for R & R Ranches LLC - Vierra Dairy Farms #2 | W50: 12/14/2020 - Change of owner and operator - AK | X50: R5-2013-0122 | Y50: Active | Z50: 44222 | AA50: 39262 | AB50: 10/02/2018 | AC50: 10 - Confined animal feeding facility | AD50: Lamyae Zinebi | AE50: 1 | AF50: 654 | AG50: Mature dairy cattle | AH50: Dairies | AI50: 560 | AJ50: Y
A51: 5S | B51: 705503 | C51: Michael Brasil Dairy | D51: Growing | E51: Animal Feeding | F51: Agricultural | G51: Brasil, Michael | H51: Privately-Owned Business | I51: 18254 First Avenue | J51: Stevinson | K51: 95374 | L51: Merced | M51: 37.34393 | N51: -120.83146 | O51: Dairy Farms | P51: Dairy Cattle and Milk Production | Q51: ANIWSTCOWS | R51: ANIMALWASTE | S51: 5B24NC00264 | T51: 334891 | U51: Enrollee - WDR | V51: Enrollee Under Dairy Gen Order for Brasil, Michael - Michael Brasil Dairy | X51: R5-2013-0122 | Y51: Active | Z51: 43490 | AA51: 39262 | AB51: 10/02/2018 | AC51: 10 - Confined animal feeding facility | AD51: Lamyae Zinebi | AE51: 1 | AF51: 1308 | AG51: Mature dairy cattle | AH51: Dairies | AI51: 1840 | AJ51: Y
A52: 5S | B52: 705505 | C52: Anchor J Dairy | D52: Growing | E52: Animal Feeding | F52: Agricultural | G52: James J. Stevinson, A Corp. | H52: Privately-Owned Business | I52: 24507 First Avenue | J52: Stevinson | K52: 95374 | L52: Merced | M52: 37.33732 | N52: -120.93195 | O52: Dairy Farms | Q52: ANIWSTCOWS | R52: ANIMALWASTE | S52: 5B24NC00265 | T52: 334892 | U52: Enrollee - WDR | V52: Enrollee Under Dairy GO for Stevinson, James J, A Corporation - Anchor J Dairy | W52: 10/17/2019 - Bovine operation located at 1232 S. Van Clief Road, Stevinson is now merged with this dairy. - AK 10/08/2018 Anchor J Heifer Facility is now merged with this Dairy. -JY | X52: R5-2013-0122 | Y52: Active | Z52: 43760 | AA52: 39262 | AB52: 10/02/2018 | AC52: 10 - Confined animal feeding facility | AD52: Lamyae Zinebi | AE52: 1 | AF52: 2725 | AG52: Mature dairy cattle | AH52: Dairies | AI52: 3000 | AJ52: Y
A53: 5S | B53: 705508 | C53: Oliveira Dairy | D53: Growing | E53: Animal Feeding | F53: Agricultural | G53: Oliveira, Arthur & Antelma | H53: Privately-Owned Business | I53: 3991 Lander Avenue | J53: Stevinson | K53: 95374 | L53: Merced | M53: 37.34489 | N53: -120.85302 | O53: Dairy Farms | P53: Dairy Cattle and Milk Production | Q53: ANIWSTCOWS | R53: ANIMALWASTE | S53: 5B24NC00267 | T53: 334894 | U53: Enrollee - WDR | V53: Enrollee Under Dairy GO for Oliveira, Arthur & Antelma - Oliveira Dairy | X53: R5-2013-0122 | Y53: Active | Z53: 43412 | AA53: 39262 | AB53: 10/02/2018 | AC53: 10 - Confined animal feeding facility | AD53: Lamyae Zinebi | AE53: 1 | AF53: 654 | AG53: Mature dairy cattle | AH53: Dairies | AI53: 725 | AJ53: Y
A54: 5S | B54: 705510 | C54: Souza Bros Dairy | D54: Growing | E54: Animal Feeding | F54: Agricultural | G54: Souza Joe S & John S | H54: Privately-Owned Business | I54: 3887 McCullagh Road | J54: Stevinson | K54: 95374 | L54: Merced | M54: 37.34448 | N54: -120.87829 | O54: Dairy Farms | P54: Dairy Cattle and Milk Production | Q54: ANIWSTCOWS | R54: ANIMALWASTE | S54: 5B24NC00268 | T54: 334895 | U54: Enrollee - WDR | V54: Enrollee Under Dairy GO for Souza, Joe S & John S - Souza Bros Dairy | X54: R5-2013-0122 | Y54: Active | Z54: 43412 | AA54: 39262 | AB54: 10/02/2018 | AC54: 10 - Confined animal feeding facility | AD54: Lamyae Zinebi | AE54: 1 | AF54: 1308 | AG54: Mature dairy cattle | AH54: Dairies | AI54: 672 | AJ54: Y
A55: 5S | B55: 705512 | C55: Miguel Family Dairy | D55: Growing | E55: Animal Feeding | F55: Agricultural | G55: Dennis Miguel | H55: Privately-Individual | I55: 20755 West River Road | J55: Stevinson | K55: 95374 | L55: Merced | M55: 37.34689 | N55: -120.8658 | O55: Dairy Farms | Q55: ANIWSTCOWS | R55: ANIMALWASTE | S55: 5B24NC00270 | T55: 334897 | U55: Enrollee - WDR | V55: Enrollee Under Dairy GO for Dennis Miguel - Miguel Family Dairy | X55: R5-2013-0122 | Y55: Active | Z55: 43412 | AA55: 39262 | AB55: 10/02/2018 | AC55: 10 - Confined animal feeding facility | AD55: Lamyae Zinebi | AE55: 1 | AF55: 654 | AG55: Mature dairy cattle | AH55: Dairies | AI55: 0 | AJ55: N
A56: 5S | B56: 705514 | C56: Dias Family Dairy | D56: Growing | E56: Animal Feeding | F56: Agricultural | G56: Dias, Robert | H56: Privately-Owned Business | I56: 21330 West Second Avenue | J56: Stevinson | K56: 95374 | L56: Merced | M56: 37.33689 | N56: -120.87556 | O56: Dairy Farms | P56: Dairy Cattle and Milk Production | Q56: ANIWSTCOWS | R56: ANIMALWASTE | S56: 5B24NC00271 | T56: 334898 | U56: Enrollee - WDR | V56: Enrollee Under Dairy GO for Dias, Robert - Dias Family Dairy | X56: R5-2013-0122 | Y56: Active | Z56: 43412 | AA56: 39262 | AB56: 10/02/2018 | AC56: 10 - Confined animal feeding facility | AD56: Lamyae Zinebi | AE56: 1 | AF56: 654 | AG56: Mature dairy cattle | AH56: Dairies | AI56: 342 | AJ56: Y
A57: 5S | B57: 705515 | C57: Empty was A_D Dairy | D57: Growing | E57: Animal Feeding | F57: Agricultural | G57: Lewis, Joe Jr | H57: Privately-Owned Business | I57: 23489 West Second Avenue | J57: Stevinson | K57: 95324 | L57: Merced | M57: 37.33526 | N57: -120.91451 | O57: Dairy Farms | Q57: ANIWSTCOWS | R57: ANIMALWASTE | S57: 5B24NC00273 | T57: 334900 | U57: Enrollee - WDR | V57: Enrollee Under Dairy GO for Lewis, Joe Jr. | W57: On 11/07/08, we received a request for transfer of operator for the A-D Dairy. The operator transfer approval is effective 3/16/09 - jv | X57: R5-2013-0122 | Y57: Active | Z57: 42173 | AA57: 39262 | AB57: 10/02/2018 | AC57: 10 - Confined animal feeding facility | AD57: Lamyae Zinebi | AE57: 1 | AF57: 654 | AG57: Heifers (non dairy affiliated) | AH57: Dairies | AI57: 750 | AJ57: N
A58: 5S | B58: 705519 | C58: Michael Brasil Dairy #2 | D58: Growing | E58: Animal Feeding | F58: Agricultural | G58: Brasil, Michael | H58: Privately-Owned Business | I58: 4971 Van Clief Road | J58: Stevinson | K58: 95374 | L58: Merced | M58: 37.3597 | N58: -120.83239 | O58: Dairy Farms | P58: Dairy Cattle and Milk Production | Q58: ANIWSTCOWS | R58: ANIMALWASTE | S58: 5B24NC00275 | T58: 334902 | U58: Enrollee - WDR | V58: Enrollee Under Dairy Gen Order for Brasil, Michael - Michael Brasil Dairy #2 | W58: CDQAP list shows this facility lost certification as of 9/22/2007. | X58: R5-2013-0122 | Y58: Active | Z58: 43417 | AA58: 39262 | AB58: 10/02/2018 | AC58: 10 - Confined animal feeding facility | AD58: Lamyae Zinebi | AE58: 1 | AF58: 654 | AG58: Mature dairy cattle | AH58: Dairies | AI58: 0 | AJ58: N
A59: 5S | B59: 705523 | C59: F & A Lemos Dairy | D59: Growing | E59: Animal Feeding | F59: Agricultural | G59: Lemos, Frank S & Annette | H59: Privately-Owned Business | I59: 14371 East Avenue | J59: Turlock | K59: 95380 | L59: Merced | M59: 37.49211 | N59: -120.74073 | O59: Dairy Farms | P59: Dairy Cattle and Milk Production | Q59: ANIWSTCOWS | R59: ANIMALWASTE | S59: 5B24NC00280 | T59: 334907 | U59: Enrollee - WDR | V59: Enrollee Under Dairy GO for Lemos, Frank S & Annette - F & A Lemos Dairy | X59: R5-2013-0122 | Y59: Active | Z59: 43417 | AA59: 39262 | AB59: 10/02/2018 | AC59: 10 - Confined animal feeding facility | AD59: Lamyae Zinebi | AE59: 1 | AF59: 654 | AG59: Mature dairy cattle | AH59: Dairies | AI59: 673 | AJ59: N
A60: 5S | B60: 705524 | C60: Alves & Son Dairy #2 | D60: Growing | E60: Animal Feeding | F60: Agricultural | G60: Alves & Son Dairy #2 | H60: Privately-Individual | I60: 13831 East Avenue | J60: Turlock | K60: 95380 | L60: Merced | M60: 37.49183 | N60: -120.73667 | O60: Dairy Farms | P60: Dairy Cattle and Milk Production | Q60: ANIWSTCOWS | R60: ANIMALWASTE | S60: 5B24NC00281 | T60: 334908 | U60: Enrollee - WDR | V60: Enrollee Under Dairy Gen Order for Alves & Son Dairy #2 | W60: 12/14/2020 - Change of owner and operator - AK | X60: R5-2013-0122 | Y60: Active | Z60: 44222 | AA60: 39262 | AB60: 10/02/2018 | AC60: 10 - Confined animal feeding facility | AD60: Lamyae Zinebi | AE60: 1 | AF60: 1308 | AG60: Mature dairy cattle | AH60: Dairies | AI60: 1199 | AJ60: N
A61: 5S | B61: 705526 | C61: Golf Link RanchesLLC | D61: Growing | E61: Animal Feeding | F61: Agricultural | G61: Ahlem, Mark | H61: Privately-Owned Business | I61: 10220 Golf Link Road | J61: Turlock | K61: 95380 | L61: Merced | M61: 37.4362 | N61: -120.83128 | O61: Dairy Farms | Q61: ANIWSTCOWS | R61: ANIMALWASTE | S61: 5B24NC00283 | T61: 334910 | U61: Enrollee - WDR | V61: Enrollee Under Dairy GO for Ahlem, Mark - Golf Link Ranches, LLC | X61: R5-2013-0122 | Y61: Active | Z61: 43417 | AA61: 39262 | AB61: 10/02/2018 | AC61: 10 - Confined animal feeding facility | AD61: Lamyae Zinebi | AE61: 1 | AF61: 1308 | AG61: Heifers (non dairy affiliated) | AH61: Dairies | AI61: 471 | AJ61: N
A62: 5S | B62: 705527 | C62: Triple M Jerseys | D62: Growing | E62: Animal Feeding | F62: Agricultural | G62: Perry, John J. | H62: Privately-Owned Business | I62: 1008 North Verduga Road | J62: Turlock | K62: 95380 | L62: Stanislaus | M62: 37.50211 | N62: -120.80551 | O62: Dairy Farms | P62: Dairy Cattle and Milk Production | Q62: ANIWSTCOWS | R62: ANIMALWASTE | S62: 5B24NC00287 | T62: 334914 | U62: Enrollee - WDR | V62: Enrollee Under Dairy GO for Perry, John J - Triple M Jerseys | W62: 01/31/2021 - Change of operator - AK 3/19/2019 - Removal of Operator Approval. - JY 09/21/2010 - The Board approves the request for operator transfer for Santa Rita Dairy - jv 01/26/10 - The Board approves the request for operator transfer for the Top Of The Line Dairy effective 26 January 2010 - jv 09/17/2009 - The Board approves the request for operator transfer for the John Perry Dairy - jv | X62: R5-2013-0122 | Y62: Active | Z62: 44236 | AA62: 39262 | AB62: 10/02/2018 | AC62: 10 - Confined animal feeding facility | AD62: Lamyae Zinebi | AE62: 1 | AF62: 327 | AG62: Mature dairy cattle | AH62: Dairies | AI62: 150 | AJ62: N
A63: 5S | B63: 705528 | C63: Jose & Teresa Soares Dairy | D63: Growing | E63: Animal Feeding | F63: Agricultural | G63: Soares, Jose and Teresa | H63: Privately-Owned Business | I63: 11076 North Vincent Road | J63: Turlock | K63: 95380 | L63: Merced | M63: 37.45621 | N63: -120.77628 | O63: Dairy Farms | Q63: ANIWSTCOWS | R63: ANIMALWASTE | S63: 5B24NC00288 | T63: 334915 | U63: Enrollee - WDR | V63: Enrollee Under Dairy GO for Soares, Jose & Teresa - Jose & Teresa Soares Dairy | X63: R5-2013-0122 | Y63: Active | Z63: 42173 | AA63: 39262 | AB63: 10/02/2018 | AC63: 10 - Confined animal feeding facility | AD63: Lamyae Zinebi | AE63: 1 | AF63: 1308 | AG63: Mature dairy cattle | AH63: Dairies | AI63: 1380 | AJ63: N
A64: 5S | B64: 705530 | C64: MachadoGabriel&SonsDairy | D64: Growing | E64: Animal Feeding | F64: Agricultural | G64: Machado, Mary | H64: Privately-Owned Business | I64: 12464 South Vincent Road | J64: Turlock | K64: 95380 | L64: Merced | M64: 37.46957 | N64: -120.77565 | O64: Dairy Farms | P64: Dairy Cattle and Milk Production | Q64: ANIWSTCOWS | R64: ANIMALWASTE | S64: 5B24NC00290 | T64: 334917 | U64: Enrollee - WDR | V64: Enrollee Under Dairy GO for Machado, Mary - Machado Gabriel & Sons Dairy | X64: R5-2013-0122 | Y64: Active | Z64: 43417 | AA64: 39262 | AB64: 10/02/2018 | AC64: 10 - Confined animal feeding facility | AD64: Lamyae Zinebi | AE64: 1 | AF64: 654 | AG64: Mature dairy cattle | AH64: Dairies | AI64: 620 | AJ64: Y
A65: 5S | B65: 705775 | C65: Hawkins Ranch | D65: Growing | E65: Animal Feeding | F65: Agricultural | G65: James J. Stevinson, A Corp. | H65: Privately-Owned Business | I65: 5301 North De Angelis Road | J65: Stevinson | K65: 95374 | L65: Merced | M65: 37.36459 | N65: -120.93076 | O65: Dairy Farms | P65: Dairy Cattle and Milk Production | Q65: ANIWSTCOWS | R65: ANIMALWASTE | S65: 5B24NC00333 | T65: 334888 | U65: Enrollee - WDR | V65: Enrollee Under Dairy GO for James J. Stevinson, a Corporation - Hawkins Ranch | W65: New owner and operator 04/26/16 - ak New operator 7-20-14 gc | X65: R5-2013-0122 | Y65: Active | Z65: 43412 | AA65: 39262 | AB65: 10/02/2018 | AC65: 10 - Confined animal feeding facility | AD65: Lamyae Zinebi | AE65: 1 | AF65: 1308 | AG65: Mature dairy cattle | AH65: Dairies | AI65: 315 | AJ65: Y
A66: 5S | B66: 705776 | C66: Silva Dairy Farms #3B | D66: Growing | E66: Animal Feeding | F66: Agricultural | G66: Silva, Manuel | H66: Privately-Owned Business | I66: 1904 Edminster Road | J66: Stevinson | K66: 95374 | L66: Merced | M66: 37.31544 | N66: -120.89665 | O66: Dairy Farms | P66: Dairy Cattle and Milk Production | Q66: ANIWSTCOWS | R66: ANIMALWASTE | S66: 5B24NC00262 | T66: 334889 | U66: Enrollee - WDR | V66: Enrollee Under Dairy GO for Silva, Manuel and George - Silva Dairy Farms #3B | X66: R5-2013-0122 | Y66: Active | Z66: 43412 | AA66: 39262 | AB66: 10/02/2018 | AC66: 10 - Confined animal feeding facility | AD66: Lamyae Zinebi | AE66: 1 | AF66: 1308 | AG66: Heifers (non dairy affiliated) | AH66: Dairies | AI66: 1025 | AJ66: N
A67: 5S | B67: 706122 | C67: AhlemFarmsPartnership | D67: Growing | E67: Animal Feeding | G67: Ahlem Farms Partnership | H67: Privately-Owned Business | I67: 24093 West American Avenue | J67: Hilmar | K67: 95324 | L67: Merced | M67: 37.41194 | N67: -120.92694 | O67: Dairy Farms | P67: Dairy Cattle and Milk Production | Q67: ANIWSTCOWS | R67: ANIMALWASTE | S67: 5B24NC00104 | T67: 334737 | U67: Enrollee - WDR | V67: Enrollee Under Dairy Gen Order for Ahlem Farms Partnership | W67: CDQAP list shows facility lost QA certification as of 9/22/2007 | X67: R5-2013-0122 | Y67: Active | Z67: 42172 | AA67: 39262 | AB67: 10/02/2018 | AC67: 10 - Confined animal feeding facility | AD67: Lamyae Zinebi | AE67: 1 | AF67: 4260 | AG67: Mature dairy cattle | AH67: Dairies | AI67: 3450 | AJ67: Y | AK67: 3450
A68: 5S | B68: 706124 | C68: Vierra Dairy Farms #4 | D68: Growing | E68: Animal Feeding | F68: Agricultural | G68: Old Castile Properties LP | H68: Privately-Owned Business | I68: 25511 West American Avenue | J68: Hilmar | K68: 95322 | L68: Merced | M68: 37.41223 | N68: -120.95089 | O68: Dairy Farms | P68: Dairy Cattle and Milk Production | Q68: ANIWSTCOWS | R68: ANIMALWASTE | S68: 5B24NC00105 | T68: 334738 | U68: Enrollee - WDR | V68: Enrollee Under Dairy Gen Order for Old Castille Properties - Vierra Dairy Farms #4 | W68: 9/21/18 Owner/Operator Transfer - JY 02/16/2018 - the dairy located at 8187 N Prairie Flower Road in Hilmar and the dairy on 25511 W American Avenue have been converted into a single facility with all the animals to be housed at the 25511 W American Avenue facility. | X68: R5-2013-0122 | Y68: Active | Z68: 43367 | AA68: 39262 | AB68: 10/02/2018 | AC68: 10 - Confined animal feeding facility | AD68: Lamyae Zinebi | AE68: 1 | AF68: 654 | AG68: Heifers (non dairy affiliated) | AH68: Dairies | AI68: 200 | AJ68: N
A69: 5S | B69: 706125 | C69: CaliforniaDairyFarms LLC | D69: Growing | E69: Animal Feeding | F69: Agricultural | G69: Forebay Farms, LLC | H69: Privately-Owned Business | I69: 18128 American Avenue | J69: Hilmar | K69: 95324 | L69: Merced | M69: 37.41141 | N69: -120.81532 | O69: Dairy Farms | P69: Dairy Cattle and Milk Production | Q69: ANIWSTCOWS | R69: ANIMALWASTE | S69: 5B24NC00106 | T69: 334739 | U69: Enrollee - WDR | V69: Enrollee Under Dairy Gen Order for Forebay Farms, LLC - California Dairy Farms, LLC | W69: 08/04/2020 - Change of owner and operator - ak | X69: R5-2013-0122 | Y69: Active | Z69: 44453 | AA69: 39262 | AB69: 10/02/2018 | AC69: 10 - Confined animal feeding facility | AD69: Lamyae Zinebi | AE69: 1 | AF69: 1308 | AG69: Mature dairy cattle | AH69: Dairies | AI69: 1500 | AJ69: Y
A70: 5S | B70: 706126 | C70: Larry Peterson Dairy | D70: Growing | E70: Animal Feeding | F70: Agricultural | G70: Peterson, Larry | H70: Privately-Owned Business | I70: 21189 American Avenue | J70: Hilmar | K70: 95324 | L70: Merced | M70: 37.41167 | N70: -120.87187 | O70: Dairy Farms | P70: Dairy Cattle and Milk Production | Q70: ANIWSTCOWS | R70: ANIMALWASTE | S70: 5B24NC00108 | T70: 334741 | U70: Enrollee - WDR | V70: Enrollee Under Dairy GO for Peterson, Larry - Larry Peterson Dairy | X70: R5-2013-0122 | Y70: Active | Z70: 43411 | AA70: 39262 | AB70: 10/02/2018 | AC70: 10 - Confined animal feeding facility | AD70: Lamyae Zinebi | AE70: 1 | AF70: 1308 | AG70: Mature dairy cattle | AH70: Dairies | AI70: 1337 | AJ70: Y
A71: 5S | B71: 706128 | C71: Joe Egli&Sons Dairy | D71: Growing | E71: Animal Feeding | F71: Agricultural | G71: Egli, Joseph | H71: Privately-Owned Business | I71: 21810 West August Avenue | J71: Hilmar | K71: 95324 | L71: Merced | M71: 37.41895 | N71: -120.88239 | O71: Dairy Farms | P71: Dairy Cattle and Milk Production | Q71: ANIWSTCOWS | R71: ANIMALWASTE | S71: 5B24NC00113 | T71: 334746 | U71: Enrollee - WDR | V71: Enrollee Under Dairy GO for Egli, Joseph - Joe Egli and Sons Dairy | X71: R5-2013-0122 | Y71: Active | Z71: 43411 | AA71: 39262 | AB71: 10/02/2018 | AC71: 10 - Confined animal feeding facility | AD71: Lamyae Zinebi | AE71: 1 | AF71: 327 | AG71: Mature dairy cattle | AH71: Dairies | AI71: 298 | AJ71: N
A72: 5S | B72: 706129 | C72: CMA Livestock #2 | D72: Growing | E72: Animal Feeding | F72: Agricultural | G72: Ahlem, Mark | H72: Privately-Owned Business | I72: 23970 West August Avenue | J72: Hilmar | K72: 95324 | L72: Merced | M72: 37.41924 | N72: -120.92159 | O72: Dairy Farms | P72: Dairy Cattle and Milk Production | Q72: ANIWSTCOWS | R72: ANIMALWASTE | S72: 5B24NC00114 | T72: 334747 | U72: Enrollee - WDR | V72: Enrollee Under Dairy GO for Ahlem, Mark - CMA Livestock #2 | X72: R5-2013-0122 | Y72: Active | Z72: 43411 | AA72: 39262 | AB72: 10/02/2018 | AC72: 10 - Confined animal feeding facility | AD72: Lamyae Zinebi | AE72: 1 | AF72: 654 | AG72: Mature dairy cattle | AH72: Dairies | AI72: 184 | AJ72: Y
A73: 5S | B73: 706131 | C73: Valentine Dairy | D73: Growing | E73: Animal Feeding | F73: Agricultural | G73: Jorritsma, Kimberly Clauss | H73: Privately-Individual | I73: 20717 Bloss Avenue | J73: Hilmar | K73: 95324 | L73: Merced | M73: 37.40424 | N73: -120.86221 | O73: Dairy Farms | P73: Dairy Cattle and Milk Production | Q73: ANIWSTCOWS | R73: ANIMALWASTE | S73: 5B24NC00116 | T73: 334749 | U73: Enrollee - WDR | V73: Enrollee Under Dairy GO for Jorritsma, Kimberly Clauss - Valentine Dairy | W73: 10/06/2017 Owner/Operator transfer - JY | X73: R5-2013-0122 | Y73: Active | Z73: 43432 | AA73: 39262 | AB73: 10/02/2018 | AC73: 10 - Confined animal feeding facility | AD73: Lamyae Zinebi | AE73: 1 | AF73: 1308 | AG73: Mature dairy cattle | AH73: Dairies | AI73: 450 | AJ73: Y
A74: 5S | B74: 706132 | C74: CMC Jerseys LLC | D74: Growing | E74: Animal Feeding | F74: Agricultural | G74: Ahlem, Mark | H74: Privately-Owned Business | I74: 23204 Bloss Avenue | J74: Hilmar | K74: 95324 | L74: Merced | M74: 37.40463 | N74: -120.90847 | O74: Dairy Farms | P74: Dairy Cattle and Milk Production | Q74: ANIWSTCOWS | R74: ANIMALWASTE | S74: 5B24NC00117 | T74: 334750 | U74: Enrollee - WDR | V74: Enrollee Under Dairy Gen Order for Ahlem, Mark - CMC Jerseys LLC | X74: R5-2013-0122 | Y74: Active | Z74: 43411 | AA74: 39262 | AB74: 10/02/2018 | AC74: 10 - Confined animal feeding facility | AD74: Lamyae Zinebi | AE74: 1 | AF74: 654 | AG74: Mature dairy cattle | AH74: Dairies | AI74: 700 | AJ74: Y
A75: 5S | B75: 706133 | C75: Fanelli_Fanelli Brothers | D75: Growing | E75: Animal Feeding | F75: Agricultural | G75: Gomes, Joe | H75: Privately-Owned Business | I75: 23839 Bloss Avenue | J75: Hilmar | K75: 95324 | L75: Merced | M75: 37.40471 | N75: -120.91691 | O75: Dairy Farms | P75: Dairy Cattle and Milk Production | Q75: ANIWSTCOWS | R75: ANIMALWASTE | S75: 5B24NC00118 | T75: 334751 | U75: Enrollee - WDR | V75: Enrollee Under Dairy GO for Fanelli Bros Partnership - Fanelli Dairy | X75: R5-2013-0122 | Y75: Active | Z75: 44252 | AA75: 39262 | AB75: 10/02/2018 | AC75: 10 - Confined animal feeding facility | AD75: Lamyae Zinebi | AE75: 1 | AF75: 654 | AG75: Mature dairy cattle | AH75: Dairies | AI75: 351 | AJ75: N
A76: 5S | B76: 706135 | C76: Martins Bros Dairy | D76: Growing | E76: Animal Feeding | F76: Agricultural | G76: Martins, George | H76: Privately-Owned Business | I76: 6041 Central Avenue | J76: Hilmar | K76: 95324 | L76: Merced | M76: 37.3776 | N76: -120.95958 | O76: Dairy Farms | P76: Dairy Cattle and Milk Production | Q76: ANIWSTCOWS | R76: ANIMALWASTE | S76: 5B24NC00122 | T76: 334755 | U76: Enrollee - WDR | V76: Enrollee Under Dairy GO for Martins, George - Martins Bros Dairy | W76: 7/10/2019 - Merger reversal and removal of Mitchell Ranch. - JY 12/18/2018 Sousa Ranch is now merged with this dairy. -JY 12/18/2018 Mitchell Ranch is now merged with this dairy. -JY | X76: R5-2013-0122 | Y76: Active | Z76: 43656 | AA76: 39262 | AB76: 10/02/2018 | AC76: 10 - Confined animal feeding facility | AD76: Lamyae Zinebi | AE76: 1 | AF76: 2725 | AG76: Mature dairy cattle | AH76: Dairies | AI76: 1892 | AJ76: Y
A77: 5S | B77: 706422 | C77: Gomes Heifer Ranch | D77: Growing | E77: Animal Feeding | F77: Agricultural | G77: De Sousa, Armelin & Maria | H77: Privately-Owned Business | I77: 737 South Blaker Road | J77: Turlock | K77: 95380 | L77: Stanislaus | M77: 37.485968 | N77: -120.96743 | O77: Dairy Farms | Q77: ANIWSTCOWS | R77: ANIMALWASTE | S77: 5B50NC00207 | T77: 335240 | U77: Enrollee - WDR | V77: Enrollee Under Dairy GO for de Sousa, Armelin - Gomes Heifer Ranch | W77: 25 June 2012 - the Board approves the transfer of ownership for the Gomes Heifer Ranch effective the date of the letter (jav) | X77: R5-2013-0122 | Y77: Active | Z77: 43439 | AA77: 39262 | AB77: 10/02/2018 | AC77: 10 - Confined animal feeding facility | AD77: Lamyae Zinebi | AE77: 1 | AF77: 327 | AG77: Heifers (non dairy affiliated) | AH77: Dairies | AI77: 295 | AJ77: N
A78: 5S | B78: 706423 | C78: Ed Hirdes Dairy | D78: Growing | E78: Animal Feeding | F78: Agricultural | G78: Hirdes, Edward & Marilyn | H78: Privately-Owned Business | I78: 2131 South Blaker Road | J78: Turlock | K78: 95380 | L78: Stanislaus | M78: 37.47416 | N78: -120.96728 | O78: Dairy Farms | P78: Dairy Cattle and Milk Production | Q78: ANIWSTCOWS | R78: ANIMALWASTE | S78: 5B50NC00208 | T78: 335241 | U78: Enrollee - WDR | V78: Enrollee Under Dairy GO for Hirdes, Edward & Marilyn | X78: R5-2013-0122 | Y78: Active | Z78: 42181 | AA78: 39262 | AB78: 10/02/2018 | AC78: 10 - Confined animal feeding facility | AD78: Lamyae Zinebi | AE78: 1 | AF78: 327 | AG78: Mature dairy cattle | AH78: Dairies | AI78: 225 | AJ78: N
A79: 5S | B79: 706424 | C79: Dematos Dairy | D79: Growing | E79: Animal Feeding | F79: Agricultural | G79: Dematos, Nuno & Marylou | H79: Privately-Individual | I79: 931 South Blaker Road | J79: Turlock | K79: 95380 | L79: Stanislaus | M79: 37.48374 | N79: -120.96961 | O79: Dairy Farms | P79: Dairy Cattle and Milk Production | Q79: ANIWSTCOWS | R79: ANIMALWASTE | S79: 5B50NC00209 | T79: 335242 | U79: Enrollee - WDR | V79: Enrollee Under Dairy GO for Dematos, Nuno & Marylou - Dematos Dairy | W79: 04/16/2021 - Change of Operator - AK 12/12/18 Operator Transfer - JY On 01/05/09, we received a request for operator transfer approval for A-C Vierra Dairy #1. The operator approval was issued effective 03/16/09 - jv CDQAP list shows facility passed QA certification as of 9/22/2007 | X79: R5-2013-0122 | Y79: Active | Z79: 44364 | AA79: 39262 | AB79: 10/02/2018 | AC79: 10 - Confined animal feeding facility | AD79: Lamyae Zinebi | AE79: 1 | AF79: 654 | AG79: Mature dairy cattle | AH79: Dairies | AI79: 610 | AJ79: N
A80: 5S | B80: 706431 | C80: Carlos Estacio&Sons Dairy | D80: Growing | E80: Animal Feeding | F80: Agricultural | G80: Estacio, Carlos F & Maria | H80: Privately-Owned Business | I80: 8900 West Bradbury Road | J80: Turlock | K80: 95380 | L80: Stanislaus | M80: 37.44916 | N80: -120.94999 | O80: Dairy Farms | P80: Dairy Cattle and Milk Production | Q80: ANIWSTCOWS | R80: ANIMALWASTE | S80: 5B50NC00215 | T80: 335248 | U80: Enrollee - WDR | V80: Enrollee Under Dairy GO for Estacio, Carlos F & Maria | X80: R5-2013-0122 | Y80: Active | Z80: 42181 | AA80: 39262 | AB80: 10/02/2018 | AC80: 10 - Confined animal feeding facility | AD80: Lamyae Zinebi | AE80: 1 | AF80: 654 | AG80: Mature dairy cattle | AH80: Dairies | AI80: 160 | AJ80: N
A81: 5S | B81: 706447 | C81: Live Oak Dairy G | D81: Growing | E81: Animal Feeding | F81: Agricultural | G81: Nyman, Brad | H81: Privately-Owned Business | I81: 730 Bystrum | J81: Turlock | K81: 95380 | L81: Stanislaus | M81: 37.494911 | N81: -120.98542 | O81: Dairy Farms | P81: Dairy Cattle and Milk Production | Q81: ANIWSTCOWS | R81: ANIMALWASTE | S81: 5B50NC00323 | T81: 335251 | U81: Enrollee - WDR | V81: Enrollee Under Dairy Gen Order for Nyman, Brad, Live Oak Dairy G | W81: 10/17/2019 - Bovine operation located on Central Ave between August Ave and Williams Ave, Hilmar is now merged with this dairy. - AK | X81: R5-2013-0122 | Y81: Active | Z81: 43760 | AA81: 39262 | AB81: 10/02/2018 | AC81: 10 - Confined animal feeding facility | AD81: Lamyae Zinebi | AE81: 1 | AF81: 1308 | AG81: Mature dairy cattle | AH81: Dairies | AI81: 1350 | AJ81: Y
A82: 5S | B82: 706449 | C82: Verissimo Facility | D82: Growing | E82: Animal Feeding | F82: Agricultural | G82: Machado, Adelina V. | H82: Privately-Individual | I82: 6125 South Central Avenue | J82: Turlock | K82: 95380 | L82: Stanislaus | M82: 37.434336 | N82: -120.96795 | O82: Dairy Farms | P82: Dairy Cattle and Milk Production | Q82: ANIWSTCOWS | R82: ANIMALWASTE | S82: 5B50NC00219 | T82: 335252 | U82: Enrollee - WDR | V82: Enrollee Under Dairy GO for Machado, Adelina V. - Verissimo Facility | W82: 3/19/2019 - Operator Removal Approval. - JY The Board approves the operator transfer for Santos Dairy effective 13 April 2010. As the new operator, John Santos is now authorized to operate the Santos Dairy - jv | X82: R5-2013-0122 | Y82: Active | Z82: 44454 | AA82: 39262 | AB82: 10/02/2018 | AC82: 10 - Confined animal feeding facility | AD82: Lamyae Zinebi | AE82: 1 | AF82: 654 | AG82: Heifers (non dairy affiliated) | AH82: Dairies | AI82: 210 | AJ82: N
A83: 5S | B83: 706450 | C83: Double Cross Dairy | D83: Growing | E83: Animal Feeding | F83: Agricultural | G83: Double Cross Dairy | H83: Privately-Owned Business | I83: 7025 South Central Avenue | J83: Turlock | K83: 95380 | L83: Stanislaus | M83: 37.4285 | N83: -120.9586 | O83: Dairy Farms | P83: Dairy Cattle and Milk Production | Q83: ANIWSTCOWS | R83: ANIMALWASTE | S83: 5B50NC00220 | T83: 335253 | U83: Enrollee - WDR | V83: Enrollee Under Dairy GO for Double Cross Dairy | X83: R5-2013-0122 | Y83: Active | Z83: 42181 | AA83: 39262 | AB83: 10/02/2018 | AC83: 10 - Confined animal feeding facility | AD83: Lamyae Zinebi | AE83: 1 | AF83: 1308 | AG83: Mature dairy cattle | AH83: Dairies | AI83: 888 | AJ83: Y
A84: 5S | B84: 706453 | C84: Double Cross #4 | D84: Growing | E84: Animal Feeding | F84: Agricultural | G84: Chaves, Callie | H84: Privately-Individual | I84: 6006 South Central Avenue | J84: Turlock | K84: 95380 | L84: Stanislaus | M84: 37.43803 | N84: -120.95837 | O84: Dairy Farms | P84: Dairy Cattle and Milk Production | Q84: ANIWSTCOWS | R84: ANIMALWASTE | S84: 5B50NC00222 | T84: 359150 | U84: Enrollee - WDR | V84: Enrollee Under Dairy GO for Chaves, Callie | W84: 11/21/2016 Operator Transfer - ak | X84: R5-2013-0122 | Y84: Active | Z84: 42181 | AA84: 39262 | AB84: 10/02/2018 | AC84: 10 - Confined animal feeding facility | AD84: Lamyae Zinebi | AE84: 1 | AF84: 654 | AG84: Mature dairy cattle | AH84: Dairies | AI84: 0 | AJ84: N
A85: 5S | B85: 706454 | C85: King Dairy | D85: Growing | E85: Animal Feeding | F85: Agricultural | G85: King, Elsie | H85: Privately-Owned Business | I85: 5524 South Central Avenue | J85: Turlock | K85: 95380 | L85: Stanislaus | M85: 37.441996 | N85: -120.95822 | O85: Dairy Farms | P85: Dairy Cattle and Milk Production | Q85: ANIWSTCOWS | R85: ANIMALWASTE | S85: 5B50NC00223 | T85: 335256 | U85: Enrollee - WDR | V85: Enrollee Under Dairy GO for King, Elsie | X85: R5-2013-0122 | Y85: Active | Z85: 42181 | AA85: 39262 | AB85: 10/02/2018 | AC85: 10 - Confined animal feeding facility | AD85: Lamyae Zinebi | AE85: 1 | AF85: 654 | AG85: Mature dairy cattle | AH85: Dairies | AI85: 308 | AJ85: Y
A86: 5S | B86: 706459 | C86: Vieira Livestock | D86: Growing | E86: Animal Feeding | F86: Agricultural | G86: Joe and Christine Vieira | H86: Privately-Individual | I86: 3800 South Central Avenue | J86: Turlock | K86: 95380 | L86: Stanislaus | M86: 37.45829 | N86: -120.95582 | O86: Dairy Farms | P86: Dairy Cattle and Milk Production | Q86: ANIWSTCOWS | R86: ANIMALWASTE | S86: 5B50NC00225 | T86: 335258 | U86: Enrollee - WDR | V86: Enrollee Under Dairy GO for Joe and Christine Vieira | W86: 11-24-15 Facility Owner and Operator has been change from William Katen to Joe and Christine Vieira. -gc Facility Owner and Operator has been change from Joe Bello to William Katen effective 10.23.2012. -Dy | X86: R5-2013-0122 | Y86: Active | Z86: 42346 | AA86: 39262 | AB86: 10/02/2018 | AC86: 10 - Confined animal feeding facility | AD86: Lamyae Zinebi | AE86: 1 | AF86: 654 | AG86: Mature dairy cattle | AH86: Dairies | AI86: 11 | AJ86: N
A87: 5S | B87: 706462 | C87: AldenPeterson&SonsDairy Inc. | D87: Growing | E87: Animal Feeding | F87: Agricultural | G87: Alden Peterson & Sons Dairy Inc | H87: Privately-Owned Business | I87: 1431 North Central Avenue | J87: Turlock | K87: 95380 | L87: Stanislaus | M87: 37.506155 | N87: -120.95858 | O87: Dairy Farms | P87: Dairy Cattle and Milk Production | Q87: ANIWSTCOWS | R87: ANIMALWASTE | S87: 5B50NC00227 | T87: 335260 | U87: Enrollee - WDR | V87: Enrollee Under Dairy Gen Order for Alden Peterson & Sons Dairy Inc. | X87: R5-2013-0122 | Y87: Active | Z87: 42172 | AA87: 39262 | AB87: 10/02/2018 | AC87: 10 - Confined animal feeding facility | AD87: Lamyae Zinebi | AE87: 1 | AF87: 654 | AG87: Mature dairy cattle | AH87: Dairies | AI87: 717 | AJ87: Y
A88: 5S | B88: 706464 | C88: John Nunes Dairy #3 | D88: Growing | E88: Animal Feeding | F88: Agricultural | G88: Brasil, Antonio & Maria | H88: Privately-Owned Business | I88: 5324 Clayton Road | J88: Turlock | K88: 95380 | L88: Stanislaus | M88: 37.48149 | N88: -120.90937 | O88: Dairy Farms | P88: Dairy Cattle and Milk Production | Q88: ANIWSTCOWS | R88: ANIMALWASTE | S88: 5B50NC00228 | T88: 335261 | U88: Enrollee - WDR | V88: Enrollee Under Dairy Gen Order for Brasil, Antonio & Maria, John Nunes Dairy #3 | X88: R5-2013-0122 | Y88: Active | Z88: 42181 | AA88: 39262 | AB88: 10/02/2018 | AC88: 10 - Confined animal feeding facility | AD88: Lamyae Zinebi | AE88: 1 | AF88: 1308 | AG88: Mature dairy cattle | AH88: Dairies | AI88: 790 | AJ88: N
A89: 5S | B89: 706477 | C89: Roestar Dairy | D89: Growing | E89: Animal Feeding | F89: Agricultural | G89: Roest, Aire | H89: Privately-Owned Business | I89: 10407 West Bradbury Road | J89: Turlock | K89: 95380 | L89: Stanislaus | M89: 37.44926 | N89: -120.96781 | O89: Dairy Farms | Q89: ANIWSTCOWS | R89: ANIMALWASTE | S89: 5B50NC00291 | T89: 335324 | U89: Enrollee - WDR | V89: Enrollee Under Dairy GO for Roest, Arie | W89: 10/23/12 - The Board approved the transfer of ow/op for the above dairy. As the new ow/op, Arie Roest is now authorized to own and operate the dairy in compliance with the WDR for Milk Cow Dairies - jv | X89: R5-2013-0122 | Y89: Active | Z89: 42181 | AA89: 39262 | AB89: 10/02/2018 | AC89: 10 - Confined animal feeding facility | AD89: Lamyae Zinebi | AE89: 1 | AF89: 1308 | AG89: Mature dairy cattle | AH89: Dairies | AI89: 1035 | AJ89: Y
A90: 5S | B90: 706496 | C90: Luis M. Azevedo Dairy | D90: Growing | E90: Animal Feeding | F90: Agricultural | G90: Souza, Ray | H90: Privately-Owned Business | I90: 11412 West Main Street | J90: Turlock | K90: 95380 | L90: Stanislaus | M90: 37.49291 | N90: -120.97934 | O90: Dairy Farms | P90: Dairy Cattle and Milk Production | Q90: ANIWSTCOWS | R90: ANIMALWASTE | S90: 5B50NC00252 | T90: 335285 | U90: Enrollee - WDR | V90: Enrollee Under Dairy GO for Souza, Ray | W90: CDQAP list shows facility passed QA certification as of 9/22/2007 | X90: R5-2013-0122 | Y90: Active | Z90: 42181 | AA90: 39262 | AB90: 10/02/2018 | AC90: 10 - Confined animal feeding facility | AD90: Lamyae Zinebi | AE90: 1 | AF90: 1308 | AG90: Mature dairy cattle | AH90: Dairies | AI90: 920 | AJ90: N
A91: 5S | B91: 706497 | C91: Arlinda Holsteins | D91: Growing | E91: Animal Feeding | F91: Agricultural | G91: Vieira, Carl & Laurie | H91: Privately-Owned Business | I91: 6325 West Main Street | J91: Turlock | K91: 95380 | L91: Stanislaus | M91: 37.493892 | N91: -120.92127 | O91: Dairy Farms | P91: Dairy Cattle and Milk Production | Q91: ANIWSTCOWS | R91: ANIMALWASTE | S91: 5B50NC00253 | T91: 335286 | U91: Enrollee - WDR | V91: Enrollee Under Dairy GO for Vieira, Carl and Laurie - Arlinda Holsteins | X91: R5-2013-0122 | Y91: Active | Z91: 42181 | AA91: 39262 | AB91: 10/02/2018 | AC91: 10 - Confined animal feeding facility | AD91: Lamyae Zinebi | AE91: 1 | AF91: 654 | AG91: Mature dairy cattle | AH91: Dairies | AI91: 340 | AJ91: Y
A92: 5S | B92: 706498 | C92: Robert Gioletti & Sons Dairy | D92: Growing | E92: Animal Feeding | F92: Agricultural | G92: Gioletti & Sons Dairy | H92: Privately-Owned Business | I92: 10213 West Main Street | J92: Turlock | K92: 95380 | L92: Stanislaus | M92: 37.493028 | N92: -120.96535 | O92: Dairy Farms | P92: Dairy Cattle and Milk Production | Q92: ANIWSTCOWS | R92: ANIMALWASTE | S92: 5B50NC00254 | T92: 335287 | U92: Enrollee - WDR | V92: Enrollee Under Dairy GO for Robert Gioletti & Sons Dairy | W92: 12/18/2018 Mitchell Heifer Ranch is now merged with this dairy. -JY 10/08/2018 Gioletti Bovine Facility is now merged with this dairy. -JY | X92: R5-2013-0122 | Y92: Active | Z92: 43510 | AA92: 39262 | AB92: 10/02/2018 | AC92: 10 - Confined animal feeding facility | AD92: Lamyae Zinebi | AE92: 1 | AF92: 2725 | AG92: Mature dairy cattle | AH92: Dairies | AI92: 3480 | AJ92: Y
A93: 5S | B93: 706499 | C93: Carl Vieira Dairy | D93: Growing | E93: Animal Feeding | F93: Agricultural | G93: Vieira, Carl & Laurie | H93: Privately-Owned Business | I93: 1000 North Mitchell Road | J93: Turlock | K93: 95380 | L93: Stanislaus | M93: 37.502614 | N93: -120.94035 | O93: Dairy Farms | P93: Dairy Cattle and Milk Production | Q93: ANIWSTCOWS | R93: ANIMALWASTE | S93: 5B50NC00255 | T93: 335288 | U93: Enrollee - WDR | V93: Enrollee Under Dairy GO for Vieira, Carl and Laurie - Carl Vieira Dairy | W93: 6/30/20 Changed address from 1101 N Mitchell to 1000 N Mitchell per CMH and consultant email -ER 02/21/2017 - Merger letter issued combining the dairy at 1518 N Mitchell Rd, Turlock with this dairy - jv CDQAP list shows this facility passed certification as of 9/22/2007 | X93: R5-2013-0122 | Y93: Active | Z93: 44012 | AA93: 39262 | AB93: 10/02/2018 | AC93: 10 - Confined animal feeding facility | AD93: Lamyae Zinebi | AE93: 1 | AF93: 654 | AG93: Mature dairy cattle | AH93: Dairies | AI93: 1360 | AJ93: Y
A94: 5S | B94: 706505 | C94: John Brasil & Sons Dairy | D94: Growing | E94: Animal Feeding | F94: Agricultural | G94: Brasil, John & Maria | H94: Privately-Owned Business | I94: 2613 South Mitchell Road | J94: Turlock | K94: 95380 | L94: Stanislaus | M94: 37.468674 | N94: -120.94009 | O94: Dairy Farms | P94: Dairy Cattle and Milk Production | Q94: ANIWSTCOWS | R94: ANIMALWASTE | S94: 5B50NC00259 | T94: 335292 | U94: Enrollee - WDR | V94: Enrollee Under Dairy Gen Order for Brasil, John & Maria - John Brasil & Sons Dairy | X94: R5-2013-0122 | Y94: Active | Z94: 43528 | AA94: 39262 | AB94: 10/02/2018 | AC94: 10 - Confined animal feeding facility | AD94: Lamyae Zinebi | AE94: 1 | AF94: 1308 | AG94: Mature dairy cattle | AH94: Dairies | AI94: 1200 | AJ94: N
A95: 5S | B95: 706506 | C95: John Brasil Dairy #3 | D95: Growing | E95: Animal Feeding | F95: Agricultural | G95: Brasil, John & Maria | H95: Privately-Owned Business | I95: 1707 South Mitchell Road | J95: Turlock | K95: 95380 | L95: Stanislaus | M95: 37.476967 | N95: -120.94016 | O95: Dairy Farms | Q95: ANIWSTCOWS | R95: ANIMALWASTE | S95: 5B50NC00260 | T95: 335293 | U95: Enrollee - WDR | V95: Enrollee Under Dairy GO for John Brasil, John Brasil Dairy #3 | W95: 12/20/2018 Heifer Feedlot located at 2230 S Mitchell Road, Turlock is now merged with this dairy. -JY | X95: R5-2013-0122 | Y95: Active | Z95: 43579 | AA95: 39262 | AB95: 10/02/2018 | AC95: 10 - Confined animal feeding facility | AD95: Lamyae Zinebi | AE95: 2 | AF95: 654 | AG95: Mature dairy cattle | AH95: Dairies | AI95: 620 | AJ95: Y
A96: 5S | B96: 706508 | C96: KMA Dairy | D96: Growing | E96: Animal Feeding | F96: Agricultural | G96: Souza, Ray | H96: Privately-Owned Business | I96: 539 South Morgan Road | J96: Turlock | K96: 95380 | L96: Stanislaus | M96: 37.487873 | N96: -120.97635 | O96: Dairy Farms | Q96: ANIWSTCOWS | R96: ANIMALWASTE | S96: 5B50NC00263 | T96: 335296 | U96: Enrollee - WDR | V96: Enrollee Under Dairy GO for Souza, Ray - KMA Dairy | W96: 10/06/2017 - Op. has changed - ak 04/04/2017 - Op. has changed - ak The Board has approved the transfer of Ray Souza as the owner and operator for the Dairy at 539 S. Morgan Road, Turlock as of 25 June 2012. -Dy | X96: R5-2013-0122 | Y96: Active | Z96: 43375 | AA96: 39262 | AB96: 10/02/2018 | AC96: 10 - Confined animal feeding facility | AD96: Lamyae Zinebi | AE96: 1 | AF96: 654 | AG96: Mature dairy cattle | AH96: Dairies | AI96: 300 | AJ96: N
A97: 5S | B97: 706509 | C97: Sallaberry Ranch | D97: Growing | E97: Animal Feeding | F97: Agricultural | G97: S & D Bylsma Dairy | H97: Privately-Owned Business | I97: 5608 South Morgan Road | J97: Turlock | K97: 95380 | L97: Stanislaus | M97: 37.440521 | N97: -120.97649 | O97: Dairy Farms | Q97: ANIWSTCOWS | R97: ANIMALWASTE | S97: 5B50NC00264 | T97: 335297 | U97: Enrollee - WDR | V97: Enrollee Under Dairy GO for S & D Bylsma Dairy - Sallaberry Ranch | W97: 10/19/18 - Owner/Operator Transfer - JY | X97: R5-2013-0122 | Y97: Active | Z97: 43392 | AA97: 39262 | AB97: 10/02/2018 | AC97: 10 - Confined animal feeding facility | AD97: Lamyae Zinebi | AE97: 1 | AF97: 654 | AG97: Heifers (non dairy affiliated) | AH97: Dairies | AI97: 425 | AJ97: N
A98: 5S | B98: 706510 | C98: Alfred C Nunes Dairy | D98: Growing | E98: Animal Feeding | F98: Agricultural | G98: Nunes, Alfred & Celia | H98: Privately-Owned Business | I98: 5119 South Morgan Road | J98: Turlock | K98: 95380 | L98: Stanislaus | M98: 37.445446 | N98: -120.97646 | O98: Dairy Farms | P98: Dairy Cattle and Milk Production | Q98: ANIWSTCOWS | R98: ANIMALWASTE | S98: 5B50NC00265 | T98: 335298 | U98: Enrollee - WDR | V98: Enrollee Under Dairy GO for Nunes, Alfredo C & Celia | X98: R5-2013-0122 | Y98: Active | Z98: 42181 | AA98: 39262 | AB98: 10/02/2018 | AC98: 10 - Confined animal feeding facility | AD98: Lamyae Zinebi | AE98: 1 | AF98: 1308 | AG98: Mature dairy cattle | AH98: Dairies | AI98: 1015 | AJ98: N
A99: 5S | B99: 706512 | C99: Jim Vieira & Son Dairy | D99: Growing | E99: Animal Feeding | F99: Agricultural | G99: Vieira, Jim & Donna | H99: Privately-Owned Business | I99: 2401 Newman Road | J99: Turlock | K99: 95380 | L99: Stanislaus | M99: 37.47041 | N99: -120.9277 | O99: Dairy Farms | P99: Dairy Cattle and Milk Production | Q99: ANIWSTCOWS | R99: ANIMALWASTE | S99: 5B50NC00267 | T99: 335300 | U99: Enrollee - WDR | V99: Enrollee Under Dairy GO for Viera, Jim and Donna | X99: R5-2013-0122 | Y99: Active | Z99: 42181 | AA99: 39262 | AB99: 10/02/2018 | AC99: 10 - Confined animal feeding facility | AD99: Lamyae Zinebi | AE99: 1 | AF99: 654 | AG99: Mature dairy cattle | AH99: Dairies | AI99: 635 | AJ99: N
A100: 5S | B100: 706513 | C100: Ehrlich Dairy | D100: Growing | E100: Animal Feeding | F100: Agricultural | G100: Schortzmann, Brittney | H100: Privately-Individual | I100: 5725 Ehrlich Road | J100: Turlock | K100: 95380 | L100: Stanislaus | M100: 37.433848 | N100: -120.91535 | O100: Dairy Farms | P100: Dairy Cattle and Milk Production | Q100: ANIWSTCOWS | R100: ANIMALWASTE | S100: 5B50NC00231 | T100: 335264 | U100: Enrollee - WDR | V100: Enrollee Under Dairy GO for Schortzmann, Brittney - Ehrlich Dairy | X100: R5-2013-0122 | Y100: Active | Z100: 42181 | AA100: 39262 | AB100: 10/02/2018 | AC100: 10 - Confined animal feeding facility | AD100: Lamyae Zinebi | AE100: 1 | AF100: 1308 | AG100: Mature dairy cattle | AH100: Dairies | AI100: 822 | AJ100: N
...

Sheet Input
A1: FACILITY ID | B1: ='A & M De Souza Dairy'!B1 -> 203907 | C1: ='Silva Dairy Farms #3A'!B1 -> 209495 | D1: ='Joe Borba Dairy Inc.'!B1 -> 210049 | E1: ='Ken Van Foeken Dairy #2'!B1 -> 218891 | F1: ='Da Rosa Dairy'!B1 -> 218992 | G1: ='J_D Brasil Dairy'!#REF! -> #REF! | H1: ='River Rock Ranch LLC'!L1 -> 220560 | I1: ='Double Cross #3'!L1 -> 221709 | J1: ='Edward Nunes Dairy'!L1 -> 222320 | K1: ='Gomes Dairy'!#REF! -> #REF! | L1: ='Roest Family Dairy'!L1 -> 226601 | M1: ='Gil Tex Dairy'!L1 -> 227158 | N1: ='GJ Silva'!L1 -> 227211 | O1: ='Hilmar Holsteins Inc.'!L1 -> 230428 | P1: ='Jordao Dairy'!L1 -> 233735 | Q1: ='Cross Creek Dairy'!L1 -> 233749 | R1: ='Double Cross #2'!L1 -> 233757 | S1: ='LarryPetersonDairyFarms#2'!L1 -> 233895 | T1: ='Fire_Lake Jerseys #2'!L1 -> 233934 | U1: ='Lumar Dairy Farms'!L1 -> 237694 | V1: ='CMA Livestock'!L1 -> 239367 | W1: ='Fire Lakes Jerseys'!L1 -> 251780 | X1: ='Rick Jones Farms'!L1 -> 252667 | Y1: ='Silveira Holsteins'!L1 -> 257092 | Z1: ='Diamond B Dairy'!L1 -> 263088 | AA1: ='Azevedo Dairy'!L1 -> 264484 | AB1: ='Valsigna Dairy'!L1 -> 272502 | AC1: =WickstromJerseyFarmsInc.!L1 -> 705196 | AD1: ='Diniz Dairy'!L1 -> 705203 | AE1: ='Crane Dairy Inc.'!L1 -> 705219 | AF1: ='GM Silva Dairies #2'!L1 -> 705229 | AG1: ='Joe Oliveira Dairy'!#REF! -> #REF! | AH1: ='Vierra Dairy Farms #3'!L1 -> 705238 | AI1: ='Nelson Dairy'!L1 -> 705241 | AJ1: ='Mario&ChristinaNunesDairy'!L1 -> 705247 | AK1: ='B & D Dairy'!L1 -> 705274 | AL1: ='Silveira Dairy Inc.'!L1 -> 705276 | AM1: ='Jade Jersey Dairy'!L1 -> 705277 | AN1: ='Live Oak Dairy A'!L1 -> 705279 | AO1: ='T & M Borba Dairy'!L1 -> 705281 | AP1: ='Oslo Dairy'!L1 -> 705283 | AQ1: ='Kronberg Facility'!L1 -> 705286 | AR1: ='Ken Van Foeken Dairy'!L1 -> 705288 | AS1: ='Amaral Dairy Farms'!L1 -> 705290 | AT1: ='B_6 Dairy'!L1 -> 705294 | AU1: ='6D Dores Dairy'!L1 -> 705296 | AV1: ='Fanelli Dairy'!L1 -> 705297 | AW1: ='Joao Sousa Dairy'!L1 -> 705298 | AX1: ='Vierra Dairy Farms #2'!L1 -> 705300 | AY1: ='Michael Brasil Dairy'!L1 -> 705503 | AZ1: ='Anchor J Dairy'!L1 -> 705505 | BA1: ='Oliveira Dairy'!L1 -> 705508 | BB1: ='Souza Bros Dairy'!L1 -> 705510 | BC1: ='Miguel Family Dairy'!L1 -> 705512 | BD1: ='Dias Family Dairy'!L1 -> 705514 | BE1: ='Empty was A_D Dairy'!L1 -> 705515 | BF1: ='Michael Brasil Dairy #2'!L1 -> 705519 | BG1: ='F & A Lemos Dairy'!L1 -> 705523 | BH1: ='Alves & Son Dairy #2'!L1 -> 705524 | BI1: ='Golf Link RanchesLLC'!L1 -> 705526 | BJ1: ='Triple M Jerseys'!L1 -> 705527 | BK1: ='Jose & Teresa Soares Dairy'!L1 -> 705528 | BL1: ='MachadoGabriel&SonsDairy'!L1 -> 705530 | BM1: ='Hawkins Ranch'!L1 -> 705775 | BN1: ='Silva Dairy Farms #3B'!L1 -> 705776 | BO1: =AhlemFarmsPartnership!L1 -> 706122 | BP1: ='Vierra Dairy Farms #4'!L1 -> 706124 | BQ1: ='CaliforniaDairyFarms LLC'!L1 -> 706125 | BR1: ='Larry Peterson Dairy'!L1 -> 706126 | BS1: ='Joe Egli&Sons Dairy'!L1 -> 706128 | BT1: ='CMA Livestock #2'!L1 -> 706129 | BU1: ='Valentine Dairy'!L1 -> 706131 | BV1: ='CMC Jerseys LLC'!L1 -> 706132 | BW1: ='Fanelli_Fanelli Brothers'!L1 -> 706133 | BX1: ='Martins Bros Dairy'!L1 -> 706135 | BY1: ='Gomes Heifer Ranch'!L1 -> 706422 | BZ1: ='Ed Hirdes Dairy'!B1 -> 706423 | CA1: ='Dematos Dairy'!L1 -> 706424 | CB1: ='Carlos Estacio&Sons Dairy'!L1 -> 706431 | CC1: ='Live Oak Dairy G'!L1 -> 706447 | CD1: ='Verissimo Facility'!L1 -> 706449 | CE1: ='Double Cross Dairy'!L1 -> 706450 | CF1: ='Double Cross #4'!L1 -> 706453 | CG1: ='King Dairy'!L1 -> 706454 | CH1: ='Vieira Livestock'!L1 -> 706459 | CI1: ='AldenPeterson&SonsDairy Inc.'!L1 -> 706462 | CJ1: ='John Nunes Dairy #3'!L1 -> 706464 | CK1: ='Roestar Dairy'!L1 -> 706477 | CL1: ='Luis M. Azevedo Dairy'!L1 -> 706496 | CM1: ='Arlinda Holsteins'!L1 -> 706497 | CN1: ='Robert Gioletti & Sons Dairy'!L1 -> 706498 | CO1: ='Carl Vieira Dairy'!L1 -> 706499 | CP1: ='John Brasil & Sons Dairy'!L1 -> 706505 | CQ1: ='John Brasil Dairy #3'!L1 -> 706506 | CR1: ='KMA Dairy'!L1 -> 706508 | CS1: ='Sallaberry Ranch'!L1 -> 706509 | CT1: ='Alfred C Nunes Dairy'!L1 -> 706510 | CU1: ='Jim Vieira & Son Dairy'!L1 -> 706512 | CV1: ='Ehrlich Dairy'!L1 -> 706513 | CW1: ='D&A Brasil Facility'!B1 -> 706514 | CX1: ='Silva''s Holsteins'!B1 -> 706515 | CY1: ='G J Silva #3'!B1 -> 706518 | CZ1: ='Jim Vieira and Son Dairy #2'!L1 -> 706519 | DA1: ='Johal Dairy'!L1 -> 706520 | DB1: ='A & G Azevedo Dairy'!L1 -> 706522 | DC1: ='Gentle Breezes Dairy'!L1 -> 706524 | DD1: ='Joe Sousa Jr Dairy'!L1 -> 706527 | DE1: ='John Brasil Heifers'!L1 -> 706529 | DF1: ='MHF Dairy'!L1 -> 706533 | DG1: ='Brindiero&DanbomDairyFarms'!L1 -> 706536 | DH1: ='A&C Machado Dairy #2'!L1 -> 706539 | DI1: ='J & J Toste DairyInc.'!L1 -> 706549 | DJ1: ='Bar Vee DairyInc.'!L1 -> 706551 | DK1: ='Railside Jersey FarmsLLC'!L1 -> 706555 | DL1: ='Manuel Azevedo Dairy'!L1 -> 706556 | DM1: ='Sousa Family Dairy'!L1 -> 706558 | DN1: ='UC Davis Animal Science Dairy'!L1 -> 706578 | DO1: ='Garcia''s Registered Jerseys'!L1 -> 706579 | DP1: ='Lucio Corral Cattle'!L1 -> 706582 | DQ1: ='Wickstrom Dairy Inc'!B1 -> 706583 | DR1: ='Sam Kooistra Dairy'!L1 -> 706584 | DS1: ='Vitorino & Sons Dairy'!L1 -> 706586 | DT1: ='Valley Cross Dairy'!L1 -> 706587 | DU1: ='John Brasil & Sons Dairy #2'!L1 -> 706588 | DV1: ='Pepper Dairy'!L1 -> 706945 | DW1: ='Clauss Dairy Farms'!L1 -> 726796 | DX1: ='Dairy Central Heifers'!L1 -> 727868 | DY1: ='Yosemite Jersey Dairy'!L1 -> 727901 | DZ1: ='Sunwest Jersey Dairy'!L1 -> 730625 | EA1: ='N & C Silveira Dairy'!L1 -> 730634 | EB1: ='Nyman Brothers Dairy'!L1 -> 735382 | EC1: ='Broder Farms'!L1 -> 736896 | ED1: ='Borba Dairy Farms'!L1 -> 736922 | EE1: ='Charles Ahlem Ranch'!L1 -> 743935 | EF1: ='James Ahlem Dairy'!L1 -> 743941 | EG1: ='Nylund Dairy Farms'!L1 -> 743944 | EH1: ='Vierra Ranch Dairy'!L1 -> 743948 | EI1: ='Joe O Rocha Dairy Inc.'!L1 -> 745165 | EJ1: ='Alves & Son Dairy'!L1 -> 745172 | EK1: ='3A Teixeira Dairy'!L1 -> 745179 | EL1: ='Denizma_Bud Postma Dairy'!L1 -> 745430 | EM1: ='Couco Creek Dairy'!L1 -> 782059 | EN1: ='Clausen Dairy'!L1 -> 810786
A2: FACILITY NAME | B2: ='A & M De Souza Dairy'!B2 -> A & M De Souza Dairy | C2: ='Silva Dairy Farms #3A'!B2 -> Silva Dairy Farms #3A | D2: ='Joe Borba Dairy Inc.'!B2 -> Joe Borba Dairy, Inc. | E2: ='Ken Van Foeken Dairy #2'!B2 -> Ken Van Foeken Dairy #2 | F2: ='Da Rosa Dairy'!B2 -> Da Rosa Dairy | G2: ='J_D Brasil Dairy'!#REF! -> #REF! | H2: ='River Rock Ranch LLC'!L2 -> River Rock Ranch, LLC | I2: ='Double Cross #3'!L2 -> Double Cross #3 | J2: ='Edward Nunes Dairy'!L2 -> Edward Nunes Dairy | K2: ='Gomes Dairy'!#REF! -> #REF! | L2: ='Roest Family Dairy'!L2 -> Roest Family Dairy | M2: ='Gil Tex Dairy'!L2 -> Gil Tex Dairy | N2: ='GJ Silva'!L2 -> GJ Silva | O2: ='Hilmar Holsteins Inc.'!L2 -> Hilmar Holsteins, Inc. | P2: ='Jordao Dairy'!L2 -> Jordao Dairy | Q2: ='Cross Creek Dairy'!L2 -> Vierra Dairy LLC #4 | R2: ='Double Cross #2'!L2 -> Double Cross #2 | S2: ='LarryPetersonDairyFarms#2'!L2 -> Larry B. Peterson Dairy Farms #2 | T2: ='Fire_Lake Jerseys #2'!L2 -> Fire-Lake Jerseys #2 | U2: ='Lumar Dairy Farms'!L2 -> Lumar Dairy Farms | V2: ='CMA Livestock'!L2 -> Double Cross #5 | W2: ='Fire Lakes Jerseys'!L2 -> Fire Lakes Jerseys | X2: ='Rick Jones Farms'!L2 -> Rick Jones Farms | Y2: ='Silveira Holsteins'!L2 -> Silveira Holsteins | Z2: ='Diamond B Dairy'!L2 -> Diamond B Dairy | AA2: ='Azevedo Dairy'!L2 -> Azevedo Dairy | AB2: ='Valsigna Dairy'!L2 -> Valsigna Dairy | AC2: =WickstromJerseyFarmsInc.!L2 -> Wickstrom Jersey Farms, Inc. | AD2: ='Diniz Dairy'!L2 -> Diniz Dairy | AE2: ='Crane Dairy Inc.'!L2 -> Crane Dairy, Inc. | AF2: ='GM Silva Dairies #2'!L2 -> GM Silva Dairies #2 | AG2: ='Joe Oliveira Dairy'!#REF! -> #REF! | AH2: ='Vierra Dairy Farms #3'!L2 -> Vierra Dairy Farms #3 | AI2: ='Nelson Dairy'!L2 -> Nelson Dairy | AJ2: ='Mario&ChristinaNunesDairy'!L2 -> Luis & Maria Jorge Dairy | AK2: ='B & D Dairy'!L2 -> B & D Dairy | AL2: ='Silveira Dairy Inc.'!L2 -> Live Oak Dairy H | AM2: ='Jade Jersey Dairy'!L2 -> Jade Jersey Dairy | AN2: ='Live Oak Dairy A'!L2 -> Live Oak Dairy A | AO2: ='T & M Borba Dairy'!L2 -> T & M Borba Dairy | AP2: ='Oslo Dairy'!L2 -> Oslo Dairy | AQ2: ='Kronberg Facility'!L2 -> Kronberg Facility | AR2: ='Ken Van Foeken Dairy'!L2 -> Ken Van Foeken Dairy | AS2: ='Amaral Dairy Farms'!L2 -> Amaral Dairy Farms | AT2: ='B_6 Dairy'!L2 -> B-6 Dairy | AU2: ='6D Dores Dairy'!L2 -> 6D Dores Dairy | AV2: ='Fanelli Dairy'!L2 -> Fanelli Dairy | AW2: ='Joao Sousa Dairy'!L2 -> Joao Sousa Dairy | AX2: ='Vierra Dairy Farms #2'!L2 -> Vierra Dairy Farms #2 | AY2: ='Michael Brasil Dairy'!L2 -> Borba Cattle Company, LP | AZ2: ='Anchor J Dairy'!L2 -> Anchor J Dairy | BA2: ='Oliveira Dairy'!L2 -> Oliveira Dairy | BB2: ='Souza Bros Dairy'!L2 -> Souza Bros Dairy | BC2: ='Miguel Family Dairy'!L2 -> Miguel Family Dairy | BD2: ='Dias Family Dairy'!L2 -> Dias Family Dairy | BE2: ='Empty was A_D Dairy'!L2 -> Empty (was A-D Dairy) | BF2: ='Michael Brasil Dairy #2'!L2 -> Michael Brasil Dairy #2 | BG2: ='F & A Lemos Dairy'!L2 -> F & A Lemos Dairy | BH2: ='Alves & Son Dairy #2'!L2 -> Alves & Son Dairy #2 | BI2: ='Golf Link RanchesLLC'!L2 -> Golf Link Ranches, LLC | BJ2: ='Triple M Jerseys'!L2 -> Triple M Jerseys | BK2: ='Jose & Teresa Soares Dairy'!L2 -> Jose & Teresa Soares Dairy | BL2: ='MachadoGabriel&SonsDairy'!L2 -> Machado Gabriel & Sons Dairy | BM2: ='Hawkins Ranch'!L2 -> Hawkins Ranch | BN2: ='Silva Dairy Farms #3B'!L2 -> Silva Dairy Farms #3B | BO2: =AhlemFarmsPartnership!L2 -> Ahlem Farms Partnership | BP2: ='Vierra Dairy Farms #4'!L2 -> Vierra Heifer Ranch (Dairy) | BQ2: ='CaliforniaDairyFarms LLC'!L2 -> California Dairy Farms, LLC | BR2: ='Larry Peterson Dairy'!L2 -> Double Cross #6 | BS2: ='Joe Egli&Sons Dairy'!L2 -> Joe Egli and Sons Dairy | BT2: ='CMA Livestock #2'!L2 -> CMA Livestock #2 | BU2: ='Valentine Dairy'!L2 -> Valentine Dairy | BV2: ='CMC Jerseys LLC'!L2 -> CMC Jerseys LLC | BW2: ='Fanelli_Fanelli Brothers'!L2 -> Fanelli Dairy - Fanelli Brothers | BX2: ='Martins Bros Dairy'!L2 -> Martins Bros Dairy | BY2: ='Gomes Heifer Ranch'!L2 -> Blaker Heifer Ranch | BZ2: ='Ed Hirdes Dairy'!B2 -> Ed Hirdes Dairy | CA2: ='Dematos Dairy'!L2 -> Dematos Dairy | CB2: ='Carlos Estacio&Sons Dairy'!L2 -> Carlos Estacio & Sons Dairy | CC2: ='Live Oak Dairy G'!L2 -> Live Oak Dairy G | CD2: ='Verissimo Facility'!L2 -> Verissimo Facility | CE2: ='Double Cross Dairy'!L2 -> Double Cross Dairy | CF2: ='Double Cross #4'!L2 -> Double Cross #4 | CG2: ='King Dairy'!L2 -> King Dairy | CH2: ='Vieira Livestock'!L2 -> Vieira Livestock | CI2: ='AldenPeterson&SonsDairy Inc.'!L2 -> Alden Peterson & Sons Dairy, Inc. | CJ2: ='John Nunes Dairy #3'!L2 -> S & S 2 Dairy | CK2: ='Roestar Dairy'!L2 -> Roestar Dairy | CL2: ='Luis M. Azevedo Dairy'!L2 -> Luis M. Azevedo Dairy | CM2: ='Arlinda Holsteins'!L2 -> Arlinda Holsteins | CN2: ='Robert Gioletti & Sons Dairy'!L2 -> Robert Gioletti & Sons Dairy | CO2: ='Carl Vieira Dairy'!L2 -> Carl Vieira Dairy | CP2: ='John Brasil & Sons Dairy'!L2 -> John Brasil & Sons Dairy | CQ2: ='John Brasil Dairy #3'!L2 -> John Brasil Dairy #3 | CR2: ='KMA Dairy'!L2 -> KMA Dairy | CS2: ='Sallaberry Ranch'!L2 -> Sallaberry Ranch | CT2: ='Alfred C Nunes Dairy'!L2 -> Alfred C Nunes Dairy | CU2: ='Jim Vieira & Son Dairy'!L2 -> GJC Dairy, Inc. | CV2: ='Ehrlich Dairy'!L2 -> Ehrlich Dairy | CW2: ='D&A Brasil Facility'!B2 -> D&A Brasil Facility | CX2: ='Silva''s Holsteins'!B2 -> Silva's Holsteins | CY2: ='G J Silva #3'!B2 -> #N/A | CZ2: ='Jim Vieira and Son Dairy #2'!L2 -> Jim Vieira and Son Dairy #2 | DA2: ='Johal Dairy'!L2 -> Johal Dairy | DB2: ='A & G Azevedo Dairy'!L2 -> A & G Azevedo Dairy | DC2: ='Gentle Breezes Dairy'!L2 -> Gentle Breezes Dairy | DD2: ='Joe Sousa Jr Dairy'!L2 -> Joe Sousa Feedlot | DE2: ='John Brasil Heifers'!L2 -> Reis Dairy | DF2: ='MHF Dairy'!L2 -> MHF Dairy | DG2: ='Brindiero&DanbomDairyFarms'!L2 -> Brindiero & Danbom Dairy Farms | DH2: ='A&C Machado Dairy #2'!L2 -> A&C Machado Dairy #2 | DI2: ='J & J Toste DairyInc.'!L2 -> J & J Toste Dairy, Inc. | DJ2: ='Bar Vee DairyInc.'!L2 -> Bar Vee Dairy, Inc. | DK2: ='Railside Jersey FarmsLLC'!L2 -> Cal Farm House | DL2: ='Manuel Azevedo Dairy'!L2 -> Manuel Azevedo Dairy | DM2: ='Sousa Family Dairy'!L2 -> Sousa Family Dairy | DN2: ='UC Davis Animal Science Dairy'!L2 -> UC Davis Animal Science Dairy | DO2: ='Garcia''s Registered Jerseys'!L2 -> Garcia's Registered Jerseys | DP2: ='Lucio Corral Cattle'!L2 -> Lucio Corral Cattle | DQ2: ='Wickstrom Dairy Inc'!B2 -> Wickstrom Dairy Inc | DR2: ='Sam Kooistra Dairy'!L2 -> Sam Kooistra Dairy | DS2: ='Vitorino & Sons Dairy'!L2 -> Vitorino & Sons Dairy | DT2: ='Valley Cross Dairy'!L2 -> Valley Cross Dairy | DU2: ='John Brasil & Sons Dairy #2'!L2 -> John Brasil & Sons Dairy #2 | DV2: ='Pepper Dairy'!L2 -> Pepper Dairy | DW2: ='Clauss Dairy Farms'!L2 -> Clauss Dairy Farms | DX2: ='Dairy Central Heifers'!L2 -> Dairy Central Heifers | DY2: ='Yosemite Jersey Dairy'!L2 -> River Rock Ranch, LLC | DZ2: ='Sunwest Jersey Dairy'!L2 -> Sunwest Jersey Dairy | EA2: ='N & C Silveira Dairy'!L2 -> N & C Silveira Dairy | EB2: ='Nyman Brothers Dairy'!L2 -> Nyman Brothers Dairy | EC2: ='Broder Farms'!L2 -> Broder Farms | ED2: ='Borba Dairy Farms'!L2 -> Borba Dairy Farms | EE2: ='Charles Ahlem Ranch'!L2 -> Charles Ahlem Ranch | EF2: ='James Ahlem Dairy'!L2 -> Gold Medal Ag #1 Dairy | EG2: ='Nylund Dairy Farms'!L2 -> Nylund Dairy Farms | EH2: ='Vierra Ranch Dairy'!L2 -> Vierra Ranch Dairy | EI2: ='Joe O Rocha Dairy Inc.'!L2 -> Joe O Rocha Dairy Inc. | EJ2: ='Alves & Son Dairy'!L2 -> Alves & Son Dairy | EK2: ='3A Teixeira Dairy'!L2 -> 3A Teixeira Dairy | EL2: ='Denizma_Bud Postma Dairy'!L2 -> Denizma Dairy / Bud Postma Dairy | EM2: ='Couco Creek Dairy'!L2 -> Couco Creek Dairy | EN2: ='Clausen Dairy'!L2 -> Clausen Dairy
A3: PLACE ADDRESS | B3: ='A & M De Souza Dairy'!B3 -> 3030 South Central Avenue | C3: ='Silva Dairy Farms #3A'!B3 -> 1499 North Edminster Road | D3: ='Joe Borba Dairy Inc.'!B3 -> 3431 South Moffett Road | E3: ='Ken Van Foeken Dairy #2'!B3 -> 9375 North Washington Road | F3: ='Da Rosa Dairy'!B3 -> 1131 Story Road | G3: ='J_D Brasil Dairy'!#REF! -> #REF! | H3: ='River Rock Ranch LLC'!L3 -> 22846 West Second Avenue | I3: ='Double Cross #3'!L3 -> 11071 Youngstown Road | J3: ='Edward Nunes Dairy'!L3 -> 17399 East Avena Road | K3: ='Gomes Dairy'!#REF! -> #REF! | L3: ='Roest Family Dairy'!L3 -> 2472 Gates Road | M3: ='Gil Tex Dairy'!L3 -> 5601 Mountain View Road | N3: ='GJ Silva'!L3 -> 3107 South Prairie Flower Road | O3: ='Hilmar Holsteins Inc.'!L3 -> 21859 Crane Avenue | P3: ='Jordao Dairy'!L3 -> 6025 South Central Avenue | Q3: ='Cross Creek Dairy'!L3 -> 7965 Washington Road | R3: ='Double Cross #2'!L3 -> 18637 East Bradbury Road | S3: ='LarryPetersonDairyFarms#2'!L3 -> 20775 West American Avenue | T3: ='Fire_Lake Jerseys #2'!L3 -> 10408 West Bradbury Road | U3: ='Lumar Dairy Farms'!L3 -> 7215 South Prairie Flower Road | V3: ='CMA Livestock'!L3 -> 19051 West Williams Avenue | W3: ='Fire Lakes Jerseys'!L3 -> 11301 West Bradbury Road | X3: ='Rick Jones Farms'!L3 -> 1511 Van Clief Road | Y3: ='Silveira Holsteins'!L3 -> 23356 Short Avenue | Z3: ='Diamond B Dairy'!L3 -> 3137 East Tuolumne Road | AA3: ='Azevedo Dairy'!L3 -> 21480 August Avenue | AB3: ='Valsigna Dairy'!L3 -> 6071 North Larson Avenue | AC3: =WickstromJerseyFarmsInc.!L3 -> 5638 Columbus Avenue | AD3: ='Diniz Dairy'!L3 -> 9558 Columbus Avenue | AE3: ='Crane Dairy Inc.'!L3 -> 20633 West Crane Avenue | AF3: ='GM Silva Dairies #2'!L3 -> 20316 West Crane Avenue | AG3: ='Joe Oliveira Dairy'!#REF! -> #REF! | AH3: ='Vierra Dairy Farms #3'!L3 -> 7884 Faith Home Road | AI3: ='Nelson Dairy'!L3 -> 19481 Geer Avenue | AJ3: ='Mario&ChristinaNunesDairy'!L3 -> 21625 Geer Avenue | AK3: ='B & D Dairy'!L3 -> 9579 Hultberg Road | AL3: ='Silveira Dairy Inc.'!L3 -> 20271 Johnson Avenue | AM3: ='Jade Jersey Dairy'!L3 -> 20326 Johnson Avenue | AN3: ='Live Oak Dairy A'!L3 -> 21052 Johnson Avenue | AO3: ='T & M Borba Dairy'!L3 -> 6275 Mitchell Road | AP3: ='Oslo Dairy'!L3 -> 20334 West Oslo Road | AQ3: ='Kronberg Facility'!L3 -> 20777 Riverside Avenue | AR3: ='Ken Van Foeken Dairy'!L3 -> 22338 Short Avenue | AS3: ='Amaral Dairy Farms'!L3 -> 7706 Tegner Road | AT3: ='B_6 Dairy'!L3 -> 22014 Turner Avenue | AU3: ='6D Dores Dairy'!L3 -> 25762 Turner Avenue | AV3: ='Fanelli Dairy'!L3 -> 7689 Washington Road | AW3: ='Joao Sousa Dairy'!L3 -> 18005 Williams Avenue | AX3: ='Vierra Dairy Farms #2'!L3 -> 22682 West Williams Avenue | AY3: ='Michael Brasil Dairy'!L3 -> 18254 First Avenue | AZ3: ='Anchor J Dairy'!L3 -> 24507 First Avenue | BA3: ='Oliveira Dairy'!L3 -> 3991 Lander Avenue | BB3: ='Souza Bros Dairy'!L3 -> 3887 McCullagh Road | BC3: ='Miguel Family Dairy'!L3 -> 20755 West River Road | BD3: ='Dias Family Dairy'!L3 -> 21330 West Second Avenue | BE3: ='Empty was A_D Dairy'!L3 -> 23489 West Second Avenue | BF3: ='Michael Brasil Dairy #2'!L3 -> 4971 Van Clief Road | BG3: ='F & A Lemos Dairy'!L3 -> 14371 East Avenue | BH3: ='Alves & Son Dairy #2'!L3 -> 13831 East Avenue | BI3: ='Golf Link RanchesLLC'!L3 -> 10220 Golf Link Road | BJ3: ='Triple M Jerseys'!L3 -> 1008 North Verduga Road | BK3: ='Jose & Teresa Soares Dairy'!L3 -> 11076 North Vincent Road | BL3: ='MachadoGabriel&SonsDairy'!L3 -> 12464 South Vincent Road | BM3: ='Hawkins Ranch'!L3 -> 5301 North De Angelis Road | BN3: ='Silva Dairy Farms #3B'!L3 -> 1904 Edminster Road | BO3: =AhlemFarmsPartnership!L3 -> 24093 West American Avenue | BP3: ='Vierra Dairy Farms #4'!L3 -> 25511 West American Avenue | BQ3: ='CaliforniaDairyFarms LLC'!L3 -> 18128 American Avenue | BR3: ='Larry Peterson Dairy'!L3 -> 21189 American Avenue | BS3: ='Joe Egli&Sons Dairy'!L3 -> 21810 West August Avenue | BT3: ='CMA Livestock #2'!L3 -> 23970 West August Avenue | BU3: ='Valentine Dairy'!L3 -> 20717 Bloss Avenue | BV3: ='CMC Jerseys LLC'!L3 -> 23204 Bloss Avenue | BW3: ='Fanelli_Fanelli Brothers'!L3 -> 23839 Bloss Avenue | BX3: ='Martins Bros Dairy'!L3 -> 6041 Central Avenue | BY3: ='Gomes Heifer Ranch'!L3 -> 737 South Blaker Road | BZ3: ='Ed Hirdes Dairy'!B3 -> 2131 South Blaker Road | CA3: ='Dematos Dairy'!L3 -> 931 South Blaker Road | CB3: ='Carlos Estacio&Sons Dairy'!L3 -> 8900 West Bradbury Road | CC3: ='Live Oak Dairy G'!L3 -> 730 Bystrum | CD3: ='Verissimo Facility'!L3 -> 6125 South Central Avenue | CE3: ='Double Cross Dairy'!L3 -> 7025 South Central Avenue | CF3: ='Double Cross #4'!L3 -> 6006 South Central Avenue | CG3: ='King Dairy'!L3 -> 5524 South Central Avenue | CH3: ='Vieira Livestock'!L3 -> 3800 South Central Avenue | CI3: ='AldenPeterson&SonsDairy Inc.'!L3 -> 1431 North Central Avenue | CJ3: ='John Nunes Dairy #3'!L3 -> 5324 Clayton Road | CK3: ='Roestar Dairy'!L3 -> 10407 West Bradbury Road | CL3: ='Luis M. Azevedo Dairy'!L3 -> 11412 West Main Street | CM3: ='Arlinda Holsteins'!L3 -> 6325 West Main Street | CN3: ='Robert Gioletti & Sons Dairy'!L3 -> 10213 West Main Street | CO3: ='Carl Vieira Dairy'!L3 -> 1000 North Mitchell Road | CP3: ='John Brasil & Sons Dairy'!L3 -> 2613 South Mitchell Road | CQ3: ='John Brasil Dairy #3'!L3 -> 1707 South Mitchell Road | CR3: ='KMA Dairy'!L3 -> 539 South Morgan Road | CS3: ='Sallaberry Ranch'!L3 -> 5608 South Morgan Road | CT3: ='Alfred C Nunes Dairy'!L3 -> 5119 South Morgan Road | CU3: ='Jim Vieira & Son Dairy'!L3 -> 2401 Newman Road | CV3: ='Ehrlich Dairy'!L3 -> 5725 Ehrlich Road | CW3: ='D&A Brasil Facility'!B3 -> 4218 South Prairie Flower Road | CX3: ='Silva''s Holsteins'!B3 -> 6706 Elaine Road | CY3: ='G J Silva #3'!B3 -> #N/A | CZ3: ='Jim Vieira and Son Dairy #2'!L3 -> 3100 South Prairie Flower Road | DA3: ='Johal Dairy'!L3 -> 315 North Prairie Flower Road | DB3: ='A & G Azevedo Dairy'!L3 -> 536 North Prairie Flower Road | DC3: ='Gentle Breezes Dairy'!L3 -> 4419 South Faith Home Road | DD3: ='Joe Sousa Jr Dairy'!L3 -> 1519 North Prairie Flower Road | DE3: ='John Brasil Heifers'!L3 -> 6730 West Harding | DF3: ='MHF Dairy'!L3 -> 501 South Story Road | DG3: ='Brindiero&DanbomDairyFarms'!L3 -> 5831 South Tegner Road | DH3: ='A&C Machado Dairy #2'!L3 -> 619 South Vincent Road | DI3: ='J & J Toste DairyInc.'!L3 -> 2207 South Walnut Road | DJ3: ='Bar Vee DairyInc.'!L3 -> 3031 North Washington Road | DK3: ='Railside Jersey FarmsLLC'!L3 -> 6816 North Washington Road | DL3: ='Manuel Azevedo Dairy'!L3 -> 2800 White Road | DM3: ='Sousa Family Dairy'!L3 -> 12801 West Bradbury Road | DN3: ='UC Davis Animal Science Dairy'!L3 -> 201 Dairy Road | DO3: ='Garcia''s Registered Jerseys'!L3 -> 1018 Hickman Road | DP3: ='Lucio Corral Cattle'!L3 -> 207 Holland Drive | DQ3: ='Wickstrom Dairy Inc'!B3 -> 5612 Hultberg Road | DR3: ='Sam Kooistra Dairy'!L3 -> 5837 Hultberg Road | DS3: ='Vitorino & Sons Dairy'!L3 -> 3918 South Kilroy Road | DT3: ='Valley Cross Dairy'!L3 -> 9500 West Linwood Avenue | DU3: ='John Brasil & Sons Dairy #2'!L3 -> 9018 West Linwood Avenue | DV3: ='Pepper Dairy'!L3 -> 13942 North Pepper Street | DW3: ='Clauss Dairy Farms'!L3 -> 21670 Bloss Avenue | DX3: ='Dairy Central Heifers'!L3 -> 10119 West August Road | DY3: ='Yosemite Jersey Dairy'!L3 -> 21522 Geer Avenue | DZ3: ='Sunwest Jersey Dairy'!L3 -> 22270 Bloss Avenue | EA3: ='N & C Silveira Dairy'!L3 -> 6025 Hultberg Road | EB3: ='Nyman Brothers Dairy'!L3 -> 20445 August Avenue | EC3: ='Broder Farms'!L3 -> 22245 August Avenue | ED3: ='Borba Dairy Farms'!L3 -> 5297 Kelley Road | EE3: ='Charles Ahlem Ranch'!L3 -> 23546 West American Avenue | EF3: ='James Ahlem Dairy'!L3 -> 9483 Columbus Avenue | EG3: ='Nylund Dairy Farms'!L3 -> 20723 Geer Avenue | EH3: ='Vierra Ranch Dairy'!L3 -> 23160 Williams Avenue | EI3: ='Joe O Rocha Dairy Inc.'!L3 -> 18451 East Bradbury Road | EJ3: ='Alves & Son Dairy'!L3 -> 13745 Newport Road | EK3: ='3A Teixeira Dairy'!L3 -> 12926 North Vincent Road | EL3: ='Denizma_Bud Postma Dairy'!L3 -> 6249 Parker Road | EM3: ='Couco Creek Dairy'!L3 -> 3303 South Washington Road | EN3: ='Clausen Dairy'!L3 -> 18851 East Clausen Road
A4: PLACE CITY | B4: ='A & M De Souza Dairy'!B4 -> Turlock | C4: ='Silva Dairy Farms #3A'!B4 -> Stevinson | D4: ='Joe Borba Dairy Inc.'!B4 -> Turlock | E4: ='Ken Van Foeken Dairy #2'!B4 -> Hilmar | F4: ='Da Rosa Dairy'!B4 -> Turlock | G4: ='J_D Brasil Dairy'!#REF! -> #REF! | H4: ='River Rock Ranch LLC'!L4 -> Stevinson | I4: ='Double Cross #3'!L4 -> Turlock | J4: ='Edward Nunes Dairy'!L4 -> Escalon | K4: ='Gomes Dairy'!#REF! -> #REF! | L4: ='Roest Family Dairy'!L4 -> Modesto | M4: ='Gil Tex Dairy'!L4 -> Turlock | N4: ='GJ Silva'!L4 -> Turlock | O4: ='Hilmar Holsteins Inc.'!L4 -> Hilmar | P4: ='Jordao Dairy'!L4 -> Turlock | Q4: ='Cross Creek Dairy'!L4 -> Hilmar | R4: ='Double Cross #2'!L4 -> Turlock | S4: ='LarryPetersonDairyFarms#2'!L4 -> Hilmar | T4: ='Fire_Lake Jerseys #2'!L4 -> Turlock | U4: ='Lumar Dairy Farms'!L4 -> Turlock | V4: ='CMA Livestock'!L4 -> Hilmar | W4: ='Fire Lakes Jerseys'!L4 -> Turlock | X4: ='Rick Jones Farms'!L4 -> Stevinson | Y4: ='Silveira Holsteins'!L4 -> Hilmar | Z4: ='Diamond B Dairy'!L4 -> Ceres | AA4: ='Azevedo Dairy'!L4 -> Hilmar | AB4: ='Valsigna Dairy'!L4 -> Hilmar | AC4: =WickstromJerseyFarmsInc.!L4 -> Hilmar | AD4: ='Diniz Dairy'!L4 -> Hilmar | AE4: ='Crane Dairy Inc.'!L4 -> Hilmar | AF4: ='GM Silva Dairies #2'!L4 -> Hilmar | AG4: ='Joe Oliveira Dairy'!#REF! -> #REF! | AH4: ='Vierra Dairy Farms #3'!L4 -> Hilmar | AI4: ='Nelson Dairy'!L4 -> Hilmar | AJ4: ='Mario&ChristinaNunesDairy'!L4 -> Hilmar | AK4: ='B & D Dairy'!L4 -> Hilmar | AL4: ='Silveira Dairy Inc.'!L4 -> Hilmar | AM4: ='Jade Jersey Dairy'!L4 -> Hilmar | AN4: ='Live Oak Dairy A'!L4 -> Hilmar | AO4: ='T & M Borba Dairy'!L4 -> Hilmar | AP4: ='Oslo Dairy'!L4 -> Hilmar | AQ4: ='Kronberg Facility'!L4 -> Hilmar | AR4: ='Ken Van Foeken Dairy'!L4 -> Hilmar | AS4: ='Amaral Dairy Farms'!L4 -> Hilmar | AT4: ='B_6 Dairy'!L4 -> Hilmar | AU4: ='6D Dores Dairy'!L4 -> Hilmar | AV4: ='Fanelli Dairy'!L4 -> Hilmar | AW4: ='Joao Sousa Dairy'!L4 -> Hilmar | AX4: ='Vierra Dairy Farms #2'!L4 -> Hilmar | AY4: ='Michael Brasil Dairy'!L4 -> Stevinson | AZ4: ='Anchor J Dairy'!L4 -> Stevinson | BA4: ='Oliveira Dairy'!L4 -> Stevinson | BB4: ='Souza Bros Dairy'!L4 -> Stevinson | BC4: ='Miguel Family Dairy'!L4 -> Stevinson | BD4: ='Dias Family Dairy'!L4 -> Stevinson | BE4: ='Empty was A_D Dairy'!L4 -> Stevinson | BF4: ='Michael Brasil Dairy #2'!L4 -> Stevinson | BG4: ='F & A Lemos Dairy'!L4 -> Turlock | BH4: ='Alves & Son Dairy #2'!L4 -> Turlock | BI4: ='Golf Link RanchesLLC'!L4 -> Turlock | BJ4: ='Triple M Jerseys'!L4 -> Turlock | BK4: ='Jose & Teresa Soares Dairy'!L4 -> Turlock | BL4: ='MachadoGabriel&SonsDairy'!L4 -> Turlock | BM4: ='Hawkins Ranch'!L4 -> Stevinson | BN4: ='Silva Dairy Farms #3B'!L4 -> Stevinson | BO4: =AhlemFarmsPartnership!L4 -> Hilmar | BP4: ='Vierra Dairy Farms #4'!L4 -> Hilmar | BQ4: ='CaliforniaDairyFarms LLC'!L4 -> Hilmar | BR4: ='Larry Peterson Dairy'!L4 -> Hilmar | BS4: ='Joe Egli&Sons Dairy'!L4 -> Hilmar | BT4: ='CMA Livestock #2'!L4 -> Hilmar | BU4: ='Valentine Dairy'!L4 -> Hilmar | BV4: ='CMC Jerseys LLC'!L4 -> Hilmar | BW4: ='Fanelli_Fanelli Brothers'!L4 -> Hilmar | BX4: ='Martins Bros Dairy'!L4 -> Hilmar | BY4: ='Gomes Heifer Ranch'!L4 -> Turlock | BZ4: ='Ed Hirdes Dairy'!B4 -> Turlock | CA4: ='Dematos Dairy'!L4 -> Turlock | CB4: ='Carlos Estacio&Sons Dairy'!L4 -> Turlock | CC4: ='Live Oak Dairy G'!L4 -> Turlock | CD4: ='Verissimo Facility'!L4 -> Turlock | CE4: ='Double Cross Dairy'!L4 -> Turlock | CF4: ='Double Cross #4'!L4 -> Turlock | CG4: ='King Dairy'!L4 -> Turlock | CH4: ='Vieira Livestock'!L4 -> Turlock | CI4: ='AldenPeterson&SonsDairy Inc.'!L4 -> Turlock | CJ4: ='John Nunes Dairy #3'!L4 -> Turlock | CK4: ='Roestar Dairy'!L4 -> Turlock | CL4: ='Luis M. Azevedo Dairy'!L4 -> Turlock | CM4: ='Arlinda Holsteins'!L4 -> Turlock | CN4: ='Robert Gioletti & Sons Dairy'!L4 -> Turlock | CO4: ='Carl Vieira Dairy'!L4 -> Turlock | CP4: ='John Brasil & Sons Dairy'!L4 -> Turlock | CQ4: ='John Brasil Dairy #3'!L4 -> Turlock | CR4: ='KMA Dairy'!L4 -> Turlock | CS4: ='Sallaberry Ranch'!L4 -> Turlock | CT4: ='Alfred C Nunes Dairy'!L4 -> Turlock | CU4: ='Jim Vieira & Son Dairy'!L4 -> Turlock | CV4: ='Ehrlich Dairy'!L4 -> Turlock | CW4: ='D&A Brasil Facility'!B4 -> Turlock | CX4: ='Silva''s Holsteins'!B4 -> Turlock | CY4: ='G J Silva #3'!B4 -> #N/A | CZ4: ='Jim Vieira and Son Dairy #2'!L4 -> Turlock | DA4: ='Johal Dairy'!L4 -> Turlock | DB4: ='A & G Azevedo Dairy'!L4 -> Turlock | DC4: ='Gentle Breezes Dairy'!L4 -> Turlock | DD4: ='Joe Sousa Jr Dairy'!L4 -> Turlock | DE4: ='John Brasil Heifers'!L4 -> Turlock | DF4: ='MHF Dairy'!L4 -> Turlock | DG4: ='Brindiero&DanbomDairyFarms'!L4 -> Turlock | DH4: ='A&C Machado Dairy #2'!L4 -> Turlock | DI4: ='J & J Toste DairyInc.'!L4 -> Turlock | DJ4: ='Bar Vee DairyInc.'!L4 -> Turlock | DK4: ='Railside Jersey FarmsLLC'!L4 -> Turlock | DL4: ='Manuel Azevedo Dairy'!L4 -> Turlock | DM4: ='Sousa Family Dairy'!L4 -> Turlock | DN4: ='UC Davis Animal Science Dairy'!L4 -> Davis | DO4: ='Garcia''s Registered Jerseys'!L4 -> Turlock | DP4: ='Lucio Corral Cattle'!L4 -> Turlock | DQ4: ='Wickstrom Dairy Inc'!B4 -> Turlock | DR4: ='Sam Kooistra Dairy'!L4 -> Turlock | DS4: ='Vitorino & Sons Dairy'!L4 -> Turlock | DT4: ='Valley Cross Dairy'!L4 -> Turlock | DU4: ='John Brasil & Sons Dairy #2'!L4 -> Turlock | DV4: ='Pepper Dairy'!L4 -> Turlock | DW4: ='Clauss Dairy Farms'!L4 -> Hilmar | DX4: ='Dairy Central Heifers'!L4 -> Turlock | DY4: ='Yosemite Jersey Dairy'!L4 -> Hilmar | DZ4: ='Sunwest Jersey Dairy'!L4 -> Hilmar | EA4: ='N & C Silveira Dairy'!L4 -> Turlock | EB4: ='Nyman Brothers Dairy'!L4 -> Hilmar | EC4: ='Broder Farms'!L4 -> Hilmar | ED4: ='Borba Dairy Farms'!L4 -> Hilmar | EE4: ='Charles Ahlem Ranch'!L4 -> Hilmar | EF4: ='James Ahlem Dairy'!L4 -> Hilmar | EG4: ='Nylund Dairy Farms'!L4 -> Hilmar | EH4: ='Vierra Ranch Dairy'!L4 -> Hilmar | EI4: ='Joe O Rocha Dairy Inc.'!L4 -> Turlock | EJ4: ='Alves & Son Dairy'!L4 -> Turlock | EK4: ='3A Teixeira Dairy'!L4 -> Turlock | EL4: ='Denizma_Bud Postma Dairy'!L4 -> Modesto | EM4: ='Couco Creek Dairy'!L4 -> Turlock | EN4: ='Clausen Dairy'!L4 -> Turlock
A5: PLACCE ZIP | B5: ='A & M De Souza Dairy'!B5 -> 95380 | C5: ='Silva Dairy Farms #3A'!B5 -> 95374 | D5: ='Joe Borba Dairy Inc.'!B5 -> 95380 | E5: ='Ken Van Foeken Dairy #2'!B5 -> 95324 | F5: ='Da Rosa Dairy'!B5 -> 95380 | G5: ='J_D Brasil Dairy'!#REF! -> #REF! | H5: ='River Rock Ranch LLC'!L5 -> 95374 | I5: ='Double Cross #3'!L5 -> 95380 | J5: ='Edward Nunes Dairy'!L5 -> 95320 | K5: ='Gomes Dairy'!#REF! -> #REF! | L5: ='Roest Family Dairy'!L5 -> 95358 | M5: ='Gil Tex Dairy'!L5 -> 95382 | N5: ='GJ Silva'!L5 -> 95380 | O5: ='Hilmar Holsteins Inc.'!L5 -> 95324 | P5: ='Jordao Dairy'!L5 -> 95380 | Q5: ='Cross Creek Dairy'!L5 -> 95324 | R5: ='Double Cross #2'!L5 -> 95380 | S5: ='LarryPetersonDairyFarms#2'!L5 -> 95324 | T5: ='Fire_Lake Jerseys #2'!L5 -> 95380 | U5: ='Lumar Dairy Farms'!L5 -> 95380 | V5: ='CMA Livestock'!L5 -> 95324 | W5: ='Fire Lakes Jerseys'!L5 -> 95380 | X5: ='Rick Jones Farms'!L5 -> 95374 | Y5: ='Silveira Holsteins'!L5 -> 95324 | Z5: ='Diamond B Dairy'!L5 -> 95307 | AA5: ='Azevedo Dairy'!L5 -> 95324 | AB5: ='Valsigna Dairy'!L5 -> 95324 | AC5: =WickstromJerseyFarmsInc.!L5 -> 95324 | AD5: ='Diniz Dairy'!L5 -> 95324 | AE5: ='Crane Dairy Inc.'!L5 -> 95324 | AF5: ='GM Silva Dairies #2'!L5 -> 95324 | AG5: ='Joe Oliveira Dairy'!#REF! -> #REF! | AH5: ='Vierra Dairy Farms #3'!L5 -> 95324 | AI5: ='Nelson Dairy'!L5 -> 95324 | AJ5: ='Mario&ChristinaNunesDairy'!L5 -> 95324 | AK5: ='B & D Dairy'!L5 -> 95324 | AL5: ='Silveira Dairy Inc.'!L5 -> 95324 | AM5: ='Jade Jersey Dairy'!L5 -> 95324 | AN5: ='Live Oak Dairy A'!L5 -> 95324 | AO5: ='T & M Borba Dairy'!L5 -> 95324 | AP5: ='Oslo Dairy'!L5 -> 95324 | AQ5: ='Kronberg Facility'!L5 -> 95324 | AR5: ='Ken Van Foeken Dairy'!L5 -> 95324 | AS5: ='Amaral Dairy Farms'!L5 -> 95324 | AT5: ='B_6 Dairy'!L5 -> 95324 | AU5: ='6D Dores Dairy'!L5 -> 95324 | AV5: ='Fanelli Dairy'!L5 -> 95324 | AW5: ='Joao Sousa Dairy'!L5 -> 95324 | AX5: ='Vierra Dairy Farms #2'!L5 -> 95324 | AY5: ='Michael Brasil Dairy'!L5 -> 95374 | AZ5: ='Anchor J Dairy'!L5 -> 95374 | BA5: ='Oliveira Dairy'!L5 -> 95374 | BB5: ='Souza Bros Dairy'!L5 -> 95374 | BC5: ='Miguel Family Dairy'!L5 -> 95374 | BD5: ='Dias Family Dairy'!L5 -> 95374 | BE5: ='Empty was A_D Dairy'!L5 -> 95324 | BF5: ='Michael Brasil Dairy #2'!L5 -> 95374 | BG5: ='F & A Lemos Dairy'!L5 -> 95380 | BH5: ='Alves & Son Dairy #2'!L5 -> 95380 | BI5: ='Golf Link RanchesLLC'!L5 -> 95380 | BJ5: ='Triple M Jerseys'!L5 -> 95380 | BK5: ='Jose & Teresa Soares Dairy'!L5 -> 95380 | BL5: ='MachadoGabriel&SonsDairy'!L5 -> 95380 | BM5: ='Hawkins Ranch'!L5 -> 95374 | BN5: ='Silva Dairy Farms #3B'!L5 -> 95374 | BO5: =AhlemFarmsPartnership!L5 -> 95324 | BP5: ='Vierra Dairy Farms #4'!L5 -> 95322 | BQ5: ='CaliforniaDairyFarms LLC'!L5 -> 95324 | BR5: ='Larry Peterson Dairy'!L5 -> 95324 | BS5: ='Joe Egli&Sons Dairy'!L5 -> 95324 | BT5: ='CMA Livestock #2'!L5 -> 95324 | BU5: ='Valentine Dairy'!L5 -> 95324 | BV5: ='CMC Jerseys LLC'!L5 -> 95324 | BW5: ='Fanelli_Fanelli Brothers'!L5 -> 95324 | BX5: ='Martins Bros Dairy'!L5 -> 95324 | BY5: ='Gomes Heifer Ranch'!L5 -> 95380 | BZ5: ='Ed Hirdes Dairy'!B5 -> 95380 | CA5: ='Dematos Dairy'!L5 -> 95380 | CB5: ='Carlos Estacio&Sons Dairy'!L5 -> 95380 | CC5: ='Live Oak Dairy G'!L5 -> 95380 | CD5: ='Verissimo Facility'!L5 -> 95380 | CE5: ='Double Cross Dairy'!L5 -> 95380 | CF5: ='Double Cross #4'!L5 -> 95380 | CG5: ='King Dairy'!L5 -> 95380 | CH5: ='Vieira Livestock'!L5 -> 95380 | CI5: ='AldenPeterson&SonsDairy Inc.'!L5 -> 95380 | CJ5: ='John Nunes Dairy #3'!L5 -> 95380 | CK5: ='Roestar Dairy'!L5 -> 95380 | CL5: ='Luis M. Azevedo Dairy'!L5 -> 95380 | CM5: ='Arlinda Holsteins'!L5 -> 95380 | CN5: ='Robert Gioletti & Sons Dairy'!L5 -> 95380 | CO5: ='Carl Vieira Dairy'!L5 -> 95380 | CP5: ='John Brasil & Sons Dairy'!L5 -> 95380 | CQ5: ='John Brasil Dairy #3'!L5 -> 95380 | CR5: ='KMA Dairy'!L5 -> 95380 | CS5: ='Sallaberry Ranch'!L5 -> 95380 | CT5: ='Alfred C Nunes Dairy'!L5 -> 95380 | CU5: ='Jim Vieira & Son Dairy'!L5 -> 95380 | CV5: ='Ehrlich Dairy'!L5 -> 95380 | CW5: ='D&A Brasil Facility'!B5 -> 95380 | CX5: ='Silva''s Holsteins'!B5 -> 95380 | CY5: ='G J Silva #3'!B5 -> #N/A | CZ5: ='Jim Vieira and Son Dairy #2'!L5 -> 95380 | DA5: ='Johal Dairy'!L5 -> 95380 | DB5: ='A & G Azevedo Dairy'!L5 -> 95380 | DC5: ='Gentle Breezes Dairy'!L5 -> 95380 | DD5: ='Joe Sousa Jr Dairy'!L5 -> 95380 | DE5: ='John Brasil Heifers'!L5 -> 95380 | DF5: ='MHF Dairy'!L5 -> 95380 | DG5: ='Brindiero&DanbomDairyFarms'!L5 -> 95380 | DH5: ='A&C Machado Dairy #2'!L5 -> 95380 | DI5: ='J & J Toste DairyInc.'!L5 -> 95380 | DJ5: ='Bar Vee DairyInc.'!L5 -> 95380 | DK5: ='Railside Jersey FarmsLLC'!L5 -> 95380 | DL5: ='Manuel Azevedo Dairy'!L5 -> 95380 | DM5: ='Sousa Family Dairy'!L5 -> 95380 | DN5: ='UC Davis Animal Science Dairy'!L5 -> 95616 | DO5: ='Garcia''s Registered Jerseys'!L5 -> 95380 | DP5: ='Lucio Corral Cattle'!L5 -> 95380 | DQ5: ='Wickstrom Dairy Inc'!B5 -> 95380 | DR5: ='Sam Kooistra Dairy'!L5 -> 95380 | DS5: ='Vitorino & Sons Dairy'!L5 -> 95380 | DT5: ='Valley Cross Dairy'!L5 -> 95380 | DU5: ='John Brasil & Sons Dairy #2'!L5 -> 95380 | DV5: ='Pepper Dairy'!L5 -> 95380 | DW5: ='Clauss Dairy Farms'!L5 -> 95324 | DX5: ='Dairy Central Heifers'!L5 -> 95380 | DY5: ='Yosemite Jersey Dairy'!L5 -> 95324 | DZ5: ='Sunwest Jersey Dairy'!L5 -> 95324 | EA5: ='N & C Silveira Dairy'!L5 -> 95380 | EB5: ='Nyman Brothers Dairy'!L5 -> 95324 | EC5: ='Broder Farms'!L5 -> 95324 | ED5: ='Borba Dairy Farms'!L5 -> 95324 | EE5: ='Charles Ahlem Ranch'!L5 -> 95324 | EF5: ='James Ahlem Dairy'!L5 -> 95324 | EG5: ='Nylund Dairy Farms'!L5 -> 95324 | EH5: ='Vierra Ranch Dairy'!L5 -> 95324 | EI5: ='Joe O Rocha Dairy Inc.'!L5 -> 95380 | EJ5: ='Alves & Son Dairy'!L5 -> 95380 | EK5: ='3A Teixeira Dairy'!L5 -> 95380 | EL5: ='Denizma_Bud Postma Dairy'!L5 -> 95355 | EM5: ='Couco Creek Dairy'!L5 -> 95381 | EN5: ='Clausen Dairy'!L5 -> 95315
A6: PLACE COUNTY | B6: ='A & M De Souza Dairy'!B6 -> Stanislaus | C6: ='Silva Dairy Farms #3A'!B6 -> Merced | D6: ='Joe Borba Dairy Inc.'!B6 -> Stanislaus | E6: ='Ken Van Foeken Dairy #2'!B6 -> Merced | F6: ='Da Rosa Dairy'!B6 -> Stanislaus | G6: ='J_D Brasil Dairy'!#REF! -> #REF! | H6: ='River Rock Ranch LLC'!L6 -> Merced | I6: ='Double Cross #3'!L6 -> Merced | J6: ='Edward Nunes Dairy'!L6 -> San Joaquin | K6: ='Gomes Dairy'!#REF! -> #REF! | L6: ='Roest Family Dairy'!L6 -> Stanislaus | M6: ='Gil Tex Dairy'!L6 -> Stanislaus | N6: ='GJ Silva'!L6 -> Stanislaus | O6: ='Hilmar Holsteins Inc.'!L6 -> Merced | P6: ='Jordao Dairy'!L6 -> Stanislaus | Q6: ='Cross Creek Dairy'!L6 -> Merced | R6: ='Double Cross #2'!L6 -> Merced | S6: ='LarryPetersonDairyFarms#2'!L6 -> Merced | T6: ='Fire_Lake Jerseys #2'!L6 -> Stanislaus | U6: ='Lumar Dairy Farms'!L6 -> Stanislaus | V6: ='CMA Livestock'!L6 -> Merced | W6: ='Fire Lakes Jerseys'!L6 -> Stanislaus | X6: ='Rick Jones Farms'!L6 -> Merced | Y6: ='Silveira Holsteins'!L6 -> Merced | Z6: ='Diamond B Dairy'!L6 -> Stanislaus | AA6: ='Azevedo Dairy'!L6 -> Merced | AB6: ='Valsigna Dairy'!L6 -> Merced | AC6: =WickstromJerseyFarmsInc.!L6 -> Merced | AD6: ='Diniz Dairy'!L6 -> Merced | AE6: ='Crane Dairy Inc.'!L6 -> Merced | AF6: ='GM Silva Dairies #2'!L6 -> Merced | AG6: ='Joe Oliveira Dairy'!#REF! -> #REF! | AH6: ='Vierra Dairy Farms #3'!L6 -> Merced | AI6: ='Nelson Dairy'!L6 -> Merced | AJ6: ='Mario&ChristinaNunesDairy'!L6 -> Merced | AK6: ='B & D Dairy'!L6 -> Merced | AL6: ='Silveira Dairy Inc.'!L6 -> Merced | AM6: ='Jade Jersey Dairy'!L6 -> Merced | AN6: ='Live Oak Dairy A'!L6 -> Merced | AO6: ='T & M Borba Dairy'!L6 -> Merced | AP6: ='Oslo Dairy'!L6 -> Merced | AQ6: ='Kronberg Facility'!L6 -> Merced | AR6: ='Ken Van Foeken Dairy'!L6 -> Merced | AS6: ='Amaral Dairy Farms'!L6 -> Merced | AT6: ='B_6 Dairy'!L6 -> Merced | AU6: ='6D Dores Dairy'!L6 -> Merced | AV6: ='Fanelli Dairy'!L6 -> Merced | AW6: ='Joao Sousa Dairy'!L6 -> Merced | AX6: ='Vierra Dairy Farms #2'!L6 -> Merced | AY6: ='Michael Brasil Dairy'!L6 -> Merced | AZ6: ='Anchor J Dairy'!L6 -> Merced | BA6: ='Oliveira Dairy'!L6 -> Merced | BB6: ='Souza Bros Dairy'!L6 -> Merced | BC6: ='Miguel Family Dairy'!L6 -> Merced | BD6: ='Dias Family Dairy'!L6 -> Merced | BE6: ='Empty was A_D Dairy'!L6 -> Merced | BF6: ='Michael Brasil Dairy #2'!L6 -> Merced | BG6: ='F & A Lemos Dairy'!L6 -> Merced | BH6: ='Alves & Son Dairy #2'!L6 -> Merced | BI6: ='Golf Link RanchesLLC'!L6 -> Merced | BJ6: ='Triple M Jerseys'!L6 -> Stanislaus | BK6: ='Jose & Teresa Soares Dairy'!L6 -> Merced | BL6: ='MachadoGabriel&SonsDairy'!L6 -> Merced | BM6: ='Hawkins Ranch'!L6 -> Merced | BN6: ='Silva Dairy Farms #3B'!L6 -> Merced | BO6: =AhlemFarmsPartnership!L6 -> Merced | BP6: ='Vierra Dairy Farms #4'!L6 -> Merced | BQ6: ='CaliforniaDairyFarms LLC'!L6 -> Merced | BR6: ='Larry Peterson Dairy'!L6 -> Merced | BS6: ='Joe Egli&Sons Dairy'!L6 -> Merced | BT6: ='CMA Livestock #2'!L6 -> Merced | BU6: ='Valentine Dairy'!L6 -> Merced | BV6: ='CMC Jerseys LLC'!L6 -> Merced | BW6: ='Fanelli_Fanelli Brothers'!L6 -> Merced | BX6: ='Martins Bros Dairy'!L6 -> Merced | BY6: ='Gomes Heifer Ranch'!L6 -> Stanislaus | BZ6: ='Ed Hirdes Dairy'!B6 -> Stanislaus | CA6: ='Dematos Dairy'!L6 -> Stanislaus | CB6: ='Carlos Estacio&Sons Dairy'!L6 -> Stanislaus | CC6: ='Live Oak Dairy G'!L6 -> Stanislaus | CD6: ='Verissimo Facility'!L6 -> Stanislaus | CE6: ='Double Cross Dairy'!L6 -> Stanislaus | CF6: ='Double Cross #4'!L6 -> Stanislaus | CG6: ='King Dairy'!L6 -> Stanislaus | CH6: ='Vieira Livestock'!L6 -> Stanislaus | CI6: ='AldenPeterson&SonsDairy Inc.'!L6 -> Stanislaus | CJ6: ='John Nunes Dairy #3'!L6 -> Stanislaus | CK6: ='Roestar Dairy'!L6 -> Stanislaus | CL6: ='Luis M. Azevedo Dairy'!L6 -> Stanislaus | CM6: ='Arlinda Holsteins'!L6 -> Stanislaus | CN6: ='Robert Gioletti & Sons Dairy'!L6 -> Stanislaus | CO6: ='Carl Vieira Dairy'!L6 -> Stanislaus | CP6: ='John Brasil & Sons Dairy'!L6 -> Stanislaus | CQ6: ='John Brasil Dairy #3'!L6 -> Stanislaus | CR6: ='KMA Dairy'!L6 -> Stanislaus | CS6: ='Sallaberry Ranch'!L6 -> Stanislaus | CT6: ='Alfred C Nunes Dairy'!L6 -> Stanislaus | CU6: ='Jim Vieira & Son Dairy'!L6 -> Stanislaus | CV6: ='Ehrlich Dairy'!L6 -> Stanislaus | CW6: ='D&A Brasil Facility'!B6 -> Stanislaus | CX6: ='Silva''s Holsteins'!B6 -> Stanislaus | CY6: ='G J Silva #3'!B6 -> #N/A | CZ6: ='Jim Vieira and Son Dairy #2'!L6 -> Stanislaus | DA6: ='Johal Dairy'!L6 -> Stanislaus | DB6: ='A & G Azevedo Dairy'!L6 -> Stanislaus | DC6: ='Gentle Breezes Dairy'!L6 -> Stanislaus | DD6: ='Joe Sousa Jr Dairy'!L6 -> Stanislaus | DE6: ='John Brasil Heifers'!L6 -> Stanislaus | DF6: ='MHF Dairy'!L6 -> Stanislaus | DG6: ='Brindiero&DanbomDairyFarms'!L6 -> Stanislaus | DH6: ='A&C Machado Dairy #2'!L6 -> Stanislaus | DI6: ='J & J Toste DairyInc.'!L6 -> Stanislaus | DJ6: ='Bar Vee DairyInc.'!L6 -> Stanislaus | DK6: ='Railside Jersey FarmsLLC'!L6 -> Stanislaus | DL6: ='Manuel Azevedo Dairy'!L6 -> Stanislaus | DM6: ='Sousa Family Dairy'!L6 -> Stanislaus | DN6: ='UC Davis Animal Science Dairy'!L6 -> Yolo | DO6: ='Garcia''s Registered Jerseys'!L6 -> Stanislaus | DP6: ='Lucio Corral Cattle'!L6 -> Stanislaus | DQ6: ='Wickstrom Dairy Inc'!B6 -> Stanislaus | DR6: ='Sam Kooistra Dairy'!L6 -> Stanislaus | DS6: ='Vitorino & Sons Dairy'!L6 -> Stanislaus | DT6: ='Valley Cross Dairy'!L6 -> Stanislaus | DU6: ='John Brasil & Sons Dairy #2'!L6 -> Stanislaus | DV6: ='Pepper Dairy'!L6 -> Merced | DW6: ='Clauss Dairy Farms'!L6 -> Merced | DX6: ='Dairy Central Heifers'!L6 -> Stanislaus | DY6: ='Yosemite Jersey Dairy'!L6 -> Merced | DZ6: ='Sunwest Jersey Dairy'!L6 -> Merced | EA6: ='N & C Silveira Dairy'!L6 -> Stanislaus | EB6: ='Nyman Brothers Dairy'!L6 -> Merced | EC6: ='Broder Farms'!L6 -> Merced | ED6: ='Borba Dairy Farms'!L6 -> Merced | EE6: ='Charles Ahlem Ranch'!L6 -> Merced | EF6: ='James Ahlem Dairy'!L6 -> Merced | EG6: ='Nylund Dairy Farms'!L6 -> Merced | EH6: ='Vierra Ranch Dairy'!L6 -> Merced | EI6: ='Joe O Rocha Dairy Inc.'!L6 -> Merced | EJ6: ='Alves & Son Dairy'!L6 -> Merced | EK6: ='3A Teixeira Dairy'!L6 -> Merced | EL6: ='Denizma_Bud Postma Dairy'!L6 -> Stanislaus | EM6: ='Couco Creek Dairy'!L6 -> Stanislaus | EN6: ='Clausen Dairy'!L6 -> Merced
A7: OWNER | B7: ='A & M De Souza Dairy'!B7 -> De Sousa, Armelin & Maria | C7: ='Silva Dairy Farms #3A'!B7 -> Silva, Manuel | D7: ='Joe Borba Dairy Inc.'!B7 -> Joe Borba Dairy Inc | E7: ='Ken Van Foeken Dairy #2'!B7 -> Van Foeken, Kenneth L | F7: ='Da Rosa Dairy'!B7 -> Da Rosa, Luis & Olivia | G7: ='J_D Brasil Dairy'!#REF! -> #REF! | H7: ='River Rock Ranch LLC'!L7 -> River Rock Ranch, LLC | I7: ='Double Cross #3'!L7 -> Coelho, Joe & Louise | J7: ='Edward Nunes Dairy'!L7 -> Nunes, Edward | K7: ='Gomes Dairy'!#REF! -> #REF! | L7: ='Roest Family Dairy'!L7 -> Roest, Aire | M7: ='Gil Tex Dairy'!L7 -> Teixeira, Gilbert & Linda | N7: ='GJ Silva'!L7 -> Latters, Susan | O7: ='Hilmar Holsteins Inc.'!L7 -> Matheron, Aaron dba Hilmar Holsteins Inc | P7: ='Jordao Dairy'!L7 -> Jordao, Joe & Jose | Q7: ='Cross Creek Dairy'!L7 -> Branco, Joe & Cathy | R7: ='Double Cross #2'!L7 -> Joe Coelho Dairy | S7: ='LarryPetersonDairyFarms#2'!L7 -> Leonardo, John Dairy | T7: ='Fire_Lake Jerseys #2'!L7 -> Thomas, Rhonda | U7: ='Lumar Dairy Farms'!L7 -> Borba, Luis & Maria | V7: ='CMA Livestock'!L7 -> Luis, Manuel S. & Bernardet | W7: ='Fire Lakes Jerseys'!L7 -> Sanders, Scott | X7: ='Rick Jones Farms'!L7 -> Jones Farms | Y7: ='Silveira Holsteins'!L7 -> Silveira, Manuel | Z7: ='Diamond B Dairy'!L7 -> Brasil, John | AA7: ='Azevedo Dairy'!L7 -> Azevedo, Tiberio & Rosa | AB7: ='Valsigna Dairy'!L7 -> Wickstrom, Tim & Vern | AC7: =WickstromJerseyFarmsInc.!L7 -> Wickstrom, Mike | AD7: ='Diniz Dairy'!L7 -> Diniz, Antonio V & Maria | AE7: ='Crane Dairy Inc.'!L7 -> Crane Dairy, Inc | AF7: ='GM Silva Dairies #2'!L7 -> Silva, George & Margaret | AG7: ='Joe Oliveira Dairy'!#REF! -> #REF! | AH7: ='Vierra Dairy Farms #3'!L7 -> Ferreira, Eleanor | AI7: ='Nelson Dairy'!L7 -> Joyce W. Nelson and Trust | AJ7: ='Mario&ChristinaNunesDairy'!L7 -> Jorge, Luis & Maria | AK7: ='B & D Dairy'!L7 -> Huff, Eric | AL7: ='Silveira Dairy Inc.'!L7 -> Nyman, Brad | AM7: ='Jade Jersey Dairy'!L7 -> Ahlem, James & Carol | AN7: ='Live Oak Dairy A'!L7 -> Nyman, Brad | AO7: ='T & M Borba Dairy'!L7 -> DeBorba, Maria & Antonio | AP7: ='Oslo Dairy'!L7 -> Nyman, Brad | AQ7: ='Kronberg Facility'!L7 -> Kronberg, Virgil | AR7: ='Ken Van Foeken Dairy'!L7 -> Van Foeken, Kenneth L | AS7: ='Amaral Dairy Farms'!L7 -> Kindberg, Mike | AT7: ='B_6 Dairy'!L7 -> Borba, Mike | AU7: ='6D Dores Dairy'!L7 -> Dores, John | AV7: ='Fanelli Dairy'!L7 -> Fanelli, Philip | AW7: ='Joao Sousa Dairy'!L7 -> Sousa, Joao | AX7: ='Vierra Dairy Farms #2'!L7 -> R & R Ranches LLC | AY7: ='Michael Brasil Dairy'!L7 -> Brasil, Michael | AZ7: ='Anchor J Dairy'!L7 -> James J. Stevinson, A Corp. | BA7: ='Oliveira Dairy'!L7 -> Oliveira, Arthur & Antelma | BB7: ='Souza Bros Dairy'!L7 -> Souza Joe S & John S | BC7: ='Miguel Family Dairy'!L7 -> Dennis Miguel | BD7: ='Dias Family Dairy'!L7 -> Dias, Robert | BE7: ='Empty was A_D Dairy'!L7 -> Lewis, Joe Jr | BF7: ='Michael Brasil Dairy #2'!L7 -> Brasil, Michael | BG7: ='F & A Lemos Dairy'!L7 -> Lemos, Frank S & Annette | BH7: ='Alves & Son Dairy #2'!L7 -> Alves & Son Dairy #2 | BI7: ='Golf Link RanchesLLC'!L7 -> Ahlem, Mark | BJ7: ='Triple M Jerseys'!L7 -> Perry, John J. | BK7: ='Jose & Teresa Soares Dairy'!L7 -> Soares, Jose and Teresa | BL7: ='MachadoGabriel&SonsDairy'!L7 -> Machado, Mary | BM7: ='Hawkins Ranch'!L7 -> James J. Stevinson, A Corp. | BN7: ='Silva Dairy Farms #3B'!L7 -> Silva, Manuel | BO7: =AhlemFarmsPartnership!L7 -> Ahlem Farms Partnership | BP7: ='Vierra Dairy Farms #4'!L7 -> Swanson, Matt | BQ7: ='CaliforniaDairyFarms LLC'!L7 -> Forebay Farms, LLC | BR7: ='Larry Peterson Dairy'!L7 -> Ahlem, Mark | BS7: ='Joe Egli&Sons Dairy'!L7 -> Egli, Joseph | BT7: ='CMA Livestock #2'!L7 -> Ahlem, Mark | BU7: ='Valentine Dairy'!L7 -> Jorritsma, Kimberly Clauss | BV7: ='CMC Jerseys LLC'!L7 -> Ahlem, Mark | BW7: ='Fanelli_Fanelli Brothers'!L7 -> Gomes, Joe | BX7: ='Martins Bros Dairy'!L7 -> Martins, George | BY7: ='Gomes Heifer Ranch'!L7 -> Gioletti, Devin | BZ7: ='Ed Hirdes Dairy'!B7 -> Hirdes, Edward & Marilyn | CA7: ='Dematos Dairy'!L7 -> Dematos, Nuno & Marylou | CB7: ='Carlos Estacio&Sons Dairy'!L7 -> Estacio, Carlos F & Maria | CC7: ='Live Oak Dairy G'!L7 -> Nyman, Brad | CD7: ='Verissimo Facility'!L7 -> Machado, Adelina V. | CE7: ='Double Cross Dairy'!L7 -> Double Cross Dairy | CF7: ='Double Cross #4'!L7 -> Chaves, Callie | CG7: ='King Dairy'!L7 -> King, Elsie | CH7: ='Vieira Livestock'!L7 -> Joe and Christine Vieira | CI7: ='AldenPeterson&SonsDairy Inc.'!L7 -> Alden Peterson & Sons Dairy Inc | CJ7: ='John Nunes Dairy #3'!L7 -> Silva, Paulo | CK7: ='Roestar Dairy'!L7 -> Roest, Aire | CL7: ='Luis M. Azevedo Dairy'!L7 -> Souza, Ray | CM7: ='Arlinda Holsteins'!L7 -> Vieira, Carl & Laurie | CN7: ='Robert Gioletti & Sons Dairy'!L7 -> Gioletti & Sons Dairy | CO7: ='Carl Vieira Dairy'!L7 -> Vieira, Carl & Laurie | CP7: ='John Brasil & Sons Dairy'!L7 -> Brasil, John & Maria | CQ7: ='John Brasil Dairy #3'!L7 -> Brasil, John & Maria | CR7: ='KMA Dairy'!L7 -> Souza, Ray | CS7: ='Sallaberry Ranch'!L7 -> S & D Bylsma Dairy | CT7: ='Alfred C Nunes Dairy'!L7 -> Nunes, Alfred & Celia | CU7: ='Jim Vieira & Son Dairy'!L7 -> GJC Dairy, Inc | CV7: ='Ehrlich Dairy'!L7 -> Schortzmann, Brittney | CW7: ='D&A Brasil Facility'!B7 -> Brasil, Danny & Allison | CX7: ='Silva''s Holsteins'!B7 -> Silva, Manuel M & Filomena | CY7: ='G J Silva #3'!B7 -> #N/A | CZ7: ='Jim Vieira and Son Dairy #2'!L7 -> Machado, Lucio & Maria | DA7: ='Johal Dairy'!L7 -> Johal, Gurdial & Surinder | DB7: ='A & G Azevedo Dairy'!L7 -> Azevedo, Aldevino | DC7: ='Gentle Breezes Dairy'!L7 -> Smith, Eric A. | DD7: ='Joe Sousa Jr Dairy'!L7 -> Sousa, Joe | DE7: ='John Brasil Heifers'!L7 -> G. J. Silva Dairy | DF7: ='MHF Dairy'!L7 -> Machado, Isabel | DG7: ='Brindiero&DanbomDairyFarms'!L7 -> Brindiero, James & Danbom, Paul | DH7: ='A&C Machado Dairy #2'!L7 -> Lopes, Linda & Loren | DI7: ='J & J Toste DairyInc.'!L7 -> Toste, John | DJ7: ='Bar Vee DairyInc.'!L7 -> Crowell, Michael & Adam | DK7: ='Railside Jersey FarmsLLC'!L7 -> Singh, Sukhdev | DL7: ='Manuel Azevedo Dairy'!L7 -> Azevedo, Manuel & Maria | DM7: ='Sousa Family Dairy'!L7 -> De Sousa Armelin & Maria | DN7: ='UC Davis Animal Science Dairy'!L7 -> Regents of the University of California | DO7: ='Garcia''s Registered Jerseys'!L7 -> Garcia, Jose | DP7: ='Lucio Corral Cattle'!L7 -> Lucio Corral Rodriguez | DQ7: ='Wickstrom Dairy Inc'!B7 -> Brindeiro, Eleanor | DR7: ='Sam Kooistra Dairy'!L7 -> Kooistra, Sam | DS7: ='Vitorino & Sons Dairy'!L7 -> Vitorino & Sons Dairy | DT7: ='Valley Cross Dairy'!L7 -> Estate of Doug Bacon | DU7: ='John Brasil & Sons Dairy #2'!L7 -> Brasil, John & Maria | DV7: ='Pepper Dairy'!L7 -> Lemos, Frank S | DW7: ='Clauss Dairy Farms'!L7 -> Richard Clauss | DX7: ='Dairy Central Heifers'!L7 -> Borba, Bob | DY7: ='Yosemite Jersey Dairy'!L7 -> River Rock Ranch, LLC | DZ7: ='Sunwest Jersey Dairy'!L7 -> Richard Clauss | EA7: ='N & C Silveira Dairy'!L7 -> Silveira, Natalino | EB7: ='Nyman Brothers Dairy'!L7 -> Nyman, Delton | EC7: ='Broder Farms'!L7 -> Wickstrom, Aaron Broder Farms Dairy | ED7: ='Borba Dairy Farms'!L7 -> Borba Dairy Farms Family Trust | EE7: ='Charles Ahlem Ranch'!L7 -> Ahlem, Mark | EF7: ='James Ahlem Dairy'!L7 -> Ahlem, James & Carol | EG7: ='Nylund Dairy Farms'!L7 -> Nylund, Rodney V & Julie | EH7: ='Vierra Ranch Dairy'!L7 -> Swanson, Matt | EI7: ='Joe O Rocha Dairy Inc.'!L7 -> Joe O Rocha Dairy Inc | EJ7: ='Alves & Son Dairy'!L7 -> Alves, Joe | EK7: ='3A Teixeira Dairy'!L7 -> Fiorini, Victor | EL7: ='Denizma_Bud Postma Dairy'!L7 -> Monache Meadows AG | EM7: ='Couco Creek Dairy'!L7 -> Machado, Tony | EN7: ='Clausen Dairy'!L7 -> Schortzmann, Brittney
A8: OPERATOR | B8: ='A & M De Souza Dairy'!B8 -> 0 | C8: ='Silva Dairy Farms #3A'!B8 -> 0 | D8: ='Joe Borba Dairy Inc.'!B8 -> 0 | E8: ='Ken Van Foeken Dairy #2'!B8 -> 0 | F8: ='Da Rosa Dairy'!B8 -> 0 | G8: ='J_D Brasil Dairy'!#REF! -> #REF! | H8: ='River Rock Ranch LLC'!L8 -> 0 | I8: ='Double Cross #3'!L8 -> 0 | J8: ='Edward Nunes Dairy'!L8 -> 0 | K8: ='Gomes Dairy'!#REF! -> #REF! | L8: ='Roest Family Dairy'!L8 -> 0 | M8: ='Gil Tex Dairy'!L8 -> 0 | N8: ='GJ Silva'!L8 -> 0 | O8: ='Hilmar Holsteins Inc.'!L8 -> 0 | P8: ='Jordao Dairy'!L8 -> 0 | Q8: ='Cross Creek Dairy'!L8 -> 0 | R8: ='Double Cross #2'!L8 -> 0 | S8: ='LarryPetersonDairyFarms#2'!L8 -> 0 | T8: ='Fire_Lake Jerseys #2'!L8 -> 0 | U8: ='Lumar Dairy Farms'!L8 -> 0 | V8: ='CMA Livestock'!L8 -> 0 | W8: ='Fire Lakes Jerseys'!L8 -> 0 | X8: ='Rick Jones Farms'!L8 -> 0 | Y8: ='Silveira Holsteins'!L8 -> 0 | Z8: ='Diamond B Dairy'!L8 -> 0 | AA8: ='Azevedo Dairy'!L8 -> 0 | AB8: ='Valsigna Dairy'!L8 -> 0 | AC8: =WickstromJerseyFarmsInc.!L8 -> 0 | AD8: ='Diniz Dairy'!L8 -> 0 | AE8: ='Crane Dairy Inc.'!L8 -> 0 | AF8: ='GM Silva Dairies #2'!L8 -> 0 | AG8: ='Joe Oliveira Dairy'!#REF! -> #REF! | AH8: ='Vierra Dairy Farms #3'!L8 -> 0 | AI8: ='Nelson Dairy'!L8 -> 0 | AJ8: ='Mario&ChristinaNunesDairy'!L8 -> 0 | AK8: ='B & D Dairy'!L8 -> 0 | AL8: ='Silveira Dairy Inc.'!L8 -> 0 | AM8: ='Jade Jersey Dairy'!L8 -> 0 | AN8: ='Live Oak Dairy A'!L8 -> 0 | AO8: ='T & M Borba Dairy'!L8 -> 0 | AP8: ='Oslo Dairy'!L8 -> 0 | AQ8: ='Kronberg Facility'!L8 -> 0 | AR8: ='Ken Van Foeken Dairy'!L8 -> 0 | AS8: ='Amaral Dairy Farms'!L8 -> 0 | AT8: ='B_6 Dairy'!L8 -> 0 | AU8: ='6D Dores Dairy'!L8 -> 0 | AV8: ='Fanelli Dairy'!L8 -> 0 | AW8: ='Joao Sousa Dairy'!L8 -> 0 | AX8: ='Vierra Dairy Farms #2'!L8 -> 0 | AY8: ='Michael Brasil Dairy'!L8 -> 0 | AZ8: ='Anchor J Dairy'!L8 -> 0 | BA8: ='Oliveira Dairy'!L8 -> 0 | BB8: ='Souza Bros Dairy'!L8 -> 0 | BC8: ='Miguel Family Dairy'!L8 -> 0 | BD8: ='Dias Family Dairy'!L8 -> 0 | BE8: ='Empty was A_D Dairy'!L8 -> 0 | BF8: ='Michael Brasil Dairy #2'!L8 -> 0 | BG8: ='F & A Lemos Dairy'!L8 -> 0 | BH8: ='Alves & Son Dairy #2'!L8 -> 0 | BI8: ='Golf Link RanchesLLC'!L8 -> 0 | BJ8: ='Triple M Jerseys'!L8 -> 0 | BK8: ='Jose & Teresa Soares Dairy'!L8 -> 0 | BL8: ='MachadoGabriel&SonsDairy'!L8 -> 0 | BM8: ='Hawkins Ranch'!L8 -> 0 | BN8: ='Silva Dairy Farms #3B'!L8 -> 0 | BO8: =AhlemFarmsPartnership!L8 -> 0 | BP8: ='Vierra Dairy Farms #4'!L8 -> 0 | BQ8: ='CaliforniaDairyFarms LLC'!L8 -> 0 | BR8: ='Larry Peterson Dairy'!L8 -> 0 | BS8: ='Joe Egli&Sons Dairy'!L8 -> 0 | BT8: ='CMA Livestock #2'!L8 -> 0 | BU8: ='Valentine Dairy'!L8 -> 0 | BV8: ='CMC Jerseys LLC'!L8 -> 0 | BW8: ='Fanelli_Fanelli Brothers'!L8 -> 0 | BX8: ='Martins Bros Dairy'!L8 -> 0 | BY8: ='Gomes Heifer Ranch'!L8 -> 0 | BZ8: ='Ed Hirdes Dairy'!B8 -> 0 | CA8: ='Dematos Dairy'!L8 -> 0 | CB8: ='Carlos Estacio&Sons Dairy'!L8 -> 0 | CC8: ='Live Oak Dairy G'!L8 -> 0 | CD8: ='Verissimo Facility'!L8 -> 0 | CE8: ='Double Cross Dairy'!L8 -> 0 | CF8: ='Double Cross #4'!L8 -> 0 | CG8: ='King Dairy'!L8 -> 0 | CH8: ='Vieira Livestock'!L8 -> 0 | CI8: ='AldenPeterson&SonsDairy Inc.'!L8 -> 0 | CJ8: ='John Nunes Dairy #3'!L8 -> 0 | CK8: ='Roestar Dairy'!L8 -> 0 | CL8: ='Luis M. Azevedo Dairy'!L8 -> 0 | CM8: ='Arlinda Holsteins'!L8 -> 0 | CN8: ='Robert Gioletti & Sons Dairy'!L8 -> 0 | CO8: ='Carl Vieira Dairy'!L8 -> 0 | CP8: ='John Brasil & Sons Dairy'!L8 -> 0 | CQ8: ='John Brasil Dairy #3'!L8 -> 0 | CR8: ='KMA Dairy'!L8 -> 0 | CS8: ='Sallaberry Ranch'!L8 -> 0 | CT8: ='Alfred C Nunes Dairy'!L8 -> 0 | CU8: ='Jim Vieira & Son Dairy'!L8 -> 0 | CV8: ='Ehrlich Dairy'!L8 -> 0 | CW8: ='D&A Brasil Facility'!B8 -> 0 | CX8: ='Silva''s Holsteins'!B8 -> 0 | CY8: ='G J Silva #3'!B8 -> 0 | CZ8: ='Jim Vieira and Son Dairy #2'!L8 -> 0 | DA8: ='Johal Dairy'!L8 -> 0 | DB8: ='A & G Azevedo Dairy'!L8 -> 0 | DC8: ='Gentle Breezes Dairy'!L8 -> 0 | DD8: ='Joe Sousa Jr Dairy'!L8 -> 0 | DE8: ='John Brasil Heifers'!L8 -> 0 | DF8: ='MHF Dairy'!L8 -> 0 | DG8: ='Brindiero&DanbomDairyFarms'!L8 -> 0 | DH8: ='A&C Machado Dairy #2'!L8 -> 0 | DI8: ='J & J Toste DairyInc.'!L8 -> 0 | DJ8: ='Bar Vee DairyInc.'!L8 -> 0 | DK8: ='Railside Jersey FarmsLLC'!L8 -> 0 | DL8: ='Manuel Azevedo Dairy'!L8 -> 0 | DM8: ='Sousa Family Dairy'!L8 -> 0 | DN8: ='UC Davis Animal Science Dairy'!L8 -> 0 | DO8: ='Garcia''s Registered Jerseys'!L8 -> 0 | DP8: ='Lucio Corral Cattle'!L8 -> 0 | DQ8: ='Wickstrom Dairy Inc'!B8 -> 0 | DR8: ='Sam Kooistra Dairy'!L8 -> 0 | DS8: ='Vitorino & Sons Dairy'!L8 -> 0 | DT8: ='Valley Cross Dairy'!L8 -> 0 | DU8: ='John Brasil & Sons Dairy #2'!L8 -> 0 | DV8: ='Pepper Dairy'!L8 -> 0 | DW8: ='Clauss Dairy Farms'!L8 -> 0 | DX8: ='Dairy Central Heifers'!L8 -> 0 | DY8: ='Yosemite Jersey Dairy'!L8 -> 0 | DZ8: ='Sunwest Jersey Dairy'!L8 -> 0 | EA8: ='N & C Silveira Dairy'!L8 -> 0 | EB8: ='Nyman Brothers Dairy'!L8 -> 0 | EC8: ='Broder Farms'!L8 -> 0 | ED8: ='Borba Dairy Farms'!L8 -> 0 | EE8: ='Charles Ahlem Ranch'!L8 -> 0 | EF8: ='James Ahlem Dairy'!L8 -> 0 | EG8: ='Nylund Dairy Farms'!L8 -> 0 | EH8: ='Vierra Ranch Dairy'!L8 -> 0 | EI8: ='Joe O Rocha Dairy Inc.'!L8 -> 0 | EJ8: ='Alves & Son Dairy'!L8 -> 0 | EK8: ='3A Teixeira Dairy'!L8 -> 0 | EL8: ='Denizma_Bud Postma Dairy'!L8 -> 0 | EM8: ='Couco Creek Dairy'!L8 -> 0 | EN8: ='Clausen Dairy'!L8 -> 0
A9: OwnOp = CIWQS | B9: ='A & M De Souza Dairy'!B9 -> 0 | C9: ='Silva Dairy Farms #3A'!B9 -> 0 | D9: ='Joe Borba Dairy Inc.'!B9 -> 0 | E9: ='Ken Van Foeken Dairy #2'!B9 -> 0 | F9: ='Da Rosa Dairy'!B9 -> 0 | G9: ='J_D Brasil Dairy'!#REF! -> #REF! | H9: ='River Rock Ranch LLC'!L9 -> 0 | I9: ='Double Cross #3'!L9 -> 0 | J9: ='Edward Nunes Dairy'!L9 -> 0 | K9: ='Gomes Dairy'!#REF! -> #REF! | L9: ='Roest Family Dairy'!L9 -> 0 | M9: ='Gil Tex Dairy'!L9 -> 0 | N9: ='GJ Silva'!L9 -> 0 | O9: ='Hilmar Holsteins Inc.'!L9 -> 0 | P9: ='Jordao Dairy'!L9 -> 0 | Q9: ='Cross Creek Dairy'!L9 -> 0 | R9: ='Double Cross #2'!L9 -> 0 | S9: ='LarryPetersonDairyFarms#2'!L9 -> 0 | T9: ='Fire_Lake Jerseys #2'!L9 -> 0 | U9: ='Lumar Dairy Farms'!L9 -> 0 | V9: ='CMA Livestock'!L9 -> 0 | W9: ='Fire Lakes Jerseys'!L9 -> 0 | X9: ='Rick Jones Farms'!L9 -> 0 | Y9: ='Silveira Holsteins'!L9 -> 0 | Z9: ='Diamond B Dairy'!L9 -> 0 | AA9: ='Azevedo Dairy'!L9 -> 0 | AB9: ='Valsigna Dairy'!L9 -> 0 | AC9: =WickstromJerseyFarmsInc.!L9 -> 0 | AD9: ='Diniz Dairy'!L9 -> 0 | AE9: ='Crane Dairy Inc.'!L9 -> 0 | AF9: ='GM Silva Dairies #2'!L9 -> 0 | AG9: ='Joe Oliveira Dairy'!#REF! -> #REF! | AH9: ='Vierra Dairy Farms #3'!L9 -> 0 | AI9: ='Nelson Dairy'!L9 -> 0 | AJ9: ='Mario&ChristinaNunesDairy'!L9 -> 0 | AK9: ='B & D Dairy'!L9 -> 0 | AL9: ='Silveira Dairy Inc.'!L9 -> 0 | AM9: ='Jade Jersey Dairy'!L9 -> 0 | AN9: ='Live Oak Dairy A'!L9 -> 0 | AO9: ='T & M Borba Dairy'!L9 -> 0 | AP9: ='Oslo Dairy'!L9 -> 0 | AQ9: ='Kronberg Facility'!L9 -> 0 | AR9: ='Ken Van Foeken Dairy'!L9 -> 0 | AS9: ='Amaral Dairy Farms'!L9 -> 0 | AT9: ='B_6 Dairy'!L9 -> 0 | AU9: ='6D Dores Dairy'!L9 -> 0 | AV9: ='Fanelli Dairy'!L9 -> 0 | AW9: ='Joao Sousa Dairy'!L9 -> 0 | AX9: ='Vierra Dairy Farms #2'!L9 -> 0 | AY9: ='Michael Brasil Dairy'!L9 -> 0 | AZ9: ='Anchor J Dairy'!L9 -> 0 | BA9: ='Oliveira Dairy'!L9 -> 0 | BB9: ='Souza Bros Dairy'!L9 -> 0 | BC9: ='Miguel Family Dairy'!L9 -> 0 | BD9: ='Dias Family Dairy'!L9 -> 0 | BE9: ='Empty was A_D Dairy'!L9 -> 0 | BF9: ='Michael Brasil Dairy #2'!L9 -> 0 | BG9: ='F & A Lemos Dairy'!L9 -> 0 | BH9: ='Alves & Son Dairy #2'!L9 -> 0 | BI9: ='Golf Link RanchesLLC'!L9 -> 0 | BJ9: ='Triple M Jerseys'!L9 -> 0 | BK9: ='Jose & Teresa Soares Dairy'!L9 -> 0 | BL9: ='MachadoGabriel&SonsDairy'!L9 -> 0 | BM9: ='Hawkins Ranch'!L9 -> 0 | BN9: ='Silva Dairy Farms #3B'!L9 -> 0 | BO9: =AhlemFarmsPartnership!L9 -> 0 | BP9: ='Vierra Dairy Farms #4'!L9 -> 0 | BQ9: ='CaliforniaDairyFarms LLC'!L9 -> 0 | BR9: ='Larry Peterson Dairy'!L9 -> 0 | BS9: ='Joe Egli&Sons Dairy'!L9 -> 0 | BT9: ='CMA Livestock #2'!L9 -> 0 | BU9: ='Valentine Dairy'!L9 -> 0 | BV9: ='CMC Jerseys LLC'!L9 -> 0 | BW9: ='Fanelli_Fanelli Brothers'!L9 -> 0 | BX9: ='Martins Bros Dairy'!L9 -> 0 | BY9: ='Gomes Heifer Ranch'!L9 -> 0 | BZ9: ='Ed Hirdes Dairy'!B9 -> 0 | CA9: ='Dematos Dairy'!L9 -> 0 | CB9: ='Carlos Estacio&Sons Dairy'!L9 -> 0 | CC9: ='Live Oak Dairy G'!L9 -> 0 | CD9: ='Verissimo Facility'!L9 -> 0 | CE9: ='Double Cross Dairy'!L9 -> 0 | CF9: ='Double Cross #4'!L9 -> 0 | CG9: ='King Dairy'!L9 -> 0 | CH9: ='Vieira Livestock'!L9 -> 0 | CI9: ='AldenPeterson&SonsDairy Inc.'!L9 -> 0 | CJ9: ='John Nunes Dairy #3'!L9 -> 0 | CK9: ='Roestar Dairy'!L9 -> 0 | CL9: ='Luis M. Azevedo Dairy'!L9 -> 0 | CM9: ='Arlinda Holsteins'!L9 -> 0 | CN9: ='Robert Gioletti & Sons Dairy'!L9 -> 0 | CO9: ='Carl Vieira Dairy'!L9 -> 0 | CP9: ='John Brasil & Sons Dairy'!L9 -> 0 | CQ9: ='John Brasil Dairy #3'!L9 -> 0 | CR9: ='KMA Dairy'!L9 -> 0 | CS9: ='Sallaberry Ranch'!L9 -> 0 | CT9: ='Alfred C Nunes Dairy'!L9 -> 0 | CU9: ='Jim Vieira & Son Dairy'!L9 -> 0 | CV9: ='Ehrlich Dairy'!L9 -> 0 | CW9: ='D&A Brasil Facility'!B9 -> 0 | CX9: ='Silva''s Holsteins'!B9 -> 0 | CY9: ='G J Silva #3'!B9 -> 0 | CZ9: ='Jim Vieira and Son Dairy #2'!L9 -> 0 | DA9: ='Johal Dairy'!L9 -> 0 | DB9: ='A & G Azevedo Dairy'!L9 -> 0 | DC9: ='Gentle Breezes Dairy'!L9 -> 0 | DD9: ='Joe Sousa Jr Dairy'!L9 -> 0 | DE9: ='John Brasil Heifers'!L9 -> 0 | DF9: ='MHF Dairy'!L9 -> 0 | DG9: ='Brindiero&DanbomDairyFarms'!L9 -> 0 | DH9: ='A&C Machado Dairy #2'!L9 -> 0 | DI9: ='J & J Toste DairyInc.'!L9 -> 0 | DJ9: ='Bar Vee DairyInc.'!L9 -> 0 | DK9: ='Railside Jersey FarmsLLC'!L9 -> 0 | DL9: ='Manuel Azevedo Dairy'!L9 -> 0 | DM9: ='Sousa Family Dairy'!L9 -> 0 | DN9: ='UC Davis Animal Science Dairy'!L9 -> 0 | DO9: ='Garcia''s Registered Jerseys'!L9 -> 0 | DP9: ='Lucio Corral Cattle'!L9 -> 0 | DQ9: ='Wickstrom Dairy Inc'!B9 -> 0 | DR9: ='Sam Kooistra Dairy'!L9 -> 0 | DS9: ='Vitorino & Sons Dairy'!L9 -> 0 | DT9: ='Valley Cross Dairy'!L9 -> 0 | DU9: ='John Brasil & Sons Dairy #2'!L9 -> 0 | DV9: ='Pepper Dairy'!L9 -> 0 | DW9: ='Clauss Dairy Farms'!L9 -> 0 | DX9: ='Dairy Central Heifers'!L9 -> 0 | DY9: ='Yosemite Jersey Dairy'!L9 -> 0 | DZ9: ='Sunwest Jersey Dairy'!L9 -> 0 | EA9: ='N & C Silveira Dairy'!L9 -> 0 | EB9: ='Nyman Brothers Dairy'!L9 -> 0 | EC9: ='Broder Farms'!L9 -> 0 | ED9: ='Borba Dairy Farms'!L9 -> 0 | EE9: ='Charles Ahlem Ranch'!L9 -> 0 | EF9: ='James Ahlem Dairy'!L9 -> 0 | EG9: ='Nylund Dairy Farms'!L9 -> 0 | EH9: ='Vierra Ranch Dairy'!L9 -> 0 | EI9: ='Joe O Rocha Dairy Inc.'!L9 -> 0 | EJ9: ='Alves & Son Dairy'!L9 -> 0 | EK9: ='3A Teixeira Dairy'!L9 -> 0 | EL9: ='Denizma_Bud Postma Dairy'!L9 -> 0 | EM9: ='Couco Creek Dairy'!L9 -> 0 | EN9: ='Clausen Dairy'!L9 -> 0
A10: WDID | B10: ='A & M De Souza Dairy'!B10 -> 5B50NC00226 | C10: ='Silva Dairy Farms #3A'!B10 -> 5B24NC00263 | D10: ='Joe Borba Dairy Inc.'!B10 -> 5B50NC00262 | E10: ='Ken Van Foeken Dairy #2'!B10 -> 5B24NC00160 | F10: ='Da Rosa Dairy'!B10 -> 5B50NC00277 | G10: ='J_D Brasil Dairy'!#REF! -> #REF! | H10: ='River Rock Ranch LLC'!L10 -> 5B24NC00272 | I10: ='Double Cross #3'!L10 -> 5C245033001 | J10: ='Edward Nunes Dairy'!L10 -> 5B39NC00062 | K10: ='Gomes Dairy'!#REF! -> #REF! | L10: ='Roest Family Dairy'!L10 -> 5B50NC00111 | M10: ='Gil Tex Dairy'!L10 -> 5C505022001 | N10: ='GJ Silva'!L10 -> 5B50NC00275 | O10: ='Hilmar Holsteins Inc.'!L10 -> 5B24NC00131 | P10: ='Jordao Dairy'!L10 -> 5B50NC00221 | Q10: ='Cross Creek Dairy'!L10 -> 5B24NC00159 | R10: ='Double Cross #2'!L10 -> 5B24NC00277 | S10: ='LarryPetersonDairyFarms#2'!L10 -> 5B24NC00107 | T10: ='Fire_Lake Jerseys #2'!L10 -> 5B50NC00289 | U10: ='Lumar Dairy Farms'!L10 -> 5B50NC00269 | V10: ='CMA Livestock'!L10 -> 5B24NC00163 | W10: ='Fire Lakes Jerseys'!L10 -> 5B50NC00308 | X10: ='Rick Jones Farms'!L10 -> 5C245037001 | Y10: ='Silveira Holsteins'!L10 -> 5B24NC00149 | Z10: ='Diamond B Dairy'!L10 -> 5B50NC00300 | AA10: ='Azevedo Dairy'!L10 -> 5B24NC00111 | AB10: ='Valsigna Dairy'!L10 -> 5B24NC00144 | AC10: =WickstromJerseyFarmsInc.!L10 -> 5B24NC00123 | AD10: ='Diniz Dairy'!L10 -> 5B24NC00126 | AE10: ='Crane Dairy Inc.'!L10 -> 5B24NC00128 | AF10: ='GM Silva Dairies #2'!L10 -> 5B24NC00129 | AG10: ='Joe Oliveira Dairy'!#REF! -> #REF! | AH10: ='Vierra Dairy Farms #3'!L10 -> 5B24NC00133 | AI10: ='Nelson Dairy'!L10 -> 5B24NC00134 | AJ10: ='Mario&ChristinaNunesDairy'!L10 -> 5B24NC00136 | AK10: ='B & D Dairy'!L10 -> 5B24NC00139 | AL10: ='Silveira Dairy Inc.'!L10 -> 5B24NC00140 | AM10: ='Jade Jersey Dairy'!L10 -> 5B24NC00141 | AN10: ='Live Oak Dairy A'!L10 -> 5B24NC00142 | AO10: ='T & M Borba Dairy'!L10 -> 5B24NC00145 | AP10: ='Oslo Dairy'!L10 -> 5B24NC00146 | AQ10: ='Kronberg Facility'!L10 -> 5B24NC00148 | AR10: ='Ken Van Foeken Dairy'!L10 -> 5B24NC00150 | AS10: ='Amaral Dairy Farms'!L10 -> 5B24NC00152 | AT10: ='B_6 Dairy'!L10 -> 5B24NC00156 | AU10: ='6D Dores Dairy'!L10 -> 5B24NC00157 | AV10: ='Fanelli Dairy'!L10 -> 5B24NC00158 | AW10: ='Joao Sousa Dairy'!L10 -> 5B24NC00162 | AX10: ='Vierra Dairy Farms #2'!L10 -> 5B24NC00165 | AY10: ='Michael Brasil Dairy'!L10 -> 5B24NC00264 | AZ10: ='Anchor J Dairy'!L10 -> 5B24NC00265 | BA10: ='Oliveira Dairy'!L10 -> 5B24NC00267 | BB10: ='Souza Bros Dairy'!L10 -> 5B24NC00268 | BC10: ='Miguel Family Dairy'!L10 -> 5B24NC00270 | BD10: ='Dias Family Dairy'!L10 -> 5B24NC00271 | BE10: ='Empty was A_D Dairy'!L10 -> 5B24NC00273 | BF10: ='Michael Brasil Dairy #2'!L10 -> 5B24NC00275 | BG10: ='F & A Lemos Dairy'!L10 -> 5B24NC00280 | BH10: ='Alves & Son Dairy #2'!L10 -> 5B24NC00281 | BI10: ='Golf Link RanchesLLC'!L10 -> 5B24NC00283 | BJ10: ='Triple M Jerseys'!L10 -> 5B24NC00287 | BK10: ='Jose & Teresa Soares Dairy'!L10 -> 5B24NC00288 | BL10: ='MachadoGabriel&SonsDairy'!L10 -> 5B24NC00290 | BM10: ='Hawkins Ranch'!L10 -> 5B24NC00333 | BN10: ='Silva Dairy Farms #3B'!L10 -> 5B24NC00262 | BO10: =AhlemFarmsPartnership!L10 -> 5B24NC00104 | BP10: ='Vierra Dairy Farms #4'!L10 -> 5B24NC00105 | BQ10: ='CaliforniaDairyFarms LLC'!L10 -> 5B24NC00106 | BR10: ='Larry Peterson Dairy'!L10 -> 5B24NC00108 | BS10: ='Joe Egli&Sons Dairy'!L10 -> 5B24NC00113 | BT10: ='CMA Livestock #2'!L10 -> 5B24NC00114 | BU10: ='Valentine Dairy'!L10 -> 5B24NC00116 | BV10: ='CMC Jerseys LLC'!L10 -> 5B24NC00117 | BW10: ='Fanelli_Fanelli Brothers'!L10 -> 5B24NC00118 | BX10: ='Martins Bros Dairy'!L10 -> 5B24NC00122 | BY10: ='Gomes Heifer Ranch'!L10 -> 5B50NC00207 | BZ10: ='Ed Hirdes Dairy'!B10 -> 5B50NC00208 | CA10: ='Dematos Dairy'!L10 -> 5B50NC00209 | CB10: ='Carlos Estacio&Sons Dairy'!L10 -> 5B50NC00215 | CC10: ='Live Oak Dairy G'!L10 -> 5B50NC00323 | CD10: ='Verissimo Facility'!L10 -> 5B50NC00219 | CE10: ='Double Cross Dairy'!L10 -> 5B50NC00220 | CF10: ='Double Cross #4'!L10 -> 5B50NC00222 | CG10: ='King Dairy'!L10 -> 5B50NC00223 | CH10: ='Vieira Livestock'!L10 -> 5B50NC00225 | CI10: ='AldenPeterson&SonsDairy Inc.'!L10 -> 5B50NC00227 | CJ10: ='John Nunes Dairy #3'!L10 -> 5B50NC00228 | CK10: ='Roestar Dairy'!L10 -> 5B50NC00291 | CL10: ='Luis M. Azevedo Dairy'!L10 -> 5B50NC00252 | CM10: ='Arlinda Holsteins'!L10 -> 5B50NC00253 | CN10: ='Robert Gioletti & Sons Dairy'!L10 -> 5B50NC00254 | CO10: ='Carl Vieira Dairy'!L10 -> 5B50NC00255 | CP10: ='John Brasil & Sons Dairy'!L10 -> 5B50NC00259 | CQ10: ='John Brasil Dairy #3'!L10 -> 5B50NC00260 | CR10: ='KMA Dairy'!L10 -> 5B50NC00263 | CS10: ='Sallaberry Ranch'!L10 -> 5B50NC00264 | CT10: ='Alfred C Nunes Dairy'!L10 -> 5B50NC00265 | CU10: ='Jim Vieira & Son Dairy'!L10 -> 5B50NC00267 | CV10: ='Ehrlich Dairy'!L10 -> 5B50NC00231 | CW10: ='D&A Brasil Facility'!B10 -> 5B50NC00268 | CX10: ='Silva''s Holsteins'!B10 -> 5B50NC00232 | CY10: ='G J Silva #3'!B10 -> 5B50NC00270 | CZ10: ='Jim Vieira and Son Dairy #2'!L10 -> 5B50NC00271 | DA10: ='Johal Dairy'!L10 -> 5B50NC00272 | DB10: ='A & G Azevedo Dairy'!L10 -> 5B50NC00273 | DC10: ='Gentle Breezes Dairy'!L10 -> 5B50NC00325 | DD10: ='Joe Sousa Jr Dairy'!L10 -> 5B50NC00274 | DE10: ='John Brasil Heifers'!L10 -> 5B50NC00239 | DF10: ='MHF Dairy'!L10 -> 5B50NC00276 | DG10: ='Brindiero&DanbomDairyFarms'!L10 -> 5B50NC00278 | DH10: ='A&C Machado Dairy #2'!L10 -> 5B50NC00280 | DI10: ='J & J Toste DairyInc.'!L10 -> 5B50NC00284 | DJ10: ='Bar Vee DairyInc.'!L10 -> 5B50NC00285 | DK10: ='Railside Jersey FarmsLLC'!L10 -> 5B50NC00287 | DL10: ='Manuel Azevedo Dairy'!L10 -> 5B50NC00288 | DM10: ='Sousa Family Dairy'!L10 -> 5B50NC00290 | DN10: ='UC Davis Animal Science Dairy'!L10 -> 5A57NC00022 | DO10: ='Garcia''s Registered Jerseys'!L10 -> 5B50NC00240 | DP10: ='Lucio Corral Cattle'!L10 -> 5B50NC00242 | DQ10: ='Wickstrom Dairy Inc'!B10 -> 5B50NC00243 | DR10: ='Sam Kooistra Dairy'!L10 -> 5B50NC00244 | DS10: ='Vitorino & Sons Dairy'!L10 -> 5B50NC00246 | DT10: ='Valley Cross Dairy'!L10 -> 5B50NC00247 | DU10: ='John Brasil & Sons Dairy #2'!L10 -> 5B50NC00248 | DV10: ='Pepper Dairy'!L10 -> 5B24NC00286 | DW10: ='Clauss Dairy Farms'!L10 -> 5B24NC00119 | DX10: ='Dairy Central Heifers'!L10 -> 5B50NC00301 | DY10: ='Yosemite Jersey Dairy'!L10 -> 5B24NC00137 | DZ10: ='Sunwest Jersey Dairy'!L10 -> 5B24NC00120 | EA10: ='N & C Silveira Dairy'!L10 -> 5B50NC00292 | EB10: ='Nyman Brothers Dairy'!L10 -> 5B24NC00110 | EC10: ='Broder Farms'!L10 -> 5B24NC00112 | ED10: ='Borba Dairy Farms'!L10 -> 5B24NC00143 | EE10: ='Charles Ahlem Ranch'!L10 -> 5B24NC00103 | EF10: ='James Ahlem Dairy'!L10 -> 5B24NC00125 | EG10: ='Nylund Dairy Farms'!L10 -> 5B24NC00135 | EH10: ='Vierra Ranch Dairy'!L10 -> 5B24NC00166 | EI10: ='Joe O Rocha Dairy Inc.'!L10 -> 5B24NC00278 | EJ10: ='Alves & Son Dairy'!L10 -> 5B24NC00285 | EK10: ='3A Teixeira Dairy'!L10 -> 5B24NC00291 | EL10: ='Denizma_Bud Postma Dairy'!L10 -> 5B50NC00306 | EM10: ='Couco Creek Dairy'!L10 -> 5B50NC00312 | EN10: ='Clausen Dairy'!L10 -> 5B24NC00279
A11: STATUS | B11: ='A & M De Souza Dairy'!B11 -> Active | C11: ='Silva Dairy Farms #3A'!B11 -> Active | D11: ='Joe Borba Dairy Inc.'!B11 -> Active | E11: ='Ken Van Foeken Dairy #2'!B11 -> Active | F11: ='Da Rosa Dairy'!B11 -> Active | G11: ='J_D Brasil Dairy'!#REF! -> #REF! | H11: ='River Rock Ranch LLC'!L11 -> Active | I11: ='Double Cross #3'!L11 -> Active | J11: ='Edward Nunes Dairy'!L11 -> Active | K11: ='Gomes Dairy'!#REF! -> #REF! | L11: ='Roest Family Dairy'!L11 -> Active | M11: ='Gil Tex Dairy'!L11 -> Active | N11: ='GJ Silva'!L11 -> Active | O11: ='Hilmar Holsteins Inc.'!L11 -> Active | P11: ='Jordao Dairy'!L11 -> Active | Q11: ='Cross Creek Dairy'!L11 -> Active | R11: ='Double Cross #2'!L11 -> Active | S11: ='LarryPetersonDairyFarms#2'!L11 -> Active | T11: ='Fire_Lake Jerseys #2'!L11 -> Active | U11: ='Lumar Dairy Farms'!L11 -> Active | V11: ='CMA Livestock'!L11 -> Active | W11: ='Fire Lakes Jerseys'!L11 -> Active | X11: ='Rick Jones Farms'!L11 -> Active | Y11: ='Silveira Holsteins'!L11 -> Active | Z11: ='Diamond B Dairy'!L11 -> Active | AA11: ='Azevedo Dairy'!L11 -> Active | AB11: ='Valsigna Dairy'!L11 -> Active | AC11: =WickstromJerseyFarmsInc.!L11 -> Active | AD11: ='Diniz Dairy'!L11 -> Active | AE11: ='Crane Dairy Inc.'!L11 -> Active | AF11: ='GM Silva Dairies #2'!L11 -> Active | AG11: ='Joe Oliveira Dairy'!#REF! -> #REF! | AH11: ='Vierra Dairy Farms #3'!L11 -> Active | AI11: ='Nelson Dairy'!L11 -> Active | AJ11: ='Mario&ChristinaNunesDairy'!L11 -> Active | AK11: ='B & D Dairy'!L11 -> Active | AL11: ='Silveira Dairy Inc.'!L11 -> Active | AM11: ='Jade Jersey Dairy'!L11 -> Active | AN11: ='Live Oak Dairy A'!L11 -> Active | AO11: ='T & M Borba Dairy'!L11 -> Active | AP11: ='Oslo Dairy'!L11 -> Active | AQ11: ='Kronberg Facility'!L11 -> Active | AR11: ='Ken Van Foeken Dairy'!L11 -> Active | AS11: ='Amaral Dairy Farms'!L11 -> Active | AT11: ='B_6 Dairy'!L11 -> Active | AU11: ='6D Dores Dairy'!L11 -> Active | AV11: ='Fanelli Dairy'!L11 -> Active | AW11: ='Joao Sousa Dairy'!L11 -> Active | AX11: ='Vierra Dairy Farms #2'!L11 -> Active | AY11: ='Michael Brasil Dairy'!L11 -> Active | AZ11: ='Anchor J Dairy'!L11 -> Active | BA11: ='Oliveira Dairy'!L11 -> Active | BB11: ='Souza Bros Dairy'!L11 -> Active | BC11: ='Miguel Family Dairy'!L11 -> Active | BD11: ='Dias Family Dairy'!L11 -> Active | BE11: ='Empty was A_D Dairy'!L11 -> Historical | BF11: ='Michael Brasil Dairy #2'!L11 -> Active | BG11: ='F & A Lemos Dairy'!L11 -> Active | BH11: ='Alves & Son Dairy #2'!L11 -> Active | BI11: ='Golf Link RanchesLLC'!L11 -> Active | BJ11: ='Triple M Jerseys'!L11 -> Active | BK11: ='Jose & Teresa Soares Dairy'!L11 -> Active | BL11: ='MachadoGabriel&SonsDairy'!L11 -> Active | BM11: ='Hawkins Ranch'!L11 -> Active | BN11: ='Silva Dairy Farms #3B'!L11 -> Active | BO11: =AhlemFarmsPartnership!L11 -> Active | BP11: ='Vierra Dairy Farms #4'!L11 -> Active | BQ11: ='CaliforniaDairyFarms LLC'!L11 -> Active | BR11: ='Larry Peterson Dairy'!L11 -> Active | BS11: ='Joe Egli&Sons Dairy'!L11 -> Active | BT11: ='CMA Livestock #2'!L11 -> Active | BU11: ='Valentine Dairy'!L11 -> Active | BV11: ='CMC Jerseys LLC'!L11 -> Active | BW11: ='Fanelli_Fanelli Brothers'!L11 -> Active | BX11: ='Martins Bros Dairy'!L11 -> Active | BY11: ='Gomes Heifer Ranch'!L11 -> Active | BZ11: ='Ed Hirdes Dairy'!B11 -> Historical | CA11: ='Dematos Dairy'!L11 -> Active | CB11: ='Carlos Estacio&Sons Dairy'!L11 -> Active | CC11: ='Live Oak Dairy G'!L11 -> Active | CD11: ='Verissimo Facility'!L11 -> Active | CE11: ='Double Cross Dairy'!L11 -> Active | CF11: ='Double Cross #4'!L11 -> Active | CG11: ='King Dairy'!L11 -> Active | CH11: ='Vieira Livestock'!L11 -> Active | CI11: ='AldenPeterson&SonsDairy Inc.'!L11 -> Active | CJ11: ='John Nunes Dairy #3'!L11 -> Active | CK11: ='Roestar Dairy'!L11 -> Active | CL11: ='Luis M. Azevedo Dairy'!L11 -> Active | CM11: ='Arlinda Holsteins'!L11 -> Active | CN11: ='Robert Gioletti & Sons Dairy'!L11 -> Active | CO11: ='Carl Vieira Dairy'!L11 -> Active | CP11: ='John Brasil & Sons Dairy'!L11 -> Active | CQ11: ='John Brasil Dairy #3'!L11 -> Active | CR11: ='KMA Dairy'!L11 -> Active | CS11: ='Sallaberry Ranch'!L11 -> Active | CT11: ='Alfred C Nunes Dairy'!L11 -> Active | CU11: ='Jim Vieira & Son Dairy'!L11 -> Active | CV11: ='Ehrlich Dairy'!L11 -> Active | CW11: ='D&A Brasil Facility'!B11 -> Historical | CX11: ='Silva''s Holsteins'!B11 -> Active | CY11: ='G J Silva #3'!B11 -> #N/A | CZ11: ='Jim Vieira and Son Dairy #2'!L11 -> Active | DA11: ='Johal Dairy'!L11 -> Active | DB11: ='A & G Azevedo Dairy'!L11 -> Active | DC11: ='Gentle Breezes Dairy'!L11 -> Active | DD11: ='Joe Sousa Jr Dairy'!L11 -> Active | DE11: ='John Brasil Heifers'!L11 -> Active | DF11: ='MHF Dairy'!L11 -> Active | DG11: ='Brindiero&DanbomDairyFarms'!L11 -> Active | DH11: ='A&C Machado Dairy #2'!L11 -> Active | DI11: ='J & J Toste DairyInc.'!L11 -> Active | DJ11: ='Bar Vee DairyInc.'!L11 -> Active | DK11: ='Railside Jersey FarmsLLC'!L11 -> Active | DL11: ='Manuel Azevedo Dairy'!L11 -> Active | DM11: ='Sousa Family Dairy'!L11 -> Active | DN11: ='UC Davis Animal Science Dairy'!L11 -> Active | DO11: ='Garcia''s Registered Jerseys'!L11 -> Active | DP11: ='Lucio Corral Cattle'!L11 -> Historical | DQ11: ='Wickstrom Dairy Inc'!B11 -> Active | DR11: ='Sam Kooistra Dairy'!L11 -> Active | DS11: ='Vitorino & Sons Dairy'!L11 -> Active | DT11: ='Valley Cross Dairy'!L11 -> Active | DU11: ='John Brasil & Sons Dairy #2'!L11 -> Active | DV11: ='Pepper Dairy'!L11 -> Active | DW11: ='Clauss Dairy Farms'!L11 -> Active | DX11: ='Dairy Central Heifers'!L11 -> Active | DY11: ='Yosemite Jersey Dairy'!L11 -> Active | DZ11: ='Sunwest Jersey Dairy'!L11 -> Active | EA11: ='N & C Silveira Dairy'!L11 -> Active | EB11: ='Nyman Brothers Dairy'!L11 -> Active | EC11: ='Broder Farms'!L11 -> Active | ED11: ='Borba Dairy Farms'!L11 -> Active | EE11: ='Charles Ahlem Ranch'!L11 -> Active | EF11: ='James Ahlem Dairy'!L11 -> Active | EG11: ='Nylund Dairy Farms'!L11 -> Active | EH11: ='Vierra Ranch Dairy'!L11 -> Active | EI11: ='Joe O Rocha Dairy Inc.'!L11 -> Active | EJ11: ='Alves & Son Dairy'!L11 -> Active | EK11: ='3A Teixeira Dairy'!L11 -> Active | EL11: ='Denizma_Bud Postma Dairy'!L11 -> Active | EM11: ='Couco Creek Dairy'!L11 -> Active | EN11: ='Clausen Dairy'!L11 -> Active
A12: REG MEASURE TITLE | B12: ='A & M De Souza Dairy'!B12 -> Enrollee Under Dairy GO for De Sousa, Armelin & Maria - A & M De Souza Dairy | C12: ='Silva Dairy Farms #3A'!B12 -> Enrollee Under Dairy GO for Silva, Manuel - Silva Dairy Farms #3A | D12: ='Joe Borba Dairy Inc.'!B12 -> Enrollee Under Dairy Gen Order for Joe Borba Dairy Inc | E12: ='Ken Van Foeken Dairy #2'!B12 -> Enrollee Under Dairy GO for Van Foeken, Kenneth L. - Ken Van Foeken Dairy #2 | F12: ='Da Rosa Dairy'!B12 -> Enrollee Under Dairy GO for Da Rosa, Luis & Olivia | G12: ='J_D Brasil Dairy'!#REF! -> #REF! | H12: ='River Rock Ranch LLC'!L12 -> Enrollee Under Dairy GO for River Rock Ranch, LLC | I12: ='Double Cross #3'!L12 -> Enrollee Under Dairy GO for Ahlem, Mark - Double Cross #3 | J12: ='Edward Nunes Dairy'!L12 -> Enrollee Under Dairy GO for Nunes, Edward - Edward Nunes Dairy | K12: ='Gomes Dairy'!#REF! -> #REF! | L12: ='Roest Family Dairy'!L12 -> Enrollee Under Dairy GO for Roest, Arie | M12: ='Gil Tex Dairy'!L12 -> Enrollee Under Dairy GO for Teixeira, Gilbert & Linda - Gil Tex Dairy | N12: ='GJ Silva'!L12 -> Enrollee Under Dairy GO for Latters, Susan - G J Silva (# 2) | O12: ='Hilmar Holsteins Inc.'!L12 -> Enrollee Under Dairy GO for Matheron, Aaron dba Hilmar Holsteins Inc. | P12: ='Jordao Dairy'!L12 -> Enrollee Under Dairy GO for Jordao, Joe and Jose | Q12: ='Cross Creek Dairy'!L12 -> Enrollee Under Dairy Gen Order for Branco, Joe & Cathy - Vierra Dairy LLC #4 | R12: ='Double Cross #2'!L12 -> Enrollee Under Dairy GO for Coehlo, Joe - Double Cross #2 | S12: ='LarryPetersonDairyFarms#2'!L12 -> Enrollee Under Dairy GO for John Leonardo - Larry B. Peterson Dairy Farms #2 | T12: ='Fire_Lake Jerseys #2'!L12 -> Enrollee Under Dairy GO for Thomas, Rhonda, Fire-Lake Jerseys #2 | U12: ='Lumar Dairy Farms'!L12 -> Enrollee Under Dairy Gen Order for Borba, Luis & Maria, Lumar Dairy Farms | V12: ='CMA Livestock'!L12 -> Enrollee Under Dairy GO for Manuel Luis - Double Cross #5 | W12: ='Fire Lakes Jerseys'!L12 -> Enrollee Under Dairy GO for Sanders, Scott & Sharalee | X12: ='Rick Jones Farms'!L12 -> Enrollee Under Dairy GO for Rick Jones Farms | Y12: ='Silveira Holsteins'!L12 -> Enrollee Under Dairy GO for Silveira, Manuel - Silveira Holsteins | Z12: ='Diamond B Dairy'!L12 -> Enrollee Under Dairy GO for Meneses, Adeline - Diamond B Dairy | AA12: ='Azevedo Dairy'!L12 -> Enrollee Under Dairy Gen Order for Azevedo, Tiberio & Rosa - Azevedo Dairy | AB12: ='Valsigna Dairy'!L12 -> Enrollee Under Dairy GO for Wickstrom, Tim & Vern - Valsigna Dairy | AC12: =WickstromJerseyFarmsInc.!L12 -> Enrollee Under Dairy GO for Wickstrom, Mike - Wickstrom Jersey Farms, Inc. | AD12: ='Diniz Dairy'!L12 -> Enrollee Under Dairy GO for Diniz, Antonio V & Maria - Diniz Dairy | AE12: ='Crane Dairy Inc.'!L12 -> Enrollee Under Dairy GO for Leroy Souza - Crane Dairy, Inc | AF12: ='GM Silva Dairies #2'!L12 -> Enrollee Under Dairy GO for Silva, George & Margaret - GM Silva Dairies #2 | AG12: ='Joe Oliveira Dairy'!#REF! -> #REF! | AH12: ='Vierra Dairy Farms #3'!L12 -> Enrollee Under Dairy Gen Order for Ferreira, Eleanor - Vierra Dairy Farms #3 | AI12: ='Nelson Dairy'!L12 -> Enrollee Under Dairy GO for Joyce W. Nelson and Trust - Nelson Dairy | AJ12: ='Mario&ChristinaNunesDairy'!L12 -> Enrollee Under Dairy GO for Jorge, Luis & Maria - Luis & Maria Jorge Dairy | AK12: ='B & D Dairy'!L12 -> Enrollee Under Dairy GO for Huff, Eric - B & D Dairy | AL12: ='Silveira Dairy Inc.'!L12 -> Enrollee Under Dairy GO for Nyman, Brad - Live Oak Dairy H | AM12: ='Jade Jersey Dairy'!L12 -> Enrollee Under Dairy Gen Order for Ahlem, James & Carol - Jade Jersey Dairy | AN12: ='Live Oak Dairy A'!L12 -> Enrollee Under Dairy GO for Nyman, Brad - Live Oak Dairy A | AO12: ='T & M Borba Dairy'!L12 -> Enrollee Under Dairy GO for DeBorba, Maria & Antonio - T & M Borba Dairy | AP12: ='Oslo Dairy'!L12 -> Enrollee Under Dairy GO for Nymand, Brad - Oslo Dairy | AQ12: ='Kronberg Facility'!L12 -> Enrollee Under Dairy GO for Kronberg, Virgil - Kronberg Facility | AR12: ='Ken Van Foeken Dairy'!L12 -> Enrollee Under Dairy GO for Van Foeken, Kenneth L - Ken Van Foeken Dairy | AS12: ='Amaral Dairy Farms'!L12 -> Enrollee Under Dairy GO for Kindberg, Mik - Amaral Dairy Farms | AT12: ='B_6 Dairy'!L12 -> Enrollee Under Dairy Gen Order for Borba, Mike - B-6 Dairy | AU12: ='6D Dores Dairy'!L12 -> Enrollee Under Dairy GO for Dores, John - 6D Dores Dairy | AV12: ='Fanelli Dairy'!L12 -> Enrollee Under Dairy GO for Fanelli, Phil V - Fanelli Dairy | AW12: ='Joao Sousa Dairy'!L12 -> Enrollee Under Dairy GO for Sousa, Joao - Joao Sousa Dairy | AX12: ='Vierra Dairy Farms #2'!L12 -> Enrollee Under Dairy GO for R & R Ranches LLC - Vierra Dairy Farms #2 | AY12: ='Michael Brasil Dairy'!L12 -> Enrollee Under Dairy Gen Order for Brasil, Michael - Borba Cattle Company, LP | AZ12: ='Anchor J Dairy'!L12 -> Enrollee Under Dairy GO for Stevinson, James J, A Corporation - Anchor J Dairy | BA12: ='Oliveira Dairy'!L12 -> Enrollee Under Dairy GO for Oliveira, Arthur & Antelma - Oliveira Dairy | BB12: ='Souza Bros Dairy'!L12 -> Enrollee Under Dairy GO for Souza, Joe S & John S - Souza Bros Dairy | BC12: ='Miguel Family Dairy'!L12 -> Enrollee Under Dairy GO for Dennis Miguel - Miguel Family Dairy | BD12: ='Dias Family Dairy'!L12 -> Enrollee Under Dairy GO for Dias, Robert - Dias Family Dairy | BE12: ='Empty was A_D Dairy'!L12 -> Enrollee Under Dairy GO for Lewis, Joe Jr. | BF12: ='Michael Brasil Dairy #2'!L12 -> Enrollee Under Dairy Gen Order for Brasil, Michael - Michael Brasil Dairy #2 | BG12: ='F & A Lemos Dairy'!L12 -> Enrollee Under Dairy GO for Lemos, Frank S & Annette - F & A Lemos Dairy | BH12: ='Alves & Son Dairy #2'!L12 -> Enrollee Under Dairy Gen Order for Alves & Son Dairy #2 | BI12: ='Golf Link RanchesLLC'!L12 -> Enrollee Under Dairy GO for Ahlem, Mark - Golf Link Ranches, LLC | BJ12: ='Triple M Jerseys'!L12 -> Enrollee Under Dairy GO for - Dan Perry Dairy | BK12: ='Jose & Teresa Soares Dairy'!L12 -> Enrollee Under Dairy GO for Soares, Jose & Teresa - Jose & Teresa Soares Dairy | BL12: ='MachadoGabriel&SonsDairy'!L12 -> Enrollee Under Dairy GO for Machado, Mary - Machado Gabriel & Sons Dairy | BM12: ='Hawkins Ranch'!L12 -> Enrollee Under Dairy GO for James J. Stevinson, a Corporation - Hawkins Ranch | BN12: ='Silva Dairy Farms #3B'!L12 -> Enrollee Under Dairy GO for Silva, Manuel and George - Silva Dairy Farms #3B | BO12: =AhlemFarmsPartnership!L12 -> Enrollee Under Dairy Gen Order for Ahlem Farms Partnership | BP12: ='Vierra Dairy Farms #4'!L12 -> Enrollee Under Dairy Gen Order for Swanson, Matt - Vierra Heifer Ranch (Dairy) | BQ12: ='CaliforniaDairyFarms LLC'!L12 -> Enrollee Under Dairy Gen Order for Forebay Farms, LLC - California Dairy Farms, LLC | BR12: ='Larry Peterson Dairy'!L12 -> Enrollee Under Dairy GO for Ahlem, Mark - Double Cross #6 | BS12: ='Joe Egli&Sons Dairy'!L12 -> Enrollee Under Dairy GO for Egli, Joseph - Joe Egli and Sons Dairy | BT12: ='CMA Livestock #2'!L12 -> Enrollee Under Dairy GO for Ahlem, Mark - CMA Livestock #2 | BU12: ='Valentine Dairy'!L12 -> Enrollee Under Dairy GO for Jorritsma, Kimberly Clauss - Valentine Dairy | BV12: ='CMC Jerseys LLC'!L12 -> Enrollee Under Dairy Gen Order for Ahlem, Mark - CMC Jerseys LLC | BW12: ='Fanelli_Fanelli Brothers'!L12 -> Enrollee Under Dairy GO for Fanelli Bros Partnership - Fanelli Dairy | BX12: ='Martins Bros Dairy'!L12 -> Enrollee Under Dairy GO for Martins, George - Martins Bros Dairy | BY12: ='Gomes Heifer Ranch'!L12 -> Enrollee Under Dairy GO for Gioletti, Devin - Blaker Heifer Ranch | BZ12: ='Ed Hirdes Dairy'!B12 -> Enrollee Under Dairy GO for Hirdes, Edward & Marilyn | CA12: ='Dematos Dairy'!L12 -> Enrollee Under Dairy GO for Dematos, Nuno & Marylou - Dematos Dairy | CB12: ='Carlos Estacio&Sons Dairy'!L12 -> Enrollee Under Dairy GO for Estacio, Carlos F & Maria | CC12: ='Live Oak Dairy G'!L12 -> Enrollee Under Dairy Gen Order for Nyman, Brad, Live Oak Dairy G | CD12: ='Verissimo Facility'!L12 -> Enrollee Under Dairy GO for Machado, Adelina V. - Verissimo Facility | CE12: ='Double Cross Dairy'!L12 -> Enrollee Under Dairy GO for Double Cross Dairy | CF12: ='Double Cross #4'!L12 -> Enrollee Under Dairy GO for Chaves, Callie | CG12: ='King Dairy'!L12 -> Enrollee Under Dairy GO for King, Elsie | CH12: ='Vieira Livestock'!L12 -> Enrollee Under Dairy GO for Joe and Christine Vieira | CI12: ='AldenPeterson&SonsDairy Inc.'!L12 -> Enrollee Under Dairy Gen Order for Alden Peterson & Sons Dairy Inc. | CJ12: ='John Nunes Dairy #3'!L12 -> Enrollee Under Dairy Gen Order for Silva, Paulo - S & S 2 Dairy | CK12: ='Roestar Dairy'!L12 -> Enrollee Under Dairy GO for Roest, Arie | CL12: ='Luis M. Azevedo Dairy'!L12 -> Enrollee Under Dairy GO for Souza, Ray | CM12: ='Arlinda Holsteins'!L12 -> Enrollee Under Dairy GO for Vieira, Carl and Laurie - Arlinda Holsteins | CN12: ='Robert Gioletti & Sons Dairy'!L12 -> Enrollee Under Dairy GO for Robert Gioletti & Sons Dairy | CO12: ='Carl Vieira Dairy'!L12 -> Enrollee Under Dairy GO for Vieira, Carl and Laurie - Carl Vieira Dairy | CP12: ='John Brasil & Sons Dairy'!L12 -> Enrollee Under Dairy Gen Order for Brasil, John & Maria - John Brasil & Sons Dairy | CQ12: ='John Brasil Dairy #3'!L12 -> Enrollee Under Dairy GO for John Brasil, John Brasil Dairy #3 | CR12: ='KMA Dairy'!L12 -> Enrollee Under Dairy GO for Souza, Ray - KMA Dairy | CS12: ='Sallaberry Ranch'!L12 -> Enrollee Under Dairy GO for S & D Bylsma Dairy - Sallaberry Ranch | CT12: ='Alfred C Nunes Dairy'!L12 -> Enrollee Under Dairy GO for Nunes, Alfredo C & Celia | CU12: ='Jim Vieira & Son Dairy'!L12 -> Enrollee Under Dairy GO for GJC Dairy, Inc | CV12: ='Ehrlich Dairy'!L12 -> Enrollee Under Dairy GO for Schortzmann, Brittney - Ehrlich Dairy | CW12: ='D&A Brasil Facility'!B12 -> Enrollee Under Dairy GO for Brasil, Danny & Allison - D&A Brasil Dairy | CX12: ='Silva''s Holsteins'!B12 -> Enrollee Under Dairy GO for Silva, Manuel M & Filomena | CY12: ='G J Silva #3'!B12 -> #N/A | CZ12: ='Jim Vieira and Son Dairy #2'!L12 -> Enrollee Under Dairy GO for Lucio & Maria Machado | DA12: ='Johal Dairy'!L12 -> Enrollee Under Dairy GO for Johal, Gurdial & Surinder | DB12: ='A & G Azevedo Dairy'!L12 -> Enrollee Under Dairy Gen Order for Azevedo, Aldevino, A & G Azevedo Dairy | DC12: ='Gentle Breezes Dairy'!L12 -> Enrollee Under Dairy GO for Smith, Eric | DD12: ='Joe Sousa Jr Dairy'!L12 -> 13267 Letter 12/05/2011 for Joe Sousa Jr. Dairy | DE12: ='John Brasil Heifers'!L12 -> Enrollee Under Dairy GO for G.J. Silva Dairy - Reis Dairy | DF12: ='MHF Dairy'!L12 -> Enrollee Under Dairy GO for Machado, Isabel and Johnny | DG12: ='Brindiero&DanbomDairyFarms'!L12 -> Enrollee Under Dairy Gen Order for Brindiero, James & Danbom, Paul, Brindiero & Danbom Dairy Farms | DH12: ='A&C Machado Dairy #2'!L12 -> Enrollee Under Dairy GO for Lopes, Linda & Loren - A&C Machado Dairy #2 | DI12: ='J & J Toste DairyInc.'!L12 -> Enrollee Under Dairy GO for Toste, John | DJ12: ='Bar Vee DairyInc.'!L12 -> Enrollee Under Dairy GO for Crowell, Michael and Adam | DK12: ='Railside Jersey FarmsLLC'!L12 -> Enrollee Under Dairy GO for Singh, Sukhdev - Cal Farm House | DL12: ='Manuel Azevedo Dairy'!L12 -> Enrollee Under Dairy Gen Order for Azevedo, Manuel & Maria, Manuel Azevedo Dairy | DM12: ='Sousa Family Dairy'!L12 -> Enrollee Under Dairy GO for De Sousa, Armelin & Maria - Sousa Family Dairy | DN12: ='UC Davis Animal Science Dairy'!L12 -> Enrollee Under Dairy GO for UC Davis Animal Science Dairy | DO12: ='Garcia''s Registered Jerseys'!L12 -> Enrollee Under Dairy GO for Garcia, Jose | DP12: ='Lucio Corral Cattle'!L12 -> Enrollee Under Dairy GO for Lucio Corral Rodriguez | DQ12: ='Wickstrom Dairy Inc'!B12 -> Enrollee Under Dairy Gen Order for Brindeiro, Eleanor, Wickstrom Dairy Inc | DR12: ='Sam Kooistra Dairy'!L12 -> Enrollee Under Dairy GO for Kooistra, Sam - Sam Kooistra Dairy | DS12: ='Vitorino & Sons Dairy'!L12 -> Enrollee Under Dairy GO for Vitorino and Sons Dairy | DT12: ='Valley Cross Dairy'!L12 -> Enrollee Under Dairy Gen Order for Bacon, Doug, Valley Cross Dairy | DU12: ='John Brasil & Sons Dairy #2'!L12 -> Enrollee Under Dairy Gen Order for Brasil, John & Maria, John Brasil & Sons Dairy #2 | DV12: ='Pepper Dairy'!L12 -> Enrollee Under Dairy GO for Lemos, Frank S - Pepper Dairy | DW12: ='Clauss Dairy Farms'!L12 -> Enrollee Under Dairy GO for Clauss, Richard - Clauss Dairy Farms | DX12: ='Dairy Central Heifers'!L12 -> Enrollee Under Dairy GO for Borba, Bob - Dairy Central Heifers | DY12: ='Yosemite Jersey Dairy'!L12 -> Enrollee Under Dairy GO for River Rock Ranch, LLC | DZ12: ='Sunwest Jersey Dairy'!L12 -> Enrollee Under Dairy GO for Clauss, Richard - Sunwest Jersey Dairy | EA12: ='N & C Silveira Dairy'!L12 -> Enrollee Under Dairy GO for Silveira, Natalino | EB12: ='Nyman Brothers Dairy'!L12 -> Enrollee Under Dairy GO for Nyman, Delton - Nyman Brothers Dairy | EC12: ='Broder Farms'!L12 -> Enrollee Under Dairy GO for Wickstrom, Aaron Broder Farms Dairy - Broder Farms | ED12: ='Borba Dairy Farms'!L12 -> Enrollee Under Dairy Gen Order for Borba, Mike - Borba Dairy Farms | EE12: ='Charles Ahlem Ranch'!L12 -> Enrollee Under Dairy Gen Order for Ahlem, Mark - Charles Ahlem Ranch | EF12: ='James Ahlem Dairy'!L12 -> Enrollee Under Dairy Gen Order for Ahlem, Jim & Carol, James Ahlem Dairy | EG12: ='Nylund Dairy Farms'!L12 -> Enrollee Under Dairy GO for Nylund, Rodney V & Julie - Nylund Dairy Farms | EH12: ='Vierra Ranch Dairy'!L12 -> Enrollee Under Dairy GO for Swanson, Matt - Vierra Ranch Dairy | EI12: ='Joe O Rocha Dairy Inc.'!L12 -> Enrollee Under Dairy GO for Rocha, Joe - Joe O Rocha Dairy Inc | EJ12: ='Alves & Son Dairy'!L12 -> Enrollee Under Dairy Gen Order for Alves, Joe - Alves & Son Dairy | EK12: ='3A Teixeira Dairy'!L12 -> Enrollee Under Dairy GO for Fiorini, Victor - 3A Teixeira Dairy | EL12: ='Denizma_Bud Postma Dairy'!L12 -> Enrollee Under Dairy GO for Monache Meadows AG - Denizma Dairy / Bud Postma Dairy | EM12: ='Couco Creek Dairy'!L12 -> Enrollee Under Dairy GO for Machado, Tony - Couco Creek Dairy | EN12: ='Clausen Dairy'!L12 -> Enrollee Under Dairy GO for Schortzmann, Brittney - Clausen Dairy
... A32: Total Manure Generated | B32: ='A & M De Souza Dairy'!B32 -> 43759.88 | C32: ='Silva Dairy Farms #3A'!B32 -> 51757.74 | D32: ='Joe Borba Dairy Inc.'!B32 -> 506.25 | E32: ='Ken Van Foeken Dairy #2'!B32 -> 20562.29 | F32: ='Da Rosa Dairy'!B32 -> 11252.09 | G32: ='J_D Brasil Dairy'!#REF! -> #REF! | H32: ='River Rock Ranch LLC'!L32 -> no | I32: ='Double Cross #3'!L32 -> 0 | J32: ='Edward Nunes Dairy'!L32 -> no | K32: ='Gomes Dairy'!#REF! -> #REF! | L32: ='Roest Family Dairy'!L32 -> no | M32: ='Gil Tex Dairy'!L32 -> 0 | N32: ='GJ Silva'!L32 -> 0 | O32: ='Hilmar Holsteins Inc.'!L32 -> 0 | P32: ='Jordao Dairy'!L32 -> 0 | Q32: ='Cross Creek Dairy'!L32 -> 0 | R32: ='Double Cross #2'!L32 -> 0 | S32: ='LarryPetersonDairyFarms#2'!L32 -> 0 | T32: ='Fire_Lake Jerseys #2'!L32 -> 0 | U32: ='Lumar Dairy Farms'!L32 -> 0 | V32: ='CMA Livestock'!L32 -> 0 | W32: ='Fire Lakes Jerseys'!L32 -> 0 | X32: ='Rick Jones Farms'!L32 -> 0 | Y32: ='Silveira Holsteins'!L32 -> 0 | Z32: ='Diamond B Dairy'!L32 -> 0 | AA32: ='Azevedo Dairy'!L32 -> 0 | AB32: ='Valsigna Dairy'!L32 -> 0 | AC32: =WickstromJerseyFarmsInc.!L32 -> 0 | AD32: ='Diniz Dairy'!L32 -> 0 | AE32: ='Crane Dairy Inc.'!L32 -> 0 | AF32: ='GM Silva Dairies #2'!L32 -> 0 | AG32: ='Joe Oliveira Dairy'!#REF! -> #REF! | AH32: ='Vierra Dairy Farms #3'!L32 -> 0 | AI32: ='Nelson Dairy'!L32 -> 0 | AJ32: ='Mario&ChristinaNunesDairy'!L32 -> 0 | AK32: ='B & D Dairy'!L32 -> 0 | AL32: ='Silveira Dairy Inc.'!L32 -> 0 | AM32: ='Jade Jersey Dairy'!L32 -> 0 | AN32: ='Live Oak Dairy A'!L32 -> 0 | AO32: ='T & M Borba Dairy'!L32 -> 0 | AP32: ='Oslo Dairy'!L32 -> 0 | AQ32: ='Kronberg Facility'!L32 -> 0 | AR32: ='Ken Van Foeken Dairy'!L32 -> 0 | AS32: ='Amaral Dairy Farms'!L32 -> 0 | AT32: ='B_6 Dairy'!L32 -> 0 | AU32: ='6D Dores Dairy'!L32 -> 0 | AV32: ='Fanelli Dairy'!L32 -> 0 | AW32: ='Joao Sousa Dairy'!L32 -> 0 | AX32: ='Vierra Dairy Farms #2'!L32 -> 0 | AY32: ='Michael Brasil Dairy'!L32 -> 0 | AZ32: ='Anchor J Dairy'!L32 -> 0 | BA32: ='Oliveira Dairy'!L32 -> 0 | BB32: ='Souza Bros Dairy'!L32 -> 0 | BC32: ='Miguel Family Dairy'!L32 -> 0 | BD32: ='Dias Family Dairy'!L32 -> 0 | BE32: ='Empty was A_D Dairy'!L32 -> 0 | BF32: ='Michael Brasil Dairy #2'!L32 -> 0 | BG32: ='F & A Lemos Dairy'!L32 -> 0 | BH32: ='Alves & Son Dairy #2'!L32 -> 0 | BI32: ='Golf Link RanchesLLC'!L32 -> 0 | BJ32: ='Triple M Jerseys'!L32 -> 0 | BK32: ='Jose & Teresa Soares Dairy'!L32 -> 0 | BL32: ='MachadoGabriel&SonsDairy'!L32 -> 0 | BM32: ='Hawkins Ranch'!L32 -> 0 | BN32: ='Silva Dairy Farms #3B'!L32 -> 0 | BO32: =AhlemFarmsPartnership!L32 -> 0 | BP32: ='Vierra Dairy Farms #4'!L32 -> 0 | BQ32: ='CaliforniaDairyFarms LLC'!L32 -> 0 | BR32: ='Larry Peterson Dairy'!L32 -> 0 | BS32: ='Joe Egli&Sons Dairy'!L32 -> 0 | BT32: ='CMA Livestock #2'!L32 -> 0 | BU32: ='Valentine Dairy'!L32 -> 0 | BV32: ='CMC Jerseys LLC'!L32 -> 0 | BW32: ='Fanelli_Fanelli Brothers'!L32 -> 0 | BX32: ='Martins Bros Dairy'!L32 -> 0 | BY32: ='Gomes Heifer Ranch'!L32 -> 0 | BZ32: ='Ed Hirdes Dairy'!B32 -> 0 | CA32: ='Dematos Dairy'!L32 -> 0 | CB32: ='Carlos Estacio&Sons Dairy'!L32 -> 0 | CC32: ='Live Oak Dairy G'!L32 -> 0 | CD32: ='Verissimo Facility'!L32 -> 0 | CE32: ='Double Cross Dairy'!L32 -> 0 | CF32: ='Double Cross #4'!L32 -> 0 | CG32: ='King Dairy'!L32 -> 0 | CH32: ='Vieira Livestock'!L32 -> 0 | CI32: ='AldenPeterson&SonsDairy Inc.'!L32 -> 0 | CJ32: ='John Nunes Dairy #3'!L32 -> 0 | CK32: ='Roestar Dairy'!L32 -> 0 | CL32: ='Luis M. Azevedo Dairy'!L32 -> 0 | CM32: ='Arlinda Holsteins'!L32 -> 0 | CN32: ='Robert Gioletti & Sons Dairy'!L32 -> 0 | CO32: ='Carl Vieira Dairy'!L32 -> 0 | CP32: ='John Brasil & Sons Dairy'!L32 -> 0 | CQ32: ='John Brasil Dairy #3'!L32 -> 0 | CR32: ='KMA Dairy'!L32 -> 0 | CS32: ='Sallaberry Ranch'!L32 -> 0 | CT32: ='Alfred C Nunes Dairy'!L32 -> 0 | CU32: ='Jim Vieira & Son Dairy'!L32 -> 0 | CV32: ='Ehrlich Dairy'!L32 -> 0 | CW32: ='D&A Brasil Facility'!B32 -> 0 | CX32: ='Silva''s Holsteins'!B32 -> 34621.54 | CY32: ='G J Silva #3'!B32 -> 0 | CZ32: ='Jim Vieira and Son Dairy #2'!L32 -> 0 | DA32: ='Johal Dairy'!L32 -> 0 | DB32: ='A & G Azevedo Dairy'!L32 -> 0 | DC32: ='Gentle Breezes Dairy'!L32 -> 0 | DD32: ='Joe Sousa Jr Dairy'!L32 -> 0 | DE32: ='John Brasil Heifers'!L32 -> 0 | DF32: ='MHF Dairy'!L32 -> 0 | DG32: ='Brindiero&DanbomDairyFarms'!L32 -> 0 | DH32: ='A&C Machado Dairy #2'!L32 -> 0 | DI32: ='J & J Toste DairyInc.'!L32 -> 0 | DJ32: ='Bar Vee DairyInc.'!L32 -> 0 | DK32: ='Railside Jersey FarmsLLC'!L32 -> 0 | DL32: ='Manuel Azevedo Dairy'!L32 -> 0 | DM32: ='Sousa Family Dairy'!L32 -> 0 | DN32: ='UC Davis Animal Science Dairy'!L32 -> 0 | DO32: ='Garcia''s Registered Jerseys'!L32 -> 0 | DP32: ='Lucio Corral Cattle'!L32 -> 0 | DQ32: ='Wickstrom Dairy Inc'!B32 -> 0 | DR32: ='Sam Kooistra Dairy'!L32 -> 0 | DS32: ='Vitorino & Sons Dairy'!L32 -> 0 | DT32: ='Valley Cross Dairy'!L32 -> 0 | DU32: ='John Brasil & Sons Dairy #2'!L32 -> 0 | DV32: ='Pepper Dairy'!L32 -> 0 | DW32: ='Clauss Dairy Farms'!L32 -> 0 | DX32: ='Dairy Central Heifers'!L32 -> 0 | DY32: ='Yosemite Jersey Dairy'!L32 -> 0 | DZ32: ='Sunwest Jersey Dairy'!L32 -> 0 | EA32: ='N & C Silveira Dairy'!L32 -> 0 | EB32: ='Nyman Brothers Dairy'!L32 -> 0 | EC32: ='Broder Farms'!L32 -> 0 | ED32: ='Borba Dairy Farms'!L32 -> 0 | EE32: ='Charles Ahlem Ranch'!L32 -> 0 | EF32: ='James Ahlem Dairy'!L32 -> 0 | EG32: ='Nylund Dairy Farms'!L32 -> 0 | EH32: ='Vierra Ranch Dairy'!L32 -> 0 | EI32: ='Joe O Rocha Dairy Inc.'!L32 -> 0 | EJ32: ='Alves & Son Dairy'!L32 -> 0 | EK32: ='3A Teixeira Dairy'!L32 -> 0 | EL32: ='Denizma_Bud Postma Dairy'!L32 -> 0 | EM32: ='Couco Creek Dairy'!L32 -> 0 | EN32: ='Clausen Dairy'!L32 -> 0
A33: EXPANSION | B33: ='A & M De Souza Dairy'!B33 -> 0 | C33: ='Silva Dairy Farms #3A'!B33 -> 0 | D33: ='Joe Borba Dairy Inc.'!B33 -> 0 | E33: ='Ken Van Foeken Dairy #2'!B33 -> 0 | F33: ='Da Rosa Dairy'!B33 -> 0 | G33: ='J_D Brasil Dairy'!#REF! -> #REF! | H33: ='River Rock Ranch LLC'!L31 -> 0 | I33: ='Double Cross #3'!L31 -> 0 | J33: ='Edward Nunes Dairy'!L31 -> 0 | K33: ='Gomes Dairy'!#REF! -> #REF! | L33: ='Roest Family Dairy'!L31 -> 0 | M33: ='Gil Tex Dairy'!L31 -> 0 | N33: ='GJ Silva'!L31 -> 0 | O33: ='Hilmar Holsteins Inc.'!L31 -> 0 | P33: ='Jordao Dairy'!L31 -> 0 | Q33: ='Cross Creek Dairy'!L31 -> 0 | R33: ='Double Cross #2'!L31 -> 0 | S33: ='LarryPetersonDairyFarms#2'!L31 -> 0 | T33: ='Fire_Lake Jerseys #2'!L31 -> 0 | U33: ='Lumar Dairy Farms'!L31 -> 0 | V33: ='CMA Livestock'!L31 -> 0 | W33: ='Fire Lakes Jerseys'!L31 -> 0 | X33: ='Rick Jones Farms'!L31 -> 0 | Y33: ='Silveira Holsteins'!L31 -> 0 | Z33: ='Diamond B Dairy'!L31 -> 0 | AA33: ='Azevedo Dairy'!L31 -> 0 | AB33: ='Valsigna Dairy'!L31 -> 0 | AC33: =WickstromJerseyFarmsInc.!L31 -> 0 | AD33: ='Diniz Dairy'!L31 -> 0 | AE33: ='Crane Dairy Inc.'!L31 -> 0 | AF33: ='GM Silva Dairies #2'!L31 -> 0 | AG33: ='Joe Oliveira Dairy'!#REF! -> #REF! | AH33: ='Vierra Dairy Farms #3'!L31 -> 0 | AI33: ='Nelson Dairy'!L31 -> 0 | AJ33: ='Mario&ChristinaNunesDairy'!L31 -> 0 | AK33: ='B & D Dairy'!L31 -> 0 | AL33: ='Silveira Dairy Inc.'!L31 -> 0 | AM33: ='Jade Jersey Dairy'!L31 -> 0 | AN33: ='Live Oak Dairy A'!L31 -> 0 | AO33: ='T & M Borba Dairy'!L31 -> 0 | AP33: ='Oslo Dairy'!L31 -> 0 | AQ33: ='Kronberg Facility'!L31 -> 0 | AR33: ='Ken Van Foeken Dairy'!L31 -> 0 | AS33: ='Amaral Dairy Farms'!L31 -> 0 | AT33: ='B_6 Dairy'!L31 -> 0 | AU33: ='6D Dores Dairy'!L31 -> 0 | AV33: ='Fanelli Dairy'!L31 -> 0 | AW33: ='Joao Sousa Dairy'!L31 -> 0 | AX33: ='Vierra Dairy Farms #2'!L31 -> 0 | AY33: ='Michael Brasil Dairy'!L31 -> 0 | AZ33: ='Anchor J Dairy'!L31 -> 0 | BA33: ='Oliveira Dairy'!L31 -> 0 | BB33: ='Souza Bros Dairy'!L31 -> 0 | BC33: ='Miguel Family Dairy'!L31 -> 0 | BD33: ='Dias Family Dairy'!L31 -> 0 | BE33: ='Empty was A_D Dairy'!L31 -> 0 | BF33: ='Michael Brasil Dairy #2'!L31 -> 0 | BG33: ='F & A Lemos Dairy'!L31 -> 0 | BH33: ='Alves & Son Dairy #2'!L31 -> 0 | BI33: ='Golf Link RanchesLLC'!L31 -> 0 | BJ33: ='Triple M Jerseys'!L31 -> 0 | BK33: ='Jose & Teresa Soares Dairy'!L31 -> 0 | BL33: ='MachadoGabriel&SonsDairy'!L31 -> 0 | BM33: ='Hawkins Ranch'!L31 -> 0 | BN33: ='Silva Dairy Farms #3B'!L31 -> 0 | BO33: =AhlemFarmsPartnership!L31 -> 0 | BP33: ='Vierra Dairy Farms #4'!L31 -> 0 | BQ33: ='CaliforniaDairyFarms LLC'!L31 -> 0 | BR33: ='Larry Peterson Dairy'!L31 -> 0 | BS33: ='Joe Egli&Sons Dairy'!L31 -> 0 | BT33: ='CMA Livestock #2'!L31 -> 0 | BU33: ='Valentine Dairy'!L31 -> 0 | BV33: ='CMC Jerseys LLC'!L31 -> 0 | BW33: ='Fanelli_Fanelli Brothers'!L31 -> 0 | BX33: ='Martins Bros Dairy'!L31 -> 0 | BY33: ='Gomes Heifer Ranch'!L31 -> 0 | BZ33: ='Ed Hirdes Dairy'!B33 -> 0 | CA33: ='Dematos Dairy'!L31 -> 0 | CB33: ='Carlos Estacio&Sons Dairy'!L31 -> 0 | CC33: ='Live Oak Dairy G'!L31 -> 0 | CD33: ='Verissimo Facility'!L31 -> 0 | CE33: ='Double Cross Dairy'!L31 -> 0 | CF33: ='Double Cross #4'!L31 -> 0 | CG33: ='King Dairy'!L31 -> 0 | CH33: ='Vieira Livestock'!L31 -> 0 | CI33: ='AldenPeterson&SonsDairy Inc.'!L31 -> 0 | CJ33: ='John Nunes Dairy #3'!L31 -> 0 | CK33: ='Roestar Dairy'!L31 -> 0 | CL33: ='Luis M. Azevedo Dairy'!L31 -> 0 | CM33: ='Arlinda Holsteins'!L31 -> 0 | CN33: ='Robert Gioletti & Sons Dairy'!L31 -> 0 | CO33: ='Carl Vieira Dairy'!L31 -> 0 | CP33: ='John Brasil & Sons Dairy'!L31 -> 0 | CQ33: ='John Brasil Dairy #3'!L31 -> 0 | CR33: ='KMA Dairy'!L31 -> 0 | CS33: ='Sallaberry Ranch'!L31 -> 0 | CT33: ='Alfred C Nunes Dairy'!L31 -> 0 | CU33: ='Jim Vieira & Son Dairy'!L31 -> 0 | CV33: ='Ehrlich Dairy'!L31 -> 0 | CW33: ='D&A Brasil Facility'!B33 -> 0 | CX33: ='Silva''s Holsteins'!B33 -> 0 | CY33: ='G J Silva #3'!B33 -> 0 | CZ33: ='Jim Vieira and Son Dairy #2'!L31 -> 0 | DA33: ='Johal Dairy'!L31 -> 0 | DB33: ='A & G Azevedo Dairy'!L31 -> 0 | DC33: ='Gentle Breezes Dairy'!L31 -> 0 | DD33: ='Joe Sousa Jr Dairy'!L31 -> 0 | DE33: ='John Brasil Heifers'!L31 -> 0 | DF33: ='MHF Dairy'!L31 -> 0 | DG33: ='Brindiero&DanbomDairyFarms'!L31 -> 0 | DH33: ='A&C Machado Dairy #2'!L31 -> 0 | DI33: ='J & J Toste DairyInc.'!L31 -> 0 | DJ33: ='Bar Vee DairyInc.'!L31 -> 0 | DK33: ='Railside Jersey FarmsLLC'!L31 -> 0 | DL33: ='Manuel Azevedo Dairy'!L31 -> 0 | DM33: ='Sousa Family Dairy'!L31 -> 0 | DN33: ='UC Davis Animal Science Dairy'!L31 -> 0 | DO33: ='Garcia''s Registered Jerseys'!L31 -> 0 | DP33: ='Lucio Corral Cattle'!L31 -> 0 | DQ33: ='Wickstrom Dairy Inc'!B33 -> 0 | DR33: ='Sam Kooistra Dairy'!L31 -> 0 | DS33: ='Vitorino & Sons Dairy'!L31 -> 0 | DT33: ='Valley Cross Dairy'!L31 -> 0 | DU33: ='John Brasil & Sons Dairy #2'!L31 -> 0 | DV33: ='Pepper Dairy'!L31 -> 0 | DW33: ='Clauss Dairy Farms'!L31 -> 0 | DX33: ='Dairy Central Heifers'!L31 -> 0 | DY33: ='Yosemite Jersey Dairy'!L31 -> 0 | DZ33: ='Sunwest Jersey Dairy'!L31 -> 0 | EA33: ='N & C Silveira Dairy'!L31 -> 0 | EB33: ='Nyman Brothers Dairy'!L31 -> 0 | EC33: ='Broder Farms'!L31 -> 0 | ED33: ='Borba Dairy Farms'!L31 -> 0 | EE33: ='Charles Ahlem Ranch'!L31 -> 0 | EF33: ='James Ahlem Dairy'!L31 -> 0 | EG33: ='Nylund Dairy Farms'!L31 -> 0 | EH33: ='Vierra Ranch Dairy'!L31 -> 0 | EI33: ='Joe O Rocha Dairy Inc.'!L31 -> 0 | EJ33: ='Alves & Son Dairy'!L31 -> 0 | EK33: ='3A Teixeira Dairy'!L31 -> 0 | EL33: ='Denizma_Bud Postma Dairy'!L31 -> 0 | EM33: ='Couco Creek Dairy'!L31 -> 0 | EN33: ='Clausen Dairy'!L31 -> 0
A34: WW EXPORTS | B34: ='A & M De Souza Dairy'!B34 -> 0 | C34: ='Silva Dairy Farms #3A'!B34 -> 0 | D34: ='Joe Borba Dairy Inc.'!B34 -> 0 | E34: ='Ken Van Foeken Dairy #2'!B34 -> 0 | F34: ='Da Rosa Dairy'!B34 -> 0 | G34: ='J_D Brasil Dairy'!#REF! -> #REF! | H34: ='River Rock Ranch LLC'!L32 -> no | I34: ='Double Cross #3'!L32 -> 0 | J34: ='Edward Nunes Dairy'!L32 -> no | K34: ='Gomes Dairy'!#REF! -> #REF! | L34: ='Roest Family Dairy'!L32 -> no | M34: ='Gil Tex Dairy'!L32 -> 0 | N34: ='GJ Silva'!L32 -> 0 | O34: ='Hilmar Holsteins Inc.'!L32 -> 0 | P34: ='Jordao Dairy'!L32 -> 0 | Q34: ='Cross Creek Dairy'!L32 -> 0 | R34: ='Double Cross #2'!L32 -> 0 | S34: ='LarryPetersonDairyFarms#2'!L32 -> 0 | T34: ='Fire_Lake Jerseys #2'!L32 -> 0 | U34: ='Lumar Dairy Farms'!L32 -> 0 | V34: ='CMA Livestock'!L32 -> 0 | W34: ='Fire Lakes Jerseys'!L32 -> 0 | X34: ='Rick Jones Farms'!L32 -> 0 | Y34: ='Silveira Holsteins'!L32 -> 0 | Z34: ='Diamond B Dairy'!L32 -> 0 | AA34: ='Azevedo Dairy'!L32 -> 0 | AB34: ='Valsigna Dairy'!L32 -> 0 | AC34: =WickstromJerseyFarmsInc.!L32 -> 0 | AD34: ='Diniz Dairy'!L32 -> 0 | AE34: ='Crane Dairy Inc.'!L32 -> 0 | AF34: ='GM Silva Dairies #2'!L32 -> 0 | AG34: ='Joe Oliveira Dairy'!#REF! -> #REF! | AH34: ='Vierra Dairy Farms #3'!L32 -> 0 | AI34: ='Nelson Dairy'!L32 -> 0 | AJ34: ='Mario&ChristinaNunesDairy'!L32 -> 0 | AK34: ='B & D Dairy'!L32 -> 0 | AL34: ='Silveira Dairy Inc.'!L32 -> 0 | AM34: ='Jade Jersey Dairy'!L32 -> 0 | AN34: ='Live Oak Dairy A'!L32 -> 0 | AO34: ='T & M Borba Dairy'!L32 -> 0 | AP34: ='Oslo Dairy'!L32 -> 0 | AQ34: ='Kronberg Facility'!L32 -> 0 | AR34: ='Ken Van Foeken Dairy'!L32 -> 0 | AS34: ='Amaral Dairy Farms'!L32 -> 0 | AT34: ='B_6 Dairy'!L32 -> 0 | AU34: ='6D Dores Dairy'!L32 -> 0 | AV34: ='Fanelli Dairy'!L32 -> 0 | AW34: ='Joao Sousa Dairy'!L32 -> 0 | AX34: ='Vierra Dairy Farms #2'!L32 -> 0 | AY34: ='Michael Brasil Dairy'!L32 -> 0 | AZ34: ='Anchor J Dairy'!L32 -> 0 | BA34: ='Oliveira Dairy'!L32 -> 0 | BB34: ='Souza Bros Dairy'!L32 -> 0 | BC34: ='Miguel Family Dairy'!L32 -> 0 | BD34: ='Dias Family Dairy'!L32 -> 0 | BE34: ='Empty was A_D Dairy'!L32 -> 0 | BF34: ='Michael Brasil Dairy #2'!L32 -> 0 | BG34: ='F & A Lemos Dairy'!L32 -> 0 | BH34: ='Alves & Son Dairy #2'!L32 -> 0 | BI34: ='Golf Link RanchesLLC'!L32 -> 0 | BJ34: ='Triple M Jerseys'!L32 -> 0 | BK34: ='Jose & Teresa Soares Dairy'!L32 -> 0 | BL34: ='MachadoGabriel&SonsDairy'!L32 -> 0 | BM34: ='Hawkins Ranch'!L32 -> 0 | BN34: ='Silva Dairy Farms #3B'!L32 -> 0 | BO34: =AhlemFarmsPartnership!L32 -> 0 | BP34: ='Vierra Dairy Farms #4'!L32 -> 0 | BQ34: ='CaliforniaDairyFarms LLC'!L32 -> 0 | BR34: ='Larry Peterson Dairy'!L32 -> 0 | BS34: ='Joe Egli&Sons Dairy'!L32 -> 0 | BT34: ='CMA Livestock #2'!L32 -> 0 | BU34: ='Valentine Dairy'!L32 -> 0 | BV34: ='CMC Jerseys LLC'!L32 -> 0 | BW34: ='Fanelli_Fanelli Brothers'!L32 -> 0 | BX34: ='Martins Bros Dairy'!L32 -> 0 | BY34: ='Gomes Heifer Ranch'!L32 -> 0 | BZ34: ='Ed Hirdes Dairy'!B34 -> 0 | CA34: ='Dematos Dairy'!L32 -> 0 | CB34: ='Carlos Estacio&Sons Dairy'!L32 -> 0 | CC34: ='Live Oak Dairy G'!L32 -> 0 | CD34: ='Verissimo Facility'!L32 -> 0 | CE34: ='Double Cross Dairy'!L32 -> 0 | CF34: ='Double Cross #4'!L32 -> 0 | CG34: ='King Dairy'!L32 -> 0 | CH34: ='Vieira Livestock'!L32 -> 0 | CI34: ='AldenPeterson&SonsDairy Inc.'!L32 -> 0 | CJ34: ='John Nunes Dairy #3'!L32 -> 0 | CK34: ='Roestar Dairy'!L32 -> 0 | CL34: ='Luis M. Azevedo Dairy'!L32 -> 0 | CM34: ='Arlinda Holsteins'!L32 -> 0 | CN34: ='Robert Gioletti & Sons Dairy'!L32 -> 0 | CO34: ='Carl Vieira Dairy'!L32 -> 0 | CP34: ='John Brasil & Sons Dairy'!L32 -> 0 | CQ34: ='John Brasil Dairy #3'!L32 -> 0 | CR34: ='KMA Dairy'!L32 -> 0 | CS34: ='Sallaberry Ranch'!L32 -> 0 | CT34: ='Alfred C Nunes Dairy'!L32 -> 0 | CU34: ='Jim Vieira & Son Dairy'!L32 -> 0 | CV34: ='Ehrlich Dairy'!L32 -> 0 | CW34: ='D&A Brasil Facility'!B34 -> 0 | CX34: ='Silva''s Holsteins'!B34 -> 0 | CY34: ='G J Silva #3'!B34 -> 0 | CZ34: ='Jim Vieira and Son Dairy #2'!L32 -> 0 | DA34: ='Johal Dairy'!L32 -> 0 | DB34: ='A & G Azevedo Dairy'!L32 -> 0 | DC34: ='Gentle Breezes Dairy'!L32 -> 0 | DD34: ='Joe Sousa Jr Dairy'!L32 -> 0 | DE34: ='John Brasil Heifers'!L32 -> 0 | DF34: ='MHF Dairy'!L32 -> 0 | DG34: ='Brindiero&DanbomDairyFarms'!L32 -> 0 | DH34: ='A&C Machado Dairy #2'!L32 -> 0 | DI34: ='J & J Toste DairyInc.'!L32 -> 0 | DJ34: ='Bar Vee DairyInc.'!L32 -> 0 | DK34: ='Railside Jersey FarmsLLC'!L32 -> 0 | DL34: ='Manuel Azevedo Dairy'!L32 -> 0 | DM34: ='Sousa Family Dairy'!L32 -> 0 | DN34: ='UC Davis Animal Science Dairy'!L32 -> 0 | DO34: ='Garcia''s Registered Jerseys'!L32 -> 0 | DP34: ='Lucio Corral Cattle'!L32 -> 0 | DQ34: ='Wickstrom Dairy Inc'!B34 -> 0 | DR34: ='Sam Kooistra Dairy'!L32 -> 0 | DS34: ='Vitorino & Sons Dairy'!L32 -> 0 | DT34: ='Valley Cross Dairy'!L32 -> 0 | DU34: ='John Brasil & Sons Dairy #2'!L32 -> 0 | DV34: ='Pepper Dairy'!L32 -> 0 | DW34: ='Clauss Dairy Farms'!L32 -> 0 | DX34: ='Dairy Central Heifers'!L32 -> 0 | DY34: ='Yosemite Jersey Dairy'!L32 -> 0 | DZ34: ='Sunwest Jersey Dairy'!L32 -> 0 | EA34: ='N & C Silveira Dairy'!L32 -> 0 | EB34: ='Nyman Brothers Dairy'!L32 -> 0 | EC34: ='Broder Farms'!L32 -> 0 | ED34: ='Borba Dairy Farms'!L32 -> 0 | EE34: ='Charles Ahlem Ranch'!L32 -> 0 | EF34: ='James Ahlem Dairy'!L32 -> 0 | EG34: ='Nylund Dairy Farms'!L32 -> 0 | EH34: ='Vierra Ranch Dairy'!L32 -> 0 | EI34: ='Joe O Rocha Dairy Inc.'!L32 -> 0 | EJ34: ='Alves & Son Dairy'!L32 -> 0 | EK34: ='3A Teixeira Dairy'!L32 -> 0 | EL34: ='Denizma_Bud Postma Dairy'!L32 -> 0 | EM34: ='Couco Creek Dairy'!L32 -> 0 | EN34: ='Clausen Dairy'!L32 -> 0
A35: MANURE EXPORTS | B35: ='A & M De Souza Dairy'!B35 -> 0 | C35: ='Silva Dairy Farms #3A'!B35 -> 0 | D35: ='Joe Borba Dairy Inc.'!B35 -> 0 | E35: ='Ken Van Foeken Dairy #2'!B35 -> 0 | F35: ='Da Rosa Dairy'!B35 -> 0 | G35: ='J_D Brasil Dairy'!#REF! -> #REF! | H35: ='River Rock Ranch LLC'!L33 -> yes | I35: ='Double Cross #3'!L33 -> yes | J35: ='Edward Nunes Dairy'!L33 -> yes | K35: ='Gomes Dairy'!#REF! -> #REF! | L35: ='Roest Family Dairy'!L33 -> yes | M35: ='Gil Tex Dairy'!L33 -> 0 | N35: ='GJ Silva'!L33 -> 0 | O35: ='Hilmar Holsteins Inc.'!L33 -> 0 | P35: ='Jordao Dairy'!L33 -> 0 | Q35: ='Cross Creek Dairy'!L33 -> 0 | R35: ='Double Cross #2'!L33 -> 0 | S35: ='LarryPetersonDairyFarms#2'!L33 -> 0 | T35: ='Fire_Lake Jerseys #2'!L33 -> 0 | U35: ='Lumar Dairy Farms'!L33 -> 0 | V35: ='CMA Livestock'!L33 -> 0 | W35: ='Fire Lakes Jerseys'!L33 -> 0 | X35: ='Rick Jones Farms'!L33 -> 0 | Y35: ='Silveira Holsteins'!L33 -> 0 | Z35: ='Diamond B Dairy'!L33 -> 0 | AA35: ='Azevedo Dairy'!L33 -> 0 | AB35: ='Valsigna Dairy'!L33 -> 0 | AC35: =WickstromJerseyFarmsInc.!L33 -> 0 | AD35: ='Diniz Dairy'!L33 -> 0 | AE35: ='Crane Dairy Inc.'!L33 -> 0 | AF35: ='GM Silva Dairies #2'!L33 -> 0 | AG35: ='Joe Oliveira Dairy'!#REF! -> #REF! | AH35: ='Vierra Dairy Farms #3'!L33 -> 0 | AI35: ='Nelson Dairy'!L33 -> 0 | AJ35: ='Mario&ChristinaNunesDairy'!L33 -> 0 | AK35: ='B & D Dairy'!L33 -> 0 | AL35: ='Silveira Dairy Inc.'!L33 -> 0 | AM35: ='Jade Jersey Dairy'!L33 -> 0 | AN35: ='Live Oak Dairy A'!L33 -> 0 | AO35: ='T & M Borba Dairy'!L33 -> 0 | AP35: ='Oslo Dairy'!L33 -> 0 | AQ35: ='Kronberg Facility'!L33 -> 0 | AR35: ='Ken Van Foeken Dairy'!L33 -> 0 | AS35: ='Amaral Dairy Farms'!L33 -> 0 | AT35: ='B_6 Dairy'!L33 -> 0 | AU35: ='6D Dores Dairy'!L33 -> 0 | AV35: ='Fanelli Dairy'!L33 -> 0 | AW35: ='Joao Sousa Dairy'!L33 -> 0 | AX35: ='Vierra Dairy Farms #2'!L33 -> 0 | AY35: ='Michael Brasil Dairy'!L33 -> 0 | AZ35: ='Anchor J Dairy'!L33 -> 0 | BA35: ='Oliveira Dairy'!L33 -> 0 | BB35: ='Souza Bros Dairy'!L33 -> 0 | BC35: ='Miguel Family Dairy'!L33 -> 0 | BD35: ='Dias Family Dairy'!L33 -> 0 | BE35: ='Empty was A_D Dairy'!L33 -> 0 | BF35: ='Michael Brasil Dairy #2'!L33 -> 0 | BG35: ='F & A Lemos Dairy'!L33 -> 0 | BH35: ='Alves & Son Dairy #2'!L33 -> 0 | BI35: ='Golf Link RanchesLLC'!L33 -> 0 | BJ35: ='Triple M Jerseys'!L33 -> 0 | BK35: ='Jose & Teresa Soares Dairy'!L33 -> 0 | BL35: ='MachadoGabriel&SonsDairy'!L33 -> 0 | BM35: ='Hawkins Ranch'!L33 -> 0 | BN35: ='Silva Dairy Farms #3B'!L33 -> 0 | BO35: =AhlemFarmsPartnership!L33 -> 0 | BP35: ='Vierra Dairy Farms #4'!L33 -> 0 | BQ35: ='CaliforniaDairyFarms LLC'!L33 -> 0 | BR35: ='Larry Peterson Dairy'!L33 -> 0 | BS35: ='Joe Egli&Sons Dairy'!L33 -> 0 | BT35: ='CMA Livestock #2'!L33 -> 0 | BU35: ='Valentine Dairy'!L33 -> 0 | BV35: ='CMC Jerseys LLC'!L33 -> 0 | BW35: ='Fanelli_Fanelli Brothers'!L33 -> 0 | BX35: ='Martins Bros Dairy'!L33 -> 0 | BY35: ='Gomes Heifer Ranch'!L33 -> 0 | BZ35: ='Ed Hirdes Dairy'!B35 -> 0 | CA35: ='Dematos Dairy'!L33 -> 0 | CB35: ='Carlos Estacio&Sons Dairy'!L33 -> 0 | CC35: ='Live Oak Dairy G'!L33 -> 0 | CD35: ='Verissimo Facility'!L33 -> 0 | CE35: ='Double Cross Dairy'!L33 -> 0 | CF35: ='Double Cross #4'!L33 -> 0 | CG35: ='King Dairy'!L33 -> 0 | CH35: ='Vieira Livestock'!L33 -> 0 | CI35: ='AldenPeterson&SonsDairy Inc.'!L33 -> 0 | CJ35: ='John Nunes Dairy #3'!L33 -> 0 | CK35: ='Roestar Dairy'!L33 -> 0 | CL35: ='Luis M. Azevedo Dairy'!L33 -> 0 | CM35: ='Arlinda Holsteins'!L33 -> 0 | CN35: ='Robert Gioletti & Sons Dairy'!L33 -> 0 | CO35: ='Carl Vieira Dairy'!L33 -> 0 | CP35: ='John Brasil & Sons Dairy'!L33 -> 0 | CQ35: ='John Brasil Dairy #3'!L33 -> 0 | CR35: ='KMA Dairy'!L33 -> 0 | CS35: ='Sallaberry Ranch'!L33 -> 0 | CT35: ='Alfred C Nunes Dairy'!L33 -> 0 | CU35: ='Jim Vieira & Son Dairy'!L33 -> 0 | CV35: ='Ehrlich Dairy'!L33 -> 0 | CW35: ='D&A Brasil Facility'!B35 -> 0 | CX35: ='Silva''s Holsteins'!B35 -> 0 | CY35: ='G J Silva #3'!B35 -> 0 | CZ35: ='Jim Vieira and Son Dairy #2'!L33 -> 0 | DA35: ='Johal Dairy'!L33 -> 0 | DB35: ='A & G Azevedo Dairy'!L33 -> 0 | DC35: ='Gentle Breezes Dairy'!L33 -> 0 | DD35: ='Joe Sousa Jr Dairy'!L33 -> 0 | DE35: ='John Brasil Heifers'!L33 -> 0 | DF35: ='MHF Dairy'!L33 -> 0 | DG35: ='Brindiero&DanbomDairyFarms'!L33 -> 0 | DH35: ='A&C Machado Dairy #2'!L33 -> 0 | DI35: ='J & J Toste DairyInc.'!L33 -> 0 | DJ35: ='Bar Vee DairyInc.'!L33 -> 0 | DK35: ='Railside Jersey FarmsLLC'!L33 -> 0 | DL35: ='Manuel Azevedo Dairy'!L33 -> 0 | DM35: ='Sousa Family Dairy'!L33 -> 0 | DN35: ='UC Davis Animal Science Dairy'!L33 -> 0 | DO35: ='Garcia''s Registered Jerseys'!L33 -> 0 | DP35: ='Lucio Corral Cattle'!L33 -> 0 | DQ35: ='Wickstrom Dairy Inc'!B35 -> 0 | DR35: ='Sam Kooistra Dairy'!L33 -> 0 | DS35: ='Vitorino & Sons Dairy'!L33 -> 0 | DT35: ='Valley Cross Dairy'!L33 -> 0 | DU35: ='John Brasil & Sons Dairy #2'!L33 -> 0 | DV35: ='Pepper Dairy'!L33 -> 0 | DW35: ='Clauss Dairy Farms'!L33 -> 0 | DX35: ='Dairy Central Heifers'!L33 -> 0 | DY35: ='Yosemite Jersey Dairy'!L33 -> 0 | DZ35: ='Sunwest Jersey Dairy'!L33 -> 0 | EA35: ='N & C Silveira Dairy'!L33 -> 0 | EB35: ='Nyman Brothers Dairy'!L33 -> 0 | EC35: ='Broder Farms'!L33 -> 0 | ED35: ='Borba Dairy Farms'!L33 -> 0 | EE35: ='Charles Ahlem Ranch'!L33 -> 0 | EF35: ='James Ahlem Dairy'!L33 -> 0 | EG35: ='Nylund Dairy Farms'!L33 -> 0 | EH35: ='Vierra Ranch Dairy'!L33 -> 0 | EI35: ='Joe O Rocha Dairy Inc.'!L33 -> 0 | EJ35: ='Alves & Son Dairy'!L33 -> 0 | EK35: ='3A Teixeira Dairy'!L33 -> 0 | EL35: ='Denizma_Bud Postma Dairy'!L33 -> 0 | EM35: ='Couco Creek Dairy'!L33 -> 0 | EN35: ='Clausen Dairy'!L33 -> 0
A36: IMPORTS | B36: ='A & M De Souza Dairy'!B36 -> 0 | C36: ='Silva Dairy Farms #3A'!B36 -> 0 | D36: ='Joe Borba Dairy Inc.'!B36 -> 0 | E36: ='Ken Van Foeken Dairy #2'!B36 -> 0 | F36: ='Da Rosa Dairy'!B36 -> 0 | G36: ='J_D Brasil Dairy'!#REF! -> #REF! | H36: ='River Rock Ranch LLC'!L34 -> no | I36: ='Double Cross #3'!L34 -> no | J36: ='Edward Nunes Dairy'!L34 -> no | K36: ='Gomes Dairy'!#REF! -> #REF! | L36: ='Roest Family Dairy'!L34 -> no | M36: ='Gil Tex Dairy'!L34 -> 0 | N36: ='GJ Silva'!L34 -> 0 | O36: ='Hilmar Holsteins Inc.'!L34 -> 0 | P36: ='Jordao Dairy'!L34 -> 0 | Q36: ='Cross Creek Dairy'!L34 -> 0 | R36: ='Double Cross #2'!L34 -> 0 | S36: ='LarryPetersonDairyFarms#2'!L34 -> 0 | T36: ='Fire_Lake Jerseys #2'!L34 -> 0 | U36: ='Lumar Dairy Farms'!L34 -> 0 | V36: ='CMA Livestock'!L34 -> 0 | W36: ='Fire Lakes Jerseys'!L34 -> 0 | X36: ='Rick Jones Farms'!L34 -> 0 | Y36: ='Silveira Holsteins'!L34 -> 0 | Z36: ='Diamond B Dairy'!L34 -> 0 | AA36: ='Azevedo Dairy'!L34 -> 0 | AB36: ='Valsigna Dairy'!L34 -> 0 | AC36: =WickstromJerseyFarmsInc.!L34 -> 0 | AD36: ='Diniz Dairy'!L34 -> 0 | AE36: ='Crane Dairy Inc.'!L34 -> 0 | AF36: ='GM Silva Dairies #2'!L34 -> 0 | AG36: ='Joe Oliveira Dairy'!#REF! -> #REF! | AH36: ='Vierra Dairy Farms #3'!L34 -> 0 | AI36: ='Nelson Dairy'!L34 -> 0 | AJ36: ='Mario&ChristinaNunesDairy'!L34 -> 0 | AK36: ='B & D Dairy'!L34 -> 0 | AL36: ='Silveira Dairy Inc.'!L34 -> 0 | AM36: ='Jade Jersey Dairy'!L34 -> 0 | AN36: ='Live Oak Dairy A'!L34 -> 0 | AO36: ='T & M Borba Dairy'!L34 -> 0 | AP36: ='Oslo Dairy'!L34 -> 0 | AQ36: ='Kronberg Facility'!L34 -> 0 | AR36: ='Ken Van Foeken Dairy'!L34 -> 0 | AS36: ='Amaral Dairy Farms'!L34 -> 0 | AT36: ='B_6 Dairy'!L34 -> 0 | AU36: ='6D Dores Dairy'!L34 -> 0 | AV36: ='Fanelli Dairy'!L34 -> 0 | AW36: ='Joao Sousa Dairy'!L34 -> 0 | AX36: ='Vierra Dairy Farms #2'!L34 -> 0 | AY36: ='Michael Brasil Dairy'!L34 -> 0 | AZ36: ='Anchor J Dairy'!L34 -> 0 | BA36: ='Oliveira Dairy'!L34 -> 0 | BB36: ='Souza Bros Dairy'!L34 -> 0 | BC36: ='Miguel Family Dairy'!L34 -> 0 | BD36: ='Dias Family Dairy'!L34 -> 0 | BE36: ='Empty was A_D Dairy'!L34 -> 0 | BF36: ='Michael Brasil Dairy #2'!L34 -> 0 | BG36: ='F & A Lemos Dairy'!L34 -> 0 | BH36: ='Alves & Son Dairy #2'!L34 -> 0 | BI36: ='Golf Link RanchesLLC'!L34 -> 0 | BJ36: ='Triple M Jerseys'!L34 -> 0 | BK36: ='Jose & Teresa Soares Dairy'!L34 -> 0 | BL36: ='MachadoGabriel&SonsDairy'!L34 -> 0 | BM36: ='Hawkins Ranch'!L34 -> 0 | BN36: ='Silva Dairy Farms #3B'!L34 -> 0 | BO36: =AhlemFarmsPartnership!L34 -> 0 | BP36: ='Vierra Dairy Farms #4'!L34 -> 0 | BQ36: ='CaliforniaDairyFarms LLC'!L34 -> 0 | BR36: ='Larry Peterson Dairy'!L34 -> 0 | BS36: ='Joe Egli&Sons Dairy'!L34 -> 0 | BT36: ='CMA Livestock #2'!L34 -> 0 | BU36: ='Valentine Dairy'!L34 -> 0 | BV36: ='CMC Jerseys LLC'!L34 -> 0 | BW36: ='Fanelli_Fanelli Brothers'!L34 -> 0 | BX36: ='Martins Bros Dairy'!L34 -> 0 | BY36: ='Gomes Heifer Ranch'!L34 -> 0 | BZ36: ='Ed Hirdes Dairy'!B36 -> 0 | CA36: ='Dematos Dairy'!L34 -> 0 | CB36: ='Carlos Estacio&Sons Dairy'!L34 -> 0 | CC36: ='Live Oak Dairy G'!L34 -> 0 | CD36: ='Verissimo Facility'!L34 -> 0 | CE36: ='Double Cross Dairy'!L34 -> 0 | CF36: ='Double Cross #4'!L34 -> 0 | CG36: ='King Dairy'!L34 -> 0 | CH36: ='Vieira Livestock'!L34 -> 0 | CI36: ='AldenPeterson&SonsDairy Inc.'!L34 -> 0 | CJ36: ='John Nunes Dairy #3'!L34 -> 0 | CK36: ='Roestar Dairy'!L34 -> 0 | CL36: ='Luis M. Azevedo Dairy'!L34 -> 0 | CM36: ='Arlinda Holsteins'!L34 -> 0 | CN36: ='Robert Gioletti & Sons Dairy'!L34 -> 0 | CO36: ='Carl Vieira Dairy'!L34 -> 0 | CP36: ='John Brasil & Sons Dairy'!L34 -> 0 | CQ36: ='John Brasil Dairy #3'!L34 -> 0 | CR36: ='KMA Dairy'!L34 -> 0 | CS36: ='Sallaberry Ranch'!L34 -> 0 | CT36: ='Alfred C Nunes Dairy'!L34 -> 0 | CU36: ='Jim Vieira & Son Dairy'!L34 -> 0 | CV36: ='Ehrlich Dairy'!L34 -> 0 | CW36: ='D&A Brasil Facility'!B36 -> 0 | CX36: ='Silva''s Holsteins'!B36 -> 0 | CY36: ='G J Silva #3'!B36 -> 0 | CZ36: ='Jim Vieira and Son Dairy #2'!L34 -> 0 | DA36: ='Johal Dairy'!L34 -> 0 | DB36: ='A & G Azevedo Dairy'!L34 -> 0 | DC36: ='Gentle Breezes Dairy'!L34 -> 0 | DD36: ='Joe Sousa Jr Dairy'!L34 -> 0 | DE36: ='John Brasil Heifers'!L34 -> 0 | DF36: ='MHF Dairy'!L34 -> 0 | DG36: ='Brindiero&DanbomDairyFarms'!L34 -> 0 | DH36: ='A&C Machado Dairy #2'!L34 -> 0 | DI36: ='J & J Toste DairyInc.'!L34 -> 0 | DJ36: ='Bar Vee DairyInc.'!L34 -> 0 | DK36: ='Railside Jersey FarmsLLC'!L34 -> 0 | DL36: ='Manuel Azevedo Dairy'!L34 -> 0 | DM36: ='Sousa Family Dairy'!L34 -> 0 | DN36: ='UC Davis Animal Science Dairy'!L34 -> 0 | DO36: ='Garcia''s Registered Jerseys'!L34 -> 0 | DP36: ='Lucio Corral Cattle'!L34 -> 0 | DQ36: ='Wickstrom Dairy Inc'!B36 -> 0 | DR36: ='Sam Kooistra Dairy'!L34 -> 0 | DS36: ='Vitorino & Sons Dairy'!L34 -> 0 | DT36: ='Valley Cross Dairy'!L34 -> 0 | DU36: ='John Brasil & Sons Dairy #2'!L34 -> 0 | DV36: ='Pepper Dairy'!L34 -> 0 | DW36: ='Clauss Dairy Farms'!L34 -> 0 | DX36: ='Dairy Central Heifers'!L34 -> 0 | DY36: ='Yosemite Jersey Dairy'!L34 -> 0 | DZ36: ='Sunwest Jersey Dairy'!L34 -> 0 | EA36: ='N & C Silveira Dairy'!L34 -> 0 | EB36: ='Nyman Brothers Dairy'!L34 -> 0 | EC36: ='Broder Farms'!L34 -> 0 | ED36: ='Borba Dairy Farms'!L34 -> 0 | EE36: ='Charles Ahlem Ranch'!L34 -> 0 | EF36: ='James Ahlem Dairy'!L34 -> 0 | EG36: ='Nylund Dairy Farms'!L34 -> 0 | EH36: ='Vierra Ranch Dairy'!L34 -> 0 | EI36: ='Joe O Rocha Dairy Inc.'!L34 -> 0 | EJ36: ='Alves & Son Dairy'!L34 -> 0 | EK36: ='3A Teixeira Dairy'!L34 -> 0 | EL36: ='Denizma_Bud Postma Dairy'!L34 -> 0 | EM36: ='Couco Creek Dairy'!L34 -> 0 | EN36: ='Clausen Dairy'!L34 -> 0
